Workbook
Name Price: 'Valuation'!$D$194
Name AsOfQuarter: 'Valuation'!$D$195
Name Shares: 'Valuation'!$D$196
Name SharesDiluted: 'Valuation'!$D$197
Name NetDebt: 'Valuation'!$D$198
Name Base_EBITDA: 'Valuation'!$D$199
Name Adj_EBITDA: 'Valuation'!$D$200
Name FCF_TTM: 'Valuation'!$D$201
Name Adj_FCF_TTM: 'Valuation'!$D$202
Name Revenue_TTM: 'Valuation'!$D$203
Name EPS_TTM: 'Valuation'!$D$204
Name Adj_EPS_TTM: 'Valuation'!$D$205
Name BV_PerShare: 'Valuation'!$D$206
Name TBV_PerShare: 'Valuation'!$D$207
Name Target_EV_AdjEBITDA: 'Valuation'!$D$208
Name Target_EV_EBITDA: 'Valuation'!$D$209
Name Target_EV_Yield: 'Valuation'!$D$210
Name Capex_TTM: 'Valuation'!$D$211
Name InterestPaid_TTM: 'Valuation'!$D$212
Name MaintCapexRatio: 'Valuation'!$D$213
Name RecurringCashCosts: 'Valuation'!$D$214
Name WCNormalization: 'Valuation'!$D$215
Name PerShareMode: 'Valuation'!$D$216
Name CompanyOperatingMargin_Latest: 'Valuation'!$M$14
Name OperatingMargin_Latest: 'Valuation'!$M$14
Name CompanyOperatingMargin_TTM: 'Valuation'!$M$15
Name MarketCap: 'Valuation'!$N$194
Name EV: 'Valuation'!$N$195
Name Implied_EV_AdjEBITDA: 'Valuation'!$N$196
Name Implied_EV_EBITDA: 'Valuation'!$N$197
Name FCFF_Proxy_TTM: 'Valuation'!$N$198
Name Implied_FCFF_Yield: 'Valuation'!$N$199
Name Equity_FCF_Yield: 'Valuation'!$N$200
Name OwnerEarnings_TTM: 'Valuation'!$N$201
Name OwnerEarnings_Yield: 'Valuation'!$N$202
Name EqShare_Target_Adj: 'Valuation'!$N$203
Name EqShare_Target_EV: 'Valuation'!$N$204
Name EqShare_Target_Yield: 'Valuation'!$N$205
Name AutoImpliedGT: 'Valuation'!$R$234
Name ImpliedGT_WACC: 'Valuation'!$P$223:$P$230
Name ImpliedGT_Output: 'Valuation'!$Q$223:$Q$230
Name ImpliedGT_Status: 'Valuation'!$S$223:$S$230
Name calculation_history_quarterly_rows: 'History_Q'!$A$2
Name summary_company_description: 'SUMMARY'!$A$3
Name summary_key_advantage: 'SUMMARY'!$A$7
Name summary_strategic_context: 'SUMMARY'!$A$5
Name summary_revenue_stream_rows: 'SUMMARY'!$A$9
Name summary_segment_model: 'SUMMARY'!$A$13
Name summary_key_risks: 'SUMMARY'!$A$17
Name summary_wrong_if: 'SUMMARY'!$A$23
Name summary_as_of_quarter: 'SUMMARY'!$B$26
Name summary_latest_net_income: 'SUMMARY'!$B$30
Name summary_net_leverage: 'SUMMARY'!$B$41
Name valuation_guidance_current_primary_rows: 'Valuation'!$O$9
Name valuation_guidance_historical_rows: 'Valuation'!$O$29
Name valuation_guidance_current_secondary_rows: 'Valuation'!$O$16
Name valuation_thesis_debate_rows: 'Valuation'!$O$51
Name bs_segment_quarterly_rows: 'BS_Segments'!$A$61
Name bs_segment_annual_rows: 'BS_Segments'!$A$72
Name od_watchlist_rows: 'Operating_Drivers'!$A$6

Sheet SUMMARY
A1: SUMMARY
A2: What the company does
A4: Current strategic context
A6: Key competitive advantage
A12: Operating model per segment
A16: Key dependencies (3-5)
A22: What would make me wrong
A25: Key Financials
A26: As of quarter
A27: Revenue TTM ($m) | B27: =IFERROR(IF(OR($B$26="",COUNTIF('Valuation'!$B$6:$M$6,$B$26)<>1,NOT(ISNUMBER(INDEX('Valuation'!$B$10:$M$10,1,MATCH($B$26,'Valuation'!$B$6:$M$6,0))))),"",INDEX('Valuation'!$B$10:$M$10,1,MATCH($B$26,'Valuation'!$B$6:$M$6,0))),"")
A28: Revenue, latest quarter ($m)
A29: Revenue growth YoY, latest quarter (%) | B29: =IFERROR(IF(OR($B$26="",COUNTIF('Valuation'!$B$6:$M$6,$B$26)<>1,NOT(ISNUMBER(INDEX('Valuation'!$B$11:$M$11,1,MATCH($B$26,'Valuation'!$B$6:$M$6,0))))),"",INDEX('Valuation'!$B$11:$M$11,1,MATCH($B$26,'Valuation'!$B$6:$M$6,0))),"")
A30: Net income, latest quarter ($m)
A31: Net income growth YoY, latest quarter (%) | B31: =IFERROR(IF(OR($B$26="",COUNTIF('Valuation'!$B$6:$M$6,$B$26)<>1,NOT(ISNUMBER(INDEX('Valuation'!$B$38:$M$38,1,MATCH($B$26,'Valuation'!$B$6:$M$6,0))))),"",INDEX('Valuation'!$B$38:$M$38,1,MATCH($B$26,'Valuation'!$B$6:$M$6,0))),"")
A32: GAAP diluted EPS ($/share) | B32: =IFERROR(IF(OR($B$26="",COUNTIF('Valuation'!$B$6:$M$6,$B$26)<>1,NOT(ISNUMBER(INDEX('Valuation'!$B$107:$M$107,1,MATCH($B$26,'Valuation'!$B$6:$M$6,0))))),"",INDEX('Valuation'!$B$107:$M$107,1,MATCH($B$26,'Valuation'!$B$6:$M$6,0))),"")
A33: GAAP diluted EPS growth YoY (%) | B33: =IFERROR(IF(OR($B$26="",COUNTIF('Valuation'!$B$6:$M$6,$B$26)<>1,NOT(ISNUMBER(INDEX('Valuation'!$B$108:$M$108,1,MATCH($B$26,'Valuation'!$B$6:$M$6,0))))),"",INDEX('Valuation'!$B$108:$M$108,1,MATCH($B$26,'Valuation'!$B$6:$M$6,0))),"")
A34: Total debt, latest quarter ($m) | B34: N/A
A35: Debt-to-equity, latest quarter (x) | B35: N/A
A36: FCF TTM ($m) | B36: =IFERROR(IF(OR($B$26="",COUNTIF('Valuation'!$B$6:$M$6,$B$26)<>1,NOT(ISNUMBER(INDEX('Valuation'!$B$49:$M$49,1,MATCH($B$26,'Valuation'!$B$6:$M$6,0))))),"",INDEX('Valuation'!$B$49:$M$49,1,MATCH($B$26,'Valuation'!$B$6:$M$6,0))),"")
A37: FCF growth YoY, latest quarter (%) | B37: =IFERROR(IF(OR($B$26="",COUNTIF('Valuation'!$B$6:$M$6,$B$26)<>1,MATCH($B$26,'Valuation'!$B$6:$M$6,0)<=4,NOT(ISNUMBER(INDEX('Valuation'!$B$48:$M$48,1,MATCH($B$26,'Valuation'!$B$6:$M$6,0)))),NOT(ISNUMBER(INDEX('Valuation'!$B$47:$M$47,1,MATCH($B$26,'Valuation'!$B$6:$M$6,0)-4))),INDEX('Valuation'!$B$47:$M$47,1,MATCH($B$26,'Valuation'!$B$6:$M$6,0)-4)=0),"",INDEX('Valuation'!$B$48:$M$48,1,MATCH($B$26,'Valuation'!$B$6:$M$6,0))/ABS(INDEX('Valuation'!$B$47:$M$47,1,MATCH($B$26,'Valuation'!$B$6:$M$6,0)-4))),"")
A38: P/E, price-linked (x) | B38: N/A
A39: P/S, price-linked (x) | B39: N/A
A40: Leverage / Liquidity
A41: Net leverage (x)
A42: Interest coverage, P&L TTM (x) | B42: =IFERROR(IF(OR($B$26="",COUNTIF('Valuation'!$B$6:$M$6,$B$26)<>1,NOT(ISNUMBER(INDEX('Valuation'!$B$88:$M$88,1,MATCH($B$26,'Valuation'!$B$6:$M$6,0))))),"",INDEX('Valuation'!$B$88:$M$88,1,MATCH($B$26,'Valuation'!$B$6:$M$6,0))),"")
A43: Interest coverage, cash TTM (x) | B43: N/A
A44: Revolver availability ($m)
A45: Total liquidity ($m)

Sheet Valuation
A1: Scale | B1: $m | C1: <=-15% | D1: -15..-5 | E1: -5..+5 | F1: +5..+15 | G1: >=+15%
A2: Values scaled to $m unless %
A3: Valuation
A4: QA: Revenue, EBITDA, CFO, Capex, Cash
B5: Actuals
A6: Quarter
A7: Operating | O7: Current guidance
A8: Top line | O8: Metric | Q8: Stated in | R8: Applies to | S8: Guidance | X8: Unit | Y8: Published | Z8: Evidence | AA8: Role / source status
A9: Revenue
A10: Revenue (TTM) | B10: =IF(OR(B$6="",COUNTIFS(History_Q!$C$2:$C$1000,"revenue",History_Q!$B$2:$B$1000,">="&((SUMIFS(History_Q!$B$2:$B$1000,History_Q!$A$2:$A$1000,B$6,History_Q!$C$2:$C$1000,"revenue"))-3),History_Q!$B$2:$B$1000,"<="&(SUMIFS(History_Q!$B$2:$B$1000,History_Q!$A$2:$A$1000,B$6,History_Q!$C$2:$C$1000,"revenue")),History_Q!$E$2:$E$1000,"$m",History_Q!$G$2:$G$1000,"populated")<>4,_xlfn.MAXIFS(History_Q!$B$2:$B$1000,History_Q!$C$2:$C$1000,"revenue",History_Q!$B$2:$B$1000,">="&((SUMIFS(History_Q!$B$2:$B$1000,History_Q!$A$2:$A$1000,B$6,History_Q!$C$2:$C$1000,"revenue"))-3),History_Q!$B$2:$B$1000,"<="&(SUMIFS(History_Q!$B$2:$B$1000,History_Q!$A$2:$A$1000,B$6,History_Q!$C$2:$C$1000,"revenue")),History_Q!$E$2:$E$1000,"$m",History_Q!$G$2:$G$1000,"populated")-_xlfn.MINIFS(History_Q!$B$2:$B$1000,History_Q!$C$2:$C$1000,"revenue",History_Q!$B$2:$B$1000,">="&((SUMIFS(History_Q!$B$2:$B$1000,History_Q!$A$2:$A$1000,B$6,History_Q!$C$2:$C$1000,"revenue"))-3),History_Q!$B$2:$B$1000,"<="&(SUMIFS(History_Q!$B$2:$B$1000,History_Q!$A$2:$A$1000,B$6,History_Q!$C$2:$C$1000,"revenue")),History_Q!$E$2:$E$1000,"$m",History_Q!$G$2:$G$1000,"populated")<>3),"",SUMIFS(History_Q!$D$2:$D$1000,History_Q!$C$2:$C$1000,"revenue",History_Q!$B$2:$B$1000,">="&((SUMIFS(History_Q!$B$2:$B$1000,History_Q!$A$2:$A$1000,B$6,History_Q!$C$2:$C$1000,"revenue"))-3),History_Q!$B$2:$B$1000,"<="&(SUMIFS(History_Q!$B$2:$B$1000,History_Q!$A$2:$A$1000,B$6,History_Q!$C$2:$C$1000,"revenue")),History_Q!$E$2:$E$1000,"$m",History_Q!$G$2:$G$1000,"populated")) | C10: =IF(OR(C$6="",COUNTIFS(History_Q!$C$2:$C$1000,"revenue",History_Q!$B$2:$B$1000,">="&((SUMIFS(History_Q!$B$2:$B$1000,History_Q!$A$2:$A$1000,C$6,History_Q!$C$2:$C$1000,"revenue"))-3),History_Q!$B$2:$B$1000,"<="&(SUMIFS(History_Q!$B$2:$B$1000,History_Q!$A$2:$A$1000,C$6,History_Q!$C$2:$C$1000,"revenue")),History_Q!$E$2:$E$1000,"$m",History_Q!$G$2:$G$1000,"populated")<>4,_xlfn.MAXIFS(History_Q!$B$2:$B$1000,History_Q!$C$2:$C$1000,"revenue",History_Q!$B$2:$B$1000,">="&((SUMIFS(History_Q!$B$2:$B$1000,History_Q!$A$2:$A$1000,C$6,History_Q!$C$2:$C$1000,"revenue"))-3),History_Q!$B$2:$B$1000,"<="&(SUMIFS(History_Q!$B$2:$B$1000,History_Q!$A$2:$A$1000,C$6,History_Q!$C$2:$C$1000,"revenue")),History_Q!$E$2:$E$1000,"$m",History_Q!$G$2:$G$1000,"populated")-_xlfn.MINIFS(History_Q!$B$2:$B$1000,History_Q!$C$2:$C$1000,"revenue",History_Q!$B$2:$B$1000,">="&((SUMIFS(History_Q!$B$2:$B$1000,History_Q!$A$2:$A$1000,C$6,History_Q!$C$2:$C$1000,"revenue"))-3),History_Q!$B$2:$B$1000,"<="&(SUMIFS(History_Q!$B$2:$B$1000,History_Q!$A$2:$A$1000,C$6,History_Q!$C$2:$C$1000,"revenue")),History_Q!$E$2:$E$1000,"$m",History_Q!$G$2:$G$1000,"populated")<>3),"",SUMIFS(History_Q!$D$2:$D$1000,History_Q!$C$2:$C$1000,"revenue",History_Q!$B$2:$B$1000,">="&((SUMIFS(History_Q!$B$2:$B$1000,History_Q!$A$2:$A$1000,C$6,History_Q!$C$2:$C$1000,"revenue"))-3),History_Q!$B$2:$B$1000,"<="&(SUMIFS(History_Q!$B$2:$B$1000,History_Q!$A$2:$A$1000,C$6,History_Q!$C$2:$C$1000,"revenue")),History_Q!$E$2:$E$1000,"$m",History_Q!$G$2:$G$1000,"populated")) | D10: =IF(OR(D$6="",COUNTIFS(History_Q!$C$2:$C$1000,"revenue",History_Q!$B$2:$B$1000,">="&((SUMIFS(History_Q!$B$2:$B$1000,History_Q!$A$2:$A$1000,D$6,History_Q!$C$2:$C$1000,"revenue"))-3),History_Q!$B$2:$B$1000,"<="&(SUMIFS(History_Q!$B$2:$B$1000,History_Q!$A$2:$A$1000,D$6,History_Q!$C$2:$C$1000,"revenue")),History_Q!$E$2:$E$1000,"$m",History_Q!$G$2:$G$1000,"populated")<>4,_xlfn.MAXIFS(History_Q!$B$2:$B$1000,History_Q!$C$2:$C$1000,"revenue",History_Q!$B$2:$B$1000,">="&((SUMIFS(History_Q!$B$2:$B$1000,History_Q!$A$2:$A$1000,D$6,History_Q!$C$2:$C$1000,"revenue"))-3),History_Q!$B$2:$B$1000,"<="&(SUMIFS(History_Q!$B$2:$B$1000,History_Q!$A$2:$A$1000,D$6,History_Q!$C$2:$C$1000,"revenue")),History_Q!$E$2:$E$1000,"$m",History_Q!$G$2:$G$1000,"populated")-_xlfn.MINIFS(History_Q!$B$2:$B$1000,History_Q!$C$2:$C$1000,"revenue",History_Q!$B$2:$B$1000,">="&((SUMIFS(History_Q!$B$2:$B$1000,History_Q!$A$2:$A$1000,D$6,History_Q!$C$2:$C$1000,"revenue"))-3),History_Q!$B$2:$B$1000,"<="&(SUMIFS(History_Q!$B$2:$B$1000,History_Q!$A$2:$A$1000,D$6,History_Q!$C$2:$C$1000,"revenue")),History_Q!$E$2:$E$1000,"$m",History_Q!$G$2:$G$1000,"populated")<>3),"",SUMIFS(History_Q!$D$2:$D$1000,History_Q!$C$2:$C$1000,"revenue",History_Q!$B$2:$B$1000,">="&((SUMIFS(History_Q!$B$2:$B$1000,History_Q!$A$2:$A$1000,D$6,History_Q!$C$2:$C$1000,"revenue"))-3),History_Q!$B$2:$B$1000,"<="&(SUMIFS(History_Q!$B$2:$B$1000,History_Q!$A$2:$A$1000,D$6,History_Q!$C$2:$C$1000,"revenue")),History_Q!$E$2:$E$1000,"$m",History_Q!$G$2:$G$1000,"populated")) | E10: =IF(OR(E$6="",COUNTIFS(History_Q!$C$2:$C$1000,"revenue",History_Q!$B$2:$B$1000,">="&((SUMIFS(History_Q!$B$2:$B$1000,History_Q!$A$2:$A$1000,E$6,History_Q!$C$2:$C$1000,"revenue"))-3),History_Q!$B$2:$B$1000,"<="&(SUMIFS(History_Q!$B$2:$B$1000,History_Q!$A$2:$A$1000,E$6,History_Q!$C$2:$C$1000,"revenue")),History_Q!$E$2:$E$1000,"$m",History_Q!$G$2:$G$1000,"populated")<>4,_xlfn.MAXIFS(History_Q!$B$2:$B$1000,History_Q!$C$2:$C$1000,"revenue",History_Q!$B$2:$B$1000,">="&((SUMIFS(History_Q!$B$2:$B$1000,History_Q!$A$2:$A$1000,E$6,History_Q!$C$2:$C$1000,"revenue"))-3),History_Q!$B$2:$B$1000,"<="&(SUMIFS(History_Q!$B$2:$B$1000,History_Q!$A$2:$A$1000,E$6,History_Q!$C$2:$C$1000,"revenue")),History_Q!$E$2:$E$1000,"$m",History_Q!$G$2:$G$1000,"populated")-_xlfn.MINIFS(History_Q!$B$2:$B$1000,History_Q!$C$2:$C$1000,"revenue",History_Q!$B$2:$B$1000,">="&((SUMIFS(History_Q!$B$2:$B$1000,History_Q!$A$2:$A$1000,E$6,History_Q!$C$2:$C$1000,"revenue"))-3),History_Q!$B$2:$B$1000,"<="&(SUMIFS(History_Q!$B$2:$B$1000,History_Q!$A$2:$A$1000,E$6,History_Q!$C$2:$C$1000,"revenue")),History_Q!$E$2:$E$1000,"$m",History_Q!$G$2:$G$1000,"populated")<>3),"",SUMIFS(History_Q!$D$2:$D$1000,History_Q!$C$2:$C$1000,"revenue",History_Q!$B$2:$B$1000,">="&((SUMIFS(History_Q!$B$2:$B$1000,History_Q!$A$2:$A$1000,E$6,History_Q!$C$2:$C$1000,"revenue"))-3),History_Q!$B$2:$B$1000,"<="&(SUMIFS(History_Q!$B$2:$B$1000,History_Q!$A$2:$A$1000,E$6,History_Q!$C$2:$C$1000,"revenue")),History_Q!$E$2:$E$1000,"$m",History_Q!$G$2:$G$1000,"populated")) | F10: =IF(OR(F$6="",COUNTIFS(History_Q!$C$2:$C$1000,"revenue",History_Q!$B$2:$B$1000,">="&((SUMIFS(History_Q!$B$2:$B$1000,History_Q!$A$2:$A$1000,F$6,History_Q!$C$2:$C$1000,"revenue"))-3),History_Q!$B$2:$B$1000,"<="&(SUMIFS(History_Q!$B$2:$B$1000,History_Q!$A$2:$A$1000,F$6,History_Q!$C$2:$C$1000,"revenue")),History_Q!$E$2:$E$1000,"$m",History_Q!$G$2:$G$1000,"populated")<>4,_xlfn.MAXIFS(History_Q!$B$2:$B$1000,History_Q!$C$2:$C$1000,"revenue",History_Q!$B$2:$B$1000,">="&((SUMIFS(History_Q!$B$2:$B$1000,History_Q!$A$2:$A$1000,F$6,History_Q!$C$2:$C$1000,"revenue"))-3),History_Q!$B$2:$B$1000,"<="&(SUMIFS(History_Q!$B$2:$B$1000,History_Q!$A$2:$A$1000,F$6,History_Q!$C$2:$C$1000,"revenue")),History_Q!$E$2:$E$1000,"$m",History_Q!$G$2:$G$1000,"populated")-_xlfn.MINIFS(History_Q!$B$2:$B$1000,History_Q!$C$2:$C$1000,"revenue",History_Q!$B$2:$B$1000,">="&((SUMIFS(History_Q!$B$2:$B$1000,History_Q!$A$2:$A$1000,F$6,History_Q!$C$2:$C$1000,"revenue"))-3),History_Q!$B$2:$B$1000,"<="&(SUMIFS(History_Q!$B$2:$B$1000,History_Q!$A$2:$A$1000,F$6,History_Q!$C$2:$C$1000,"revenue")),History_Q!$E$2:$E$1000,"$m",History_Q!$G$2:$G$1000,"populated")<>3),"",SUMIFS(History_Q!$D$2:$D$1000,History_Q!$C$2:$C$1000,"revenue",History_Q!$B$2:$B$1000,">="&((SUMIFS(History_Q!$B$2:$B$1000,History_Q!$A$2:$A$1000,F$6,History_Q!$C$2:$C$1000,"revenue"))-3),History_Q!$B$2:$B$1000,"<="&(SUMIFS(History_Q!$B$2:$B$1000,History_Q!$A$2:$A$1000,F$6,History_Q!$C$2:$C$1000,"revenue")),History_Q!$E$2:$E$1000,"$m",History_Q!$G$2:$G$1000,"populated")) | G10: =IF(OR(G$6="",COUNTIFS(History_Q!$C$2:$C$1000,"revenue",History_Q!$B$2:$B$1000,">="&((SUMIFS(History_Q!$B$2:$B$1000,History_Q!$A$2:$A$1000,G$6,History_Q!$C$2:$C$1000,"revenue"))-3),History_Q!$B$2:$B$1000,"<="&(SUMIFS(History_Q!$B$2:$B$1000,History_Q!$A$2:$A$1000,G$6,History_Q!$C$2:$C$1000,"revenue")),History_Q!$E$2:$E$1000,"$m",History_Q!$G$2:$G$1000,"populated")<>4,_xlfn.MAXIFS(History_Q!$B$2:$B$1000,History_Q!$C$2:$C$1000,"revenue",History_Q!$B$2:$B$1000,">="&((SUMIFS(History_Q!$B$2:$B$1000,History_Q!$A$2:$A$1000,G$6,History_Q!$C$2:$C$1000,"revenue"))-3),History_Q!$B$2:$B$1000,"<="&(SUMIFS(History_Q!$B$2:$B$1000,History_Q!$A$2:$A$1000,G$6,History_Q!$C$2:$C$1000,"revenue")),History_Q!$E$2:$E$1000,"$m",History_Q!$G$2:$G$1000,"populated")-_xlfn.MINIFS(History_Q!$B$2:$B$1000,History_Q!$C$2:$C$1000,"revenue",History_Q!$B$2:$B$1000,">="&((SUMIFS(History_Q!$B$2:$B$1000,History_Q!$A$2:$A$1000,G$6,History_Q!$C$2:$C$1000,"revenue"))-3),History_Q!$B$2:$B$1000,"<="&(SUMIFS(History_Q!$B$2:$B$1000,History_Q!$A$2:$A$1000,G$6,History_Q!$C$2:$C$1000,"revenue")),History_Q!$E$2:$E$1000,"$m",History_Q!$G$2:$G$1000,"populated")<>3),"",SUMIFS(History_Q!$D$2:$D$1000,History_Q!$C$2:$C$1000,"revenue",History_Q!$B$2:$B$1000,">="&((SUMIFS(History_Q!$B$2:$B$1000,History_Q!$A$2:$A$1000,G$6,History_Q!$C$2:$C$1000,"revenue"))-3),History_Q!$B$2:$B$1000,"<="&(SUMIFS(History_Q!$B$2:$B$1000,History_Q!$A$2:$A$1000,G$6,History_Q!$C$2:$C$1000,"revenue")),History_Q!$E$2:$E$1000,"$m",History_Q!$G$2:$G$1000,"populated")) | H10: =IF(OR(H$6="",COUNTIFS(History_Q!$C$2:$C$1000,"revenue",History_Q!$B$2:$B$1000,">="&((SUMIFS(History_Q!$B$2:$B$1000,History_Q!$A$2:$A$1000,H$6,History_Q!$C$2:$C$1000,"revenue"))-3),History_Q!$B$2:$B$1000,"<="&(SUMIFS(History_Q!$B$2:$B$1000,History_Q!$A$2:$A$1000,H$6,History_Q!$C$2:$C$1000,"revenue")),History_Q!$E$2:$E$1000,"$m",History_Q!$G$2:$G$1000,"populated")<>4,_xlfn.MAXIFS(History_Q!$B$2:$B$1000,History_Q!$C$2:$C$1000,"revenue",History_Q!$B$2:$B$1000,">="&((SUMIFS(History_Q!$B$2:$B$1000,History_Q!$A$2:$A$1000,H$6,History_Q!$C$2:$C$1000,"revenue"))-3),History_Q!$B$2:$B$1000,"<="&(SUMIFS(History_Q!$B$2:$B$1000,History_Q!$A$2:$A$1000,H$6,History_Q!$C$2:$C$1000,"revenue")),History_Q!$E$2:$E$1000,"$m",History_Q!$G$2:$G$1000,"populated")-_xlfn.MINIFS(History_Q!$B$2:$B$1000,History_Q!$C$2:$C$1000,"revenue",History_Q!$B$2:$B$1000,">="&((SUMIFS(History_Q!$B$2:$B$1000,History_Q!$A$2:$A$1000,H$6,History_Q!$C$2:$C$1000,"revenue"))-3),History_Q!$B$2:$B$1000,"<="&(SUMIFS(History_Q!$B$2:$B$1000,History_Q!$A$2:$A$1000,H$6,History_Q!$C$2:$C$1000,"revenue")),History_Q!$E$2:$E$1000,"$m",History_Q!$G$2:$G$1000,"populated")<>3),"",SUMIFS(History_Q!$D$2:$D$1000,History_Q!$C$2:$C$1000,"revenue",History_Q!$B$2:$B$1000,">="&((SUMIFS(History_Q!$B$2:$B$1000,History_Q!$A$2:$A$1000,H$6,History_Q!$C$2:$C$1000,"revenue"))-3),History_Q!$B$2:$B$1000,"<="&(SUMIFS(History_Q!$B$2:$B$1000,History_Q!$A$2:$A$1000,H$6,History_Q!$C$2:$C$1000,"revenue")),History_Q!$E$2:$E$1000,"$m",History_Q!$G$2:$G$1000,"populated")) | I10: =IF(OR(I$6="",COUNTIFS(History_Q!$C$2:$C$1000,"revenue",History_Q!$B$2:$B$1000,">="&((SUMIFS(History_Q!$B$2:$B$1000,History_Q!$A$2:$A$1000,I$6,History_Q!$C$2:$C$1000,"revenue"))-3),History_Q!$B$2:$B$1000,"<="&(SUMIFS(History_Q!$B$2:$B$1000,History_Q!$A$2:$A$1000,I$6,History_Q!$C$2:$C$1000,"revenue")),History_Q!$E$2:$E$1000,"$m",History_Q!$G$2:$G$1000,"populated")<>4,_xlfn.MAXIFS(History_Q!$B$2:$B$1000,History_Q!$C$2:$C$1000,"revenue",History_Q!$B$2:$B$1000,">="&((SUMIFS(History_Q!$B$2:$B$1000,History_Q!$A$2:$A$1000,I$6,History_Q!$C$2:$C$1000,"revenue"))-3),History_Q!$B$2:$B$1000,"<="&(SUMIFS(History_Q!$B$2:$B$1000,History_Q!$A$2:$A$1000,I$6,History_Q!$C$2:$C$1000,"revenue")),History_Q!$E$2:$E$1000,"$m",History_Q!$G$2:$G$1000,"populated")-_xlfn.MINIFS(History_Q!$B$2:$B$1000,History_Q!$C$2:$C$1000,"revenue",History_Q!$B$2:$B$1000,">="&((SUMIFS(History_Q!$B$2:$B$1000,History_Q!$A$2:$A$1000,I$6,History_Q!$C$2:$C$1000,"revenue"))-3),History_Q!$B$2:$B$1000,"<="&(SUMIFS(History_Q!$B$2:$B$1000,History_Q!$A$2:$A$1000,I$6,History_Q!$C$2:$C$1000,"revenue")),History_Q!$E$2:$E$1000,"$m",History_Q!$G$2:$G$1000,"populated")<>3),"",SUMIFS(History_Q!$D$2:$D$1000,History_Q!$C$2:$C$1000,"revenue",History_Q!$B$2:$B$1000,">="&((SUMIFS(History_Q!$B$2:$B$1000,History_Q!$A$2:$A$1000,I$6,History_Q!$C$2:$C$1000,"revenue"))-3),History_Q!$B$2:$B$1000,"<="&(SUMIFS(History_Q!$B$2:$B$1000,History_Q!$A$2:$A$1000,I$6,History_Q!$C$2:$C$1000,"revenue")),History_Q!$E$2:$E$1000,"$m",History_Q!$G$2:$G$1000,"populated")) | ... M10: =IF(OR(M$6="",COUNTIFS(History_Q!$C$2:$C$1000,"revenue",History_Q!$B$2:$B$1000,">="&((SUMIFS(History_Q!$B$2:$B$1000,History_Q!$A$2:$A$1000,M$6,History_Q!$C$2:$C$1000,"revenue"))-3),History_Q!$B$2:$B$1000,"<="&(SUMIFS(History_Q!$B$2:$B$1000,History_Q!$A$2:$A$1000,M$6,History_Q!$C$2:$C$1000,"revenue")),History_Q!$E$2:$E$1000,"$m",History_Q!$G$2:$G$1000,"populated")<>4,_xlfn.MAXIFS(History_Q!$B$2:$B$1000,History_Q!$C$2:$C$1000,"revenue",History_Q!$B$2:$B$1000,">="&((SUMIFS(History_Q!$B$2:$B$1000,History_Q!$A$2:$A$1000,M$6,History_Q!$C$2:$C$1000,"revenue"))-3),History_Q!$B$2:$B$1000,"<="&(SUMIFS(History_Q!$B$2:$B$1000,History_Q!$A$2:$A$1000,M$6,History_Q!$C$2:$C$1000,"revenue")),History_Q!$E$2:$E$1000,"$m",History_Q!$G$2:$G$1000,"populated")-_xlfn.MINIFS(History_Q!$B$2:$B$1000,History_Q!$C$2:$C$1000,"revenue",History_Q!$B$2:$B$1000,">="&((SUMIFS(History_Q!$B$2:$B$1000,History_Q!$A$2:$A$1000,M$6,History_Q!$C$2:$C$1000,"revenue"))-3),History_Q!$B$2:$B$1000,"<="&(SUMIFS(History_Q!$B$2:$B$1000,History_Q!$A$2:$A$1000,M$6,History_Q!$C$2:$C$1000,"revenue")),History_Q!$E$2:$E$1000,"$m",History_Q!$G$2:$G$1000,"populated")<>3),"",SUMIFS(History_Q!$D$2:$D$1000,History_Q!$C$2:$C$1000,"revenue",History_Q!$B$2:$B$1000,">="&((SUMIFS(History_Q!$B$2:$B$1000,History_Q!$A$2:$A$1000,M$6,History_Q!$C$2:$C$1000,"revenue"))-3),History_Q!$B$2:$B$1000,"<="&(SUMIFS(History_Q!$B$2:$B$1000,History_Q!$A$2:$A$1000,M$6,History_Q!$C$2:$C$1000,"revenue")),History_Q!$E$2:$E$1000,"$m",History_Q!$G$2:$G$1000,"populated"))
A11: Revenue YoY % | B11: =IF(OR(B$6="",COUNTIFS(History_Q!$C$2:$C$1000,"revenue",History_Q!$B$2:$B$1000,(SUMIFS(History_Q!$B$2:$B$1000,History_Q!$A$2:$A$1000,B$6,History_Q!$C$2:$C$1000,"revenue")),History_Q!$E$2:$E$1000,"$m",History_Q!$G$2:$G$1000,"populated")<>1,COUNTIFS(History_Q!$C$2:$C$1000,"revenue",History_Q!$B$2:$B$1000,(SUMIFS(History_Q!$B$2:$B$1000,History_Q!$A$2:$A$1000,B$6,History_Q!$C$2:$C$1000,"revenue")-4),History_Q!$E$2:$E$1000,"$m",History_Q!$G$2:$G$1000,"populated")<>1,SUMIFS(History_Q!$D$2:$D$1000,History_Q!$C$2:$C$1000,"revenue",History_Q!$B$2:$B$1000,(SUMIFS(History_Q!$B$2:$B$1000,History_Q!$A$2:$A$1000,B$6,History_Q!$C$2:$C$1000,"revenue")-4),History_Q!$E$2:$E$1000,"$m",History_Q!$G$2:$G$1000,"populated")=0),"",SUMIFS(History_Q!$D$2:$D$1000,History_Q!$C$2:$C$1000,"revenue",History_Q!$B$2:$B$1000,(SUMIFS(History_Q!$B$2:$B$1000,History_Q!$A$2:$A$1000,B$6,History_Q!$C$2:$C$1000,"revenue")),History_Q!$E$2:$E$1000,"$m",History_Q!$G$2:$G$1000,"populated")/SUMIFS(History_Q!$D$2:$D$1000,History_Q!$C$2:$C$1000,"revenue",History_Q!$B$2:$B$1000,(SUMIFS(History_Q!$B$2:$B$1000,History_Q!$A$2:$A$1000,B$6,History_Q!$C$2:$C$1000,"revenue")-4),History_Q!$E$2:$E$1000,"$m",History_Q!$G$2:$G$1000,"populated")-1) | C11: =IF(OR(C$6="",COUNTIFS(History_Q!$C$2:$C$1000,"revenue",History_Q!$B$2:$B$1000,(SUMIFS(History_Q!$B$2:$B$1000,History_Q!$A$2:$A$1000,C$6,History_Q!$C$2:$C$1000,"revenue")),History_Q!$E$2:$E$1000,"$m",History_Q!$G$2:$G$1000,"populated")<>1,COUNTIFS(History_Q!$C$2:$C$1000,"revenue",History_Q!$B$2:$B$1000,(SUMIFS(History_Q!$B$2:$B$1000,History_Q!$A$2:$A$1000,C$6,History_Q!$C$2:$C$1000,"revenue")-4),History_Q!$E$2:$E$1000,"$m",History_Q!$G$2:$G$1000,"populated")<>1,SUMIFS(History_Q!$D$2:$D$1000,History_Q!$C$2:$C$1000,"revenue",History_Q!$B$2:$B$1000,(SUMIFS(History_Q!$B$2:$B$1000,History_Q!$A$2:$A$1000,C$6,History_Q!$C$2:$C$1000,"revenue")-4),History_Q!$E$2:$E$1000,"$m",History_Q!$G$2:$G$1000,"populated")=0),"",SUMIFS(History_Q!$D$2:$D$1000,History_Q!$C$2:$C$1000,"revenue",History_Q!$B$2:$B$1000,(SUMIFS(History_Q!$B$2:$B$1000,History_Q!$A$2:$A$1000,C$6,History_Q!$C$2:$C$1000,"revenue")),History_Q!$E$2:$E$1000,"$m",History_Q!$G$2:$G$1000,"populated")/SUMIFS(History_Q!$D$2:$D$1000,History_Q!$C$2:$C$1000,"revenue",History_Q!$B$2:$B$1000,(SUMIFS(History_Q!$B$2:$B$1000,History_Q!$A$2:$A$1000,C$6,History_Q!$C$2:$C$1000,"revenue")-4),History_Q!$E$2:$E$1000,"$m",History_Q!$G$2:$G$1000,"populated")-1) | D11: =IF(OR(D$6="",COUNTIFS(History_Q!$C$2:$C$1000,"revenue",History_Q!$B$2:$B$1000,(SUMIFS(History_Q!$B$2:$B$1000,History_Q!$A$2:$A$1000,D$6,History_Q!$C$2:$C$1000,"revenue")),History_Q!$E$2:$E$1000,"$m",History_Q!$G$2:$G$1000,"populated")<>1,COUNTIFS(History_Q!$C$2:$C$1000,"revenue",History_Q!$B$2:$B$1000,(SUMIFS(History_Q!$B$2:$B$1000,History_Q!$A$2:$A$1000,D$6,History_Q!$C$2:$C$1000,"revenue")-4),History_Q!$E$2:$E$1000,"$m",History_Q!$G$2:$G$1000,"populated")<>1,SUMIFS(History_Q!$D$2:$D$1000,History_Q!$C$2:$C$1000,"revenue",History_Q!$B$2:$B$1000,(SUMIFS(History_Q!$B$2:$B$1000,History_Q!$A$2:$A$1000,D$6,History_Q!$C$2:$C$1000,"revenue")-4),History_Q!$E$2:$E$1000,"$m",History_Q!$G$2:$G$1000,"populated")=0),"",SUMIFS(History_Q!$D$2:$D$1000,History_Q!$C$2:$C$1000,"revenue",History_Q!$B$2:$B$1000,(SUMIFS(History_Q!$B$2:$B$1000,History_Q!$A$2:$A$1000,D$6,History_Q!$C$2:$C$1000,"revenue")),History_Q!$E$2:$E$1000,"$m",History_Q!$G$2:$G$1000,"populated")/SUMIFS(History_Q!$D$2:$D$1000,History_Q!$C$2:$C$1000,"revenue",History_Q!$B$2:$B$1000,(SUMIFS(History_Q!$B$2:$B$1000,History_Q!$A$2:$A$1000,D$6,History_Q!$C$2:$C$1000,"revenue")-4),History_Q!$E$2:$E$1000,"$m",History_Q!$G$2:$G$1000,"populated")-1) | E11: =IF(OR(E$6="",COUNTIFS(History_Q!$C$2:$C$1000,"revenue",History_Q!$B$2:$B$1000,(SUMIFS(History_Q!$B$2:$B$1000,History_Q!$A$2:$A$1000,E$6,History_Q!$C$2:$C$1000,"revenue")),History_Q!$E$2:$E$1000,"$m",History_Q!$G$2:$G$1000,"populated")<>1,COUNTIFS(History_Q!$C$2:$C$1000,"revenue",History_Q!$B$2:$B$1000,(SUMIFS(History_Q!$B$2:$B$1000,History_Q!$A$2:$A$1000,E$6,History_Q!$C$2:$C$1000,"revenue")-4),History_Q!$E$2:$E$1000,"$m",History_Q!$G$2:$G$1000,"populated")<>1,SUMIFS(History_Q!$D$2:$D$1000,History_Q!$C$2:$C$1000,"revenue",History_Q!$B$2:$B$1000,(SUMIFS(History_Q!$B$2:$B$1000,History_Q!$A$2:$A$1000,E$6,History_Q!$C$2:$C$1000,"revenue")-4),History_Q!$E$2:$E$1000,"$m",History_Q!$G$2:$G$1000,"populated")=0),"",SUMIFS(History_Q!$D$2:$D$1000,History_Q!$C$2:$C$1000,"revenue",History_Q!$B$2:$B$1000,(SUMIFS(History_Q!$B$2:$B$1000,History_Q!$A$2:$A$1000,E$6,History_Q!$C$2:$C$1000,"revenue")),History_Q!$E$2:$E$1000,"$m",History_Q!$G$2:$G$1000,"populated")/SUMIFS(History_Q!$D$2:$D$1000,History_Q!$C$2:$C$1000,"revenue",History_Q!$B$2:$B$1000,(SUMIFS(History_Q!$B$2:$B$1000,History_Q!$A$2:$A$1000,E$6,History_Q!$C$2:$C$1000,"revenue")-4),History_Q!$E$2:$E$1000,"$m",History_Q!$G$2:$G$1000,"populated")-1) | F11: =IF(OR(F$6="",COUNTIFS(History_Q!$C$2:$C$1000,"revenue",History_Q!$B$2:$B$1000,(SUMIFS(History_Q!$B$2:$B$1000,History_Q!$A$2:$A$1000,F$6,History_Q!$C$2:$C$1000,"revenue")),History_Q!$E$2:$E$1000,"$m",History_Q!$G$2:$G$1000,"populated")<>1,COUNTIFS(History_Q!$C$2:$C$1000,"revenue",History_Q!$B$2:$B$1000,(SUMIFS(History_Q!$B$2:$B$1000,History_Q!$A$2:$A$1000,F$6,History_Q!$C$2:$C$1000,"revenue")-4),History_Q!$E$2:$E$1000,"$m",History_Q!$G$2:$G$1000,"populated")<>1,SUMIFS(History_Q!$D$2:$D$1000,History_Q!$C$2:$C$1000,"revenue",History_Q!$B$2:$B$1000,(SUMIFS(History_Q!$B$2:$B$1000,History_Q!$A$2:$A$1000,F$6,History_Q!$C$2:$C$1000,"revenue")-4),History_Q!$E$2:$E$1000,"$m",History_Q!$G$2:$G$1000,"populated")=0),"",SUMIFS(History_Q!$D$2:$D$1000,History_Q!$C$2:$C$1000,"revenue",History_Q!$B$2:$B$1000,(SUMIFS(History_Q!$B$2:$B$1000,History_Q!$A$2:$A$1000,F$6,History_Q!$C$2:$C$1000,"revenue")),History_Q!$E$2:$E$1000,"$m",History_Q!$G$2:$G$1000,"populated")/SUMIFS(History_Q!$D$2:$D$1000,History_Q!$C$2:$C$1000,"revenue",History_Q!$B$2:$B$1000,(SUMIFS(History_Q!$B$2:$B$1000,History_Q!$A$2:$A$1000,F$6,History_Q!$C$2:$C$1000,"revenue")-4),History_Q!$E$2:$E$1000,"$m",History_Q!$G$2:$G$1000,"populated")-1) | G11: =IF(OR(G$6="",COUNTIFS(History_Q!$C$2:$C$1000,"revenue",History_Q!$B$2:$B$1000,(SUMIFS(History_Q!$B$2:$B$1000,History_Q!$A$2:$A$1000,G$6,History_Q!$C$2:$C$1000,"revenue")),History_Q!$E$2:$E$1000,"$m",History_Q!$G$2:$G$1000,"populated")<>1,COUNTIFS(History_Q!$C$2:$C$1000,"revenue",History_Q!$B$2:$B$1000,(SUMIFS(History_Q!$B$2:$B$1000,History_Q!$A$2:$A$1000,G$6,History_Q!$C$2:$C$1000,"revenue")-4),History_Q!$E$2:$E$1000,"$m",History_Q!$G$2:$G$1000,"populated")<>1,SUMIFS(History_Q!$D$2:$D$1000,History_Q!$C$2:$C$1000,"revenue",History_Q!$B$2:$B$1000,(SUMIFS(History_Q!$B$2:$B$1000,History_Q!$A$2:$A$1000,G$6,History_Q!$C$2:$C$1000,"revenue")-4),History_Q!$E$2:$E$1000,"$m",History_Q!$G$2:$G$1000,"populated")=0),"",SUMIFS(History_Q!$D$2:$D$1000,History_Q!$C$2:$C$1000,"revenue",History_Q!$B$2:$B$1000,(SUMIFS(History_Q!$B$2:$B$1000,History_Q!$A$2:$A$1000,G$6,History_Q!$C$2:$C$1000,"revenue")),History_Q!$E$2:$E$1000,"$m",History_Q!$G$2:$G$1000,"populated")/SUMIFS(History_Q!$D$2:$D$1000,History_Q!$C$2:$C$1000,"revenue",History_Q!$B$2:$B$1000,(SUMIFS(History_Q!$B$2:$B$1000,History_Q!$A$2:$A$1000,G$6,History_Q!$C$2:$C$1000,"revenue")-4),History_Q!$E$2:$E$1000,"$m",History_Q!$G$2:$G$1000,"populated")-1) | H11: =IF(OR(H$6="",COUNTIFS(History_Q!$C$2:$C$1000,"revenue",History_Q!$B$2:$B$1000,(SUMIFS(History_Q!$B$2:$B$1000,History_Q!$A$2:$A$1000,H$6,History_Q!$C$2:$C$1000,"revenue")),History_Q!$E$2:$E$1000,"$m",History_Q!$G$2:$G$1000,"populated")<>1,COUNTIFS(History_Q!$C$2:$C$1000,"revenue",History_Q!$B$2:$B$1000,(SUMIFS(History_Q!$B$2:$B$1000,History_Q!$A$2:$A$1000,H$6,History_Q!$C$2:$C$1000,"revenue")-4),History_Q!$E$2:$E$1000,"$m",History_Q!$G$2:$G$1000,"populated")<>1,SUMIFS(History_Q!$D$2:$D$1000,History_Q!$C$2:$C$1000,"revenue",History_Q!$B$2:$B$1000,(SUMIFS(History_Q!$B$2:$B$1000,History_Q!$A$2:$A$1000,H$6,History_Q!$C$2:$C$1000,"revenue")-4),History_Q!$E$2:$E$1000,"$m",History_Q!$G$2:$G$1000,"populated")=0),"",SUMIFS(History_Q!$D$2:$D$1000,History_Q!$C$2:$C$1000,"revenue",History_Q!$B$2:$B$1000,(SUMIFS(History_Q!$B$2:$B$1000,History_Q!$A$2:$A$1000,H$6,History_Q!$C$2:$C$1000,"revenue")),History_Q!$E$2:$E$1000,"$m",History_Q!$G$2:$G$1000,"populated")/SUMIFS(History_Q!$D$2:$D$1000,History_Q!$C$2:$C$1000,"revenue",History_Q!$B$2:$B$1000,(SUMIFS(History_Q!$B$2:$B$1000,History_Q!$A$2:$A$1000,H$6,History_Q!$C$2:$C$1000,"revenue")-4),History_Q!$E$2:$E$1000,"$m",History_Q!$G$2:$G$1000,"populated")-1) | I11: =IF(OR(I$6="",COUNTIFS(History_Q!$C$2:$C$1000,"revenue",History_Q!$B$2:$B$1000,(SUMIFS(History_Q!$B$2:$B$1000,History_Q!$A$2:$A$1000,I$6,History_Q!$C$2:$C$1000,"revenue")),History_Q!$E$2:$E$1000,"$m",History_Q!$G$2:$G$1000,"populated")<>1,COUNTIFS(History_Q!$C$2:$C$1000,"revenue",History_Q!$B$2:$B$1000,(SUMIFS(History_Q!$B$2:$B$1000,History_Q!$A$2:$A$1000,I$6,History_Q!$C$2:$C$1000,"revenue")-4),History_Q!$E$2:$E$1000,"$m",History_Q!$G$2:$G$1000,"populated")<>1,SUMIFS(History_Q!$D$2:$D$1000,History_Q!$C$2:$C$1000,"revenue",History_Q!$B$2:$B$1000,(SUMIFS(History_Q!$B$2:$B$1000,History_Q!$A$2:$A$1000,I$6,History_Q!$C$2:$C$1000,"revenue")-4),History_Q!$E$2:$E$1000,"$m",History_Q!$G$2:$G$1000,"populated")=0),"",SUMIFS(History_Q!$D$2:$D$1000,History_Q!$C$2:$C$1000,"revenue",History_Q!$B$2:$B$1000,(SUMIFS(History_Q!$B$2:$B$1000,History_Q!$A$2:$A$1000,I$6,History_Q!$C$2:$C$1000,"revenue")),History_Q!$E$2:$E$1000,"$m",History_Q!$G$2:$G$1000,"populated")/SUMIFS(History_Q!$D$2:$D$1000,History_Q!$C$2:$C$1000,"revenue",History_Q!$B$2:$B$1000,(SUMIFS(History_Q!$B$2:$B$1000,History_Q!$A$2:$A$1000,I$6,History_Q!$C$2:$C$1000,"revenue")-4),History_Q!$E$2:$E$1000,"$m",History_Q!$G$2:$G$1000,"populated")-1) | ... M11: =IF(OR(M$6="",COUNTIFS(History_Q!$C$2:$C$1000,"revenue",History_Q!$B$2:$B$1000,(SUMIFS(History_Q!$B$2:$B$1000,History_Q!$A$2:$A$1000,M$6,History_Q!$C$2:$C$1000,"revenue")),History_Q!$E$2:$E$1000,"$m",History_Q!$G$2:$G$1000,"populated")<>1,COUNTIFS(History_Q!$C$2:$C$1000,"revenue",History_Q!$B$2:$B$1000,(SUMIFS(History_Q!$B$2:$B$1000,History_Q!$A$2:$A$1000,M$6,History_Q!$C$2:$C$1000,"revenue")-4),History_Q!$E$2:$E$1000,"$m",History_Q!$G$2:$G$1000,"populated")<>1,SUMIFS(History_Q!$D$2:$D$1000,History_Q!$C$2:$C$1000,"revenue",History_Q!$B$2:$B$1000,(SUMIFS(History_Q!$B$2:$B$1000,History_Q!$A$2:$A$1000,M$6,History_Q!$C$2:$C$1000,"revenue")-4),History_Q!$E$2:$E$1000,"$m",History_Q!$G$2:$G$1000,"populated")=0),"",SUMIFS(History_Q!$D$2:$D$1000,History_Q!$C$2:$C$1000,"revenue",History_Q!$B$2:$B$1000,(SUMIFS(History_Q!$B$2:$B$1000,History_Q!$A$2:$A$1000,M$6,History_Q!$C$2:$C$1000,"revenue")),History_Q!$E$2:$E$1000,"$m",History_Q!$G$2:$G$1000,"populated")/SUMIFS(History_Q!$D$2:$D$1000,History_Q!$C$2:$C$1000,"revenue",History_Q!$B$2:$B$1000,(SUMIFS(History_Q!$B$2:$B$1000,History_Q!$A$2:$A$1000,M$6,History_Q!$C$2:$C$1000,"revenue")-4),History_Q!$E$2:$E$1000,"$m",History_Q!$G$2:$G$1000,"populated")-1)
A12: Margins
A13: Gross margin % | B13: =IF(OR(B262="",B9="",B9=0),"",B262/B9) | C13: =IF(OR(C262="",C9="",C9=0),"",C262/C9) | D13: =IF(OR(D262="",D9="",D9=0),"",D262/D9) | E13: =IF(OR(E262="",E9="",E9=0),"",E262/E9) | F13: =IF(OR(F262="",F9="",F9=0),"",F262/F9) | G13: =IF(OR(G262="",G9="",G9=0),"",G262/G9) | H13: =IF(OR(H262="",H9="",H9=0),"",H262/H9) | I13: =IF(OR(I262="",I9="",I9=0),"",I262/I9) | ... M13: =IF(OR(M262="",M9="",M9=0),"",M262/M9)
A14: Operating margin % | B14: =IF(OR(B32="",B9="",B9=0),"",B32/B9) | C14: =IF(OR(C32="",C9="",C9=0),"",C32/C9) | D14: =IF(OR(D32="",D9="",D9=0),"",D32/D9) | E14: =IF(OR(E32="",E9="",E9=0),"",E32/E9) | F14: =IF(OR(F32="",F9="",F9=0),"",F32/F9) | G14: =IF(OR(G32="",G9="",G9=0),"",G32/G9) | H14: =IF(OR(H32="",H9="",H9=0),"",H32/H9) | I14: =IF(OR(I32="",I9="",I9=0),"",I32/I9) | ... M14: =IF(OR(M32="",M9="",M9=0),"",M32/M9)
A15: Operating margin (TTM) | B15: =IF(OR(B$6="",COUNTIFS(History_Q!$C$2:$C$1000,"operating_income",History_Q!$B$2:$B$1000,">="&((SUMIFS(History_Q!$B$2:$B$1000,History_Q!$A$2:$A$1000,B$6,History_Q!$C$2:$C$1000,"operating_income"))-3),History_Q!$B$2:$B$1000,"<="&(SUMIFS(History_Q!$B$2:$B$1000,History_Q!$A$2:$A$1000,B$6,History_Q!$C$2:$C$1000,"operating_income")),History_Q!$E$2:$E$1000,"$m",History_Q!$G$2:$G$1000,"populated")<>4,COUNTIFS(History_Q!$C$2:$C$1000,"revenue",History_Q!$B$2:$B$1000,">="&((SUMIFS(History_Q!$B$2:$B$1000,History_Q!$A$2:$A$1000,B$6,History_Q!$C$2:$C$1000,"revenue"))-3),History_Q!$B$2:$B$1000,"<="&(SUMIFS(History_Q!$B$2:$B$1000,History_Q!$A$2:$A$1000,B$6,History_Q!$C$2:$C$1000,"revenue")),History_Q!$E$2:$E$1000,"$m",History_Q!$G$2:$G$1000,"populated")<>4,_xlfn.MAXIFS(History_Q!$B$2:$B$1000,History_Q!$C$2:$C$1000,"operating_income",History_Q!$B$2:$B$1000,">="&((SUMIFS(History_Q!$B$2:$B$1000,History_Q!$A$2:$A$1000,B$6,History_Q!$C$2:$C$1000,"operating_income"))-3),History_Q!$B$2:$B$1000,"<="&(SUMIFS(History_Q!$B$2:$B$1000,History_Q!$A$2:$A$1000,B$6,History_Q!$C$2:$C$1000,"operating_income")),History_Q!$E$2:$E$1000,"$m",History_Q!$G$2:$G$1000,"populated")-_xlfn.MINIFS(History_Q!$B$2:$B$1000,History_Q!$C$2:$C$1000,"operating_income",History_Q!$B$2:$B$1000,">="&((SUMIFS(History_Q!$B$2:$B$1000,History_Q!$A$2:$A$1000,B$6,History_Q!$C$2:$C$1000,"operating_income"))-3),History_Q!$B$2:$B$1000,"<="&(SUMIFS(History_Q!$B$2:$B$1000,History_Q!$A$2:$A$1000,B$6,History_Q!$C$2:$C$1000,"operating_income")),History_Q!$E$2:$E$1000,"$m",History_Q!$G$2:$G$1000,"populated")<>3,_xlfn.MAXIFS(History_Q!$B$2:$B$1000,History_Q!$C$2:$C$1000,"revenue",History_Q!$B$2:$B$1000,">="&((SUMIFS(History_Q!$B$2:$B$1000,History_Q!$A$2:$A$1000,B$6,History_Q!$C$2:$C$1000,"revenue"))-3),History_Q!$B$2:$B$1000,"<="&(SUMIFS(History_Q!$B$2:$B$1000,History_Q!$A$2:$A$1000,B$6,History_Q!$C$2:$C$1000,"revenue")),History_Q!$E$2:$E$1000,"$m",History_Q!$G$2:$G$1000,"populated")-_xlfn.MINIFS(History_Q!$B$2:$B$1000,History_Q!$C$2:$C$1000,"revenue",History_Q!$B$2:$B$1000,">="&((SUMIFS(History_Q!$B$2:$B$1000,History_Q!$A$2:$A$1000,B$6,History_Q!$C$2:$C$1000,"revenue"))-3),History_Q!$B$2:$B$1000,"<="&(SUMIFS(History_Q!$B$2:$B$1000,History_Q!$A$2:$A$1000,B$6,History_Q!$C$2:$C$1000,"revenue")),History_Q!$E$2:$E$1000,"$m",History_Q!$G$2:$G$1000,"populated")<>3,SUMIFS(History_Q!$D$2:$D$1000,History_Q!$C$2:$C$1000,"revenue",History_Q!$B$2:$B$1000,">="&((SUMIFS(History_Q!$B$2:$B$1000,History_Q!$A$2:$A$1000,B$6,History_Q!$C$2:$C$1000,"revenue"))-3),History_Q!$B$2:$B$1000,"<="&(SUMIFS(History_Q!$B$2:$B$1000,History_Q!$A$2:$A$1000,B$6,History_Q!$C$2:$C$1000,"revenue")),History_Q!$E$2:$E$1000,"$m",History_Q!$G$2:$G$1000,"populated")=0),"",SUMIFS(History_Q!$D$2:$D$1000,History_Q!$C$2:$C$1000,"operating_income",History_Q!$B$2:$B$1000,">="&((SUMIFS(History_Q!$B$2:$B$1000,History_Q!$A$2:$A$1000,B$6,History_Q!$C$2:$C$1000,"operating_income"))-3),History_Q!$B$2:$B$1000,"<="&(SUMIFS(History_Q!$B$2:$B$1000,History_Q!$A$2:$A$1000,B$6,History_Q!$C$2:$C$1000,"operating_income")),History_Q!$E$2:$E$1000,"$m",History_Q!$G$2:$G$1000,"populated")/SUMIFS(History_Q!$D$2:$D$1000,History_Q!$C$2:$C$1000,"revenue",History_Q!$B$2:$B$1000,">="&((SUMIFS(History_Q!$B$2:$B$1000,History_Q!$A$2:$A$1000,B$6,History_Q!$C$2:$C$1000,"revenue"))-3),History_Q!$B$2:$B$1000,"<="&(SUMIFS(History_Q!$B$2:$B$1000,History_Q!$A$2:$A$1000,B$6,History_Q!$C$2:$C$1000,"revenue")),History_Q!$E$2:$E$1000,"$m",History_Q!$G$2:$G$1000,"populated")) | C15: =IF(OR(C$6="",COUNTIFS(History_Q!$C$2:$C$1000,"operating_income",History_Q!$B$2:$B$1000,">="&((SUMIFS(History_Q!$B$2:$B$1000,History_Q!$A$2:$A$1000,C$6,History_Q!$C$2:$C$1000,"operating_income"))-3),History_Q!$B$2:$B$1000,"<="&(SUMIFS(History_Q!$B$2:$B$1000,History_Q!$A$2:$A$1000,C$6,History_Q!$C$2:$C$1000,"operating_income")),History_Q!$E$2:$E$1000,"$m",History_Q!$G$2:$G$1000,"populated")<>4,COUNTIFS(History_Q!$C$2:$C$1000,"revenue",History_Q!$B$2:$B$1000,">="&((SUMIFS(History_Q!$B$2:$B$1000,History_Q!$A$2:$A$1000,C$6,History_Q!$C$2:$C$1000,"revenue"))-3),History_Q!$B$2:$B$1000,"<="&(SUMIFS(History_Q!$B$2:$B$1000,History_Q!$A$2:$A$1000,C$6,History_Q!$C$2:$C$1000,"revenue")),History_Q!$E$2:$E$1000,"$m",History_Q!$G$2:$G$1000,"populated")<>4,_xlfn.MAXIFS(History_Q!$B$2:$B$1000,History_Q!$C$2:$C$1000,"operating_income",History_Q!$B$2:$B$1000,">="&((SUMIFS(History_Q!$B$2:$B$1000,History_Q!$A$2:$A$1000,C$6,History_Q!$C$2:$C$1000,"operating_income"))-3),History_Q!$B$2:$B$1000,"<="&(SUMIFS(History_Q!$B$2:$B$1000,History_Q!$A$2:$A$1000,C$6,History_Q!$C$2:$C$1000,"operating_income")),History_Q!$E$2:$E$1000,"$m",History_Q!$G$2:$G$1000,"populated")-_xlfn.MINIFS(History_Q!$B$2:$B$1000,History_Q!$C$2:$C$1000,"operating_income",History_Q!$B$2:$B$1000,">="&((SUMIFS(History_Q!$B$2:$B$1000,History_Q!$A$2:$A$1000,C$6,History_Q!$C$2:$C$1000,"operating_income"))-3),History_Q!$B$2:$B$1000,"<="&(SUMIFS(History_Q!$B$2:$B$1000,History_Q!$A$2:$A$1000,C$6,History_Q!$C$2:$C$1000,"operating_income")),History_Q!$E$2:$E$1000,"$m",History_Q!$G$2:$G$1000,"populated")<>3,_xlfn.MAXIFS(History_Q!$B$2:$B$1000,History_Q!$C$2:$C$1000,"revenue",History_Q!$B$2:$B$1000,">="&((SUMIFS(History_Q!$B$2:$B$1000,History_Q!$A$2:$A$1000,C$6,History_Q!$C$2:$C$1000,"revenue"))-3),History_Q!$B$2:$B$1000,"<="&(SUMIFS(History_Q!$B$2:$B$1000,History_Q!$A$2:$A$1000,C$6,History_Q!$C$2:$C$1000,"revenue")),History_Q!$E$2:$E$1000,"$m",History_Q!$G$2:$G$1000,"populated")-_xlfn.MINIFS(History_Q!$B$2:$B$1000,History_Q!$C$2:$C$1000,"revenue",History_Q!$B$2:$B$1000,">="&((SUMIFS(History_Q!$B$2:$B$1000,History_Q!$A$2:$A$1000,C$6,History_Q!$C$2:$C$1000,"revenue"))-3),History_Q!$B$2:$B$1000,"<="&(SUMIFS(History_Q!$B$2:$B$1000,History_Q!$A$2:$A$1000,C$6,History_Q!$C$2:$C$1000,"revenue")),History_Q!$E$2:$E$1000,"$m",History_Q!$G$2:$G$1000,"populated")<>3,SUMIFS(History_Q!$D$2:$D$1000,History_Q!$C$2:$C$1000,"revenue",History_Q!$B$2:$B$1000,">="&((SUMIFS(History_Q!$B$2:$B$1000,History_Q!$A$2:$A$1000,C$6,History_Q!$C$2:$C$1000,"revenue"))-3),History_Q!$B$2:$B$1000,"<="&(SUMIFS(History_Q!$B$2:$B$1000,History_Q!$A$2:$A$1000,C$6,History_Q!$C$2:$C$1000,"revenue")),History_Q!$E$2:$E$1000,"$m",History_Q!$G$2:$G$1000,"populated")=0),"",SUMIFS(History_Q!$D$2:$D$1000,History_Q!$C$2:$C$1000,"operating_income",History_Q!$B$2:$B$1000,">="&((SUMIFS(History_Q!$B$2:$B$1000,History_Q!$A$2:$A$1000,C$6,History_Q!$C$2:$C$1000,"operating_income"))-3),History_Q!$B$2:$B$1000,"<="&(SUMIFS(History_Q!$B$2:$B$1000,History_Q!$A$2:$A$1000,C$6,History_Q!$C$2:$C$1000,"operating_income")),History_Q!$E$2:$E$1000,"$m",History_Q!$G$2:$G$1000,"populated")/SUMIFS(History_Q!$D$2:$D$1000,History_Q!$C$2:$C$1000,"revenue",History_Q!$B$2:$B$1000,">="&((SUMIFS(History_Q!$B$2:$B$1000,History_Q!$A$2:$A$1000,C$6,History_Q!$C$2:$C$1000,"revenue"))-3),History_Q!$B$2:$B$1000,"<="&(SUMIFS(History_Q!$B$2:$B$1000,History_Q!$A$2:$A$1000,C$6,History_Q!$C$2:$C$1000,"revenue")),History_Q!$E$2:$E$1000,"$m",History_Q!$G$2:$G$1000,"populated")) | D15: =IF(OR(D$6="",COUNTIFS(History_Q!$C$2:$C$1000,"operating_income",History_Q!$B$2:$B$1000,">="&((SUMIFS(History_Q!$B$2:$B$1000,History_Q!$A$2:$A$1000,D$6,History_Q!$C$2:$C$1000,"operating_income"))-3),History_Q!$B$2:$B$1000,"<="&(SUMIFS(History_Q!$B$2:$B$1000,History_Q!$A$2:$A$1000,D$6,History_Q!$C$2:$C$1000,"operating_income")),History_Q!$E$2:$E$1000,"$m",History_Q!$G$2:$G$1000,"populated")<>4,COUNTIFS(History_Q!$C$2:$C$1000,"revenue",History_Q!$B$2:$B$1000,">="&((SUMIFS(History_Q!$B$2:$B$1000,History_Q!$A$2:$A$1000,D$6,History_Q!$C$2:$C$1000,"revenue"))-3),History_Q!$B$2:$B$1000,"<="&(SUMIFS(History_Q!$B$2:$B$1000,History_Q!$A$2:$A$1000,D$6,History_Q!$C$2:$C$1000,"revenue")),History_Q!$E$2:$E$1000,"$m",History_Q!$G$2:$G$1000,"populated")<>4,_xlfn.MAXIFS(History_Q!$B$2:$B$1000,History_Q!$C$2:$C$1000,"operating_income",History_Q!$B$2:$B$1000,">="&((SUMIFS(History_Q!$B$2:$B$1000,History_Q!$A$2:$A$1000,D$6,History_Q!$C$2:$C$1000,"operating_income"))-3),History_Q!$B$2:$B$1000,"<="&(SUMIFS(History_Q!$B$2:$B$1000,History_Q!$A$2:$A$1000,D$6,History_Q!$C$2:$C$1000,"operating_income")),History_Q!$E$2:$E$1000,"$m",History_Q!$G$2:$G$1000,"populated")-_xlfn.MINIFS(History_Q!$B$2:$B$1000,History_Q!$C$2:$C$1000,"operating_income",History_Q!$B$2:$B$1000,">="&((SUMIFS(History_Q!$B$2:$B$1000,History_Q!$A$2:$A$1000,D$6,History_Q!$C$2:$C$1000,"operating_income"))-3),History_Q!$B$2:$B$1000,"<="&(SUMIFS(History_Q!$B$2:$B$1000,History_Q!$A$2:$A$1000,D$6,History_Q!$C$2:$C$1000,"operating_income")),History_Q!$E$2:$E$1000,"$m",History_Q!$G$2:$G$1000,"populated")<>3,_xlfn.MAXIFS(History_Q!$B$2:$B$1000,History_Q!$C$2:$C$1000,"revenue",History_Q!$B$2:$B$1000,">="&((SUMIFS(History_Q!$B$2:$B$1000,History_Q!$A$2:$A$1000,D$6,History_Q!$C$2:$C$1000,"revenue"))-3),History_Q!$B$2:$B$1000,"<="&(SUMIFS(History_Q!$B$2:$B$1000,History_Q!$A$2:$A$1000,D$6,History_Q!$C$2:$C$1000,"revenue")),History_Q!$E$2:$E$1000,"$m",History_Q!$G$2:$G$1000,"populated")-_xlfn.MINIFS(History_Q!$B$2:$B$1000,History_Q!$C$2:$C$1000,"revenue",History_Q!$B$2:$B$1000,">="&((SUMIFS(History_Q!$B$2:$B$1000,History_Q!$A$2:$A$1000,D$6,History_Q!$C$2:$C$1000,"revenue"))-3),History_Q!$B$2:$B$1000,"<="&(SUMIFS(History_Q!$B$2:$B$1000,History_Q!$A$2:$A$1000,D$6,History_Q!$C$2:$C$1000,"revenue")),History_Q!$E$2:$E$1000,"$m",History_Q!$G$2:$G$1000,"populated")<>3,SUMIFS(History_Q!$D$2:$D$1000,History_Q!$C$2:$C$1000,"revenue",History_Q!$B$2:$B$1000,">="&((SUMIFS(History_Q!$B$2:$B$1000,History_Q!$A$2:$A$1000,D$6,History_Q!$C$2:$C$1000,"revenue"))-3),History_Q!$B$2:$B$1000,"<="&(SUMIFS(History_Q!$B$2:$B$1000,History_Q!$A$2:$A$1000,D$6,History_Q!$C$2:$C$1000,"revenue")),History_Q!$E$2:$E$1000,"$m",History_Q!$G$2:$G$1000,"populated")=0),"",SUMIFS(History_Q!$D$2:$D$1000,History_Q!$C$2:$C$1000,"operating_income",History_Q!$B$2:$B$1000,">="&((SUMIFS(History_Q!$B$2:$B$1000,History_Q!$A$2:$A$1000,D$6,History_Q!$C$2:$C$1000,"operating_income"))-3),History_Q!$B$2:$B$1000,"<="&(SUMIFS(History_Q!$B$2:$B$1000,History_Q!$A$2:$A$1000,D$6,History_Q!$C$2:$C$1000,"operating_income")),History_Q!$E$2:$E$1000,"$m",History_Q!$G$2:$G$1000,"populated")/SUMIFS(History_Q!$D$2:$D$1000,History_Q!$C$2:$C$1000,"revenue",History_Q!$B$2:$B$1000,">="&((SUMIFS(History_Q!$B$2:$B$1000,History_Q!$A$2:$A$1000,D$6,History_Q!$C$2:$C$1000,"revenue"))-3),History_Q!$B$2:$B$1000,"<="&(SUMIFS(History_Q!$B$2:$B$1000,History_Q!$A$2:$A$1000,D$6,History_Q!$C$2:$C$1000,"revenue")),History_Q!$E$2:$E$1000,"$m",History_Q!$G$2:$G$1000,"populated")) | E15: =IF(OR(E$6="",COUNTIFS(History_Q!$C$2:$C$1000,"operating_income",History_Q!$B$2:$B$1000,">="&((SUMIFS(History_Q!$B$2:$B$1000,History_Q!$A$2:$A$1000,E$6,History_Q!$C$2:$C$1000,"operating_income"))-3),History_Q!$B$2:$B$1000,"<="&(SUMIFS(History_Q!$B$2:$B$1000,History_Q!$A$2:$A$1000,E$6,History_Q!$C$2:$C$1000,"operating_income")),History_Q!$E$2:$E$1000,"$m",History_Q!$G$2:$G$1000,"populated")<>4,COUNTIFS(History_Q!$C$2:$C$1000,"revenue",History_Q!$B$2:$B$1000,">="&((SUMIFS(History_Q!$B$2:$B$1000,History_Q!$A$2:$A$1000,E$6,History_Q!$C$2:$C$1000,"revenue"))-3),History_Q!$B$2:$B$1000,"<="&(SUMIFS(History_Q!$B$2:$B$1000,History_Q!$A$2:$A$1000,E$6,History_Q!$C$2:$C$1000,"revenue")),History_Q!$E$2:$E$1000,"$m",History_Q!$G$2:$G$1000,"populated")<>4,_xlfn.MAXIFS(History_Q!$B$2:$B$1000,History_Q!$C$2:$C$1000,"operating_income",History_Q!$B$2:$B$1000,">="&((SUMIFS(History_Q!$B$2:$B$1000,History_Q!$A$2:$A$1000,E$6,History_Q!$C$2:$C$1000,"operating_income"))-3),History_Q!$B$2:$B$1000,"<="&(SUMIFS(History_Q!$B$2:$B$1000,History_Q!$A$2:$A$1000,E$6,History_Q!$C$2:$C$1000,"operating_income")),History_Q!$E$2:$E$1000,"$m",History_Q!$G$2:$G$1000,"populated")-_xlfn.MINIFS(History_Q!$B$2:$B$1000,History_Q!$C$2:$C$1000,"operating_income",History_Q!$B$2:$B$1000,">="&((SUMIFS(History_Q!$B$2:$B$1000,History_Q!$A$2:$A$1000,E$6,History_Q!$C$2:$C$1000,"operating_income"))-3),History_Q!$B$2:$B$1000,"<="&(SUMIFS(History_Q!$B$2:$B$1000,History_Q!$A$2:$A$1000,E$6,History_Q!$C$2:$C$1000,"operating_income")),History_Q!$E$2:$E$1000,"$m",History_Q!$G$2:$G$1000,"populated")<>3,_xlfn.MAXIFS(History_Q!$B$2:$B$1000,History_Q!$C$2:$C$1000,"revenue",History_Q!$B$2:$B$1000,">="&((SUMIFS(History_Q!$B$2:$B$1000,History_Q!$A$2:$A$1000,E$6,History_Q!$C$2:$C$1000,"revenue"))-3),History_Q!$B$2:$B$1000,"<="&(SUMIFS(History_Q!$B$2:$B$1000,History_Q!$A$2:$A$1000,E$6,History_Q!$C$2:$C$1000,"revenue")),History_Q!$E$2:$E$1000,"$m",History_Q!$G$2:$G$1000,"populated")-_xlfn.MINIFS(History_Q!$B$2:$B$1000,History_Q!$C$2:$C$1000,"revenue",History_Q!$B$2:$B$1000,">="&((SUMIFS(History_Q!$B$2:$B$1000,History_Q!$A$2:$A$1000,E$6,History_Q!$C$2:$C$1000,"revenue"))-3),History_Q!$B$2:$B$1000,"<="&(SUMIFS(History_Q!$B$2:$B$1000,History_Q!$A$2:$A$1000,E$6,History_Q!$C$2:$C$1000,"revenue")),History_Q!$E$2:$E$1000,"$m",History_Q!$G$2:$G$1000,"populated")<>3,SUMIFS(History_Q!$D$2:$D$1000,History_Q!$C$2:$C$1000,"revenue",History_Q!$B$2:$B$1000,">="&((SUMIFS(History_Q!$B$2:$B$1000,History_Q!$A$2:$A$1000,E$6,History_Q!$C$2:$C$1000,"revenue"))-3),History_Q!$B$2:$B$1000,"<="&(SUMIFS(History_Q!$B$2:$B$1000,History_Q!$A$2:$A$1000,E$6,History_Q!$C$2:$C$1000,"revenue")),History_Q!$E$2:$E$1000,"$m",History_Q!$G$2:$G$1000,"populated")=0),"",SUMIFS(History_Q!$D$2:$D$1000,History_Q!$C$2:$C$1000,"operating_income",History_Q!$B$2:$B$1000,">="&((SUMIFS(History_Q!$B$2:$B$1000,History_Q!$A$2:$A$1000,E$6,History_Q!$C$2:$C$1000,"operating_income"))-3),History_Q!$B$2:$B$1000,"<="&(SUMIFS(History_Q!$B$2:$B$1000,History_Q!$A$2:$A$1000,E$6,History_Q!$C$2:$C$1000,"operating_income")),History_Q!$E$2:$E$1000,"$m",History_Q!$G$2:$G$1000,"populated")/SUMIFS(History_Q!$D$2:$D$1000,History_Q!$C$2:$C$1000,"revenue",History_Q!$B$2:$B$1000,">="&((SUMIFS(History_Q!$B$2:$B$1000,History_Q!$A$2:$A$1000,E$6,History_Q!$C$2:$C$1000,"revenue"))-3),History_Q!$B$2:$B$1000,"<="&(SUMIFS(History_Q!$B$2:$B$1000,History_Q!$A$2:$A$1000,E$6,History_Q!$C$2:$C$1000,"revenue")),History_Q!$E$2:$E$1000,"$m",History_Q!$G$2:$G$1000,"populated")) | F15: =IF(OR(F$6="",COUNTIFS(History_Q!$C$2:$C$1000,"operating_income",History_Q!$B$2:$B$1000,">="&((SUMIFS(History_Q!$B$2:$B$1000,History_Q!$A$2:$A$1000,F$6,History_Q!$C$2:$C$1000,"operating_income"))-3),History_Q!$B$2:$B$1000,"<="&(SUMIFS(History_Q!$B$2:$B$1000,History_Q!$A$2:$A$1000,F$6,History_Q!$C$2:$C$1000,"operating_income")),History_Q!$E$2:$E$1000,"$m",History_Q!$G$2:$G$1000,"populated")<>4,COUNTIFS(History_Q!$C$2:$C$1000,"revenue",History_Q!$B$2:$B$1000,">="&((SUMIFS(History_Q!$B$2:$B$1000,History_Q!$A$2:$A$1000,F$6,History_Q!$C$2:$C$1000,"revenue"))-3),History_Q!$B$2:$B$1000,"<="&(SUMIFS(History_Q!$B$2:$B$1000,History_Q!$A$2:$A$1000,F$6,History_Q!$C$2:$C$1000,"revenue")),History_Q!$E$2:$E$1000,"$m",History_Q!$G$2:$G$1000,"populated")<>4,_xlfn.MAXIFS(History_Q!$B$2:$B$1000,History_Q!$C$2:$C$1000,"operating_income",History_Q!$B$2:$B$1000,">="&((SUMIFS(History_Q!$B$2:$B$1000,History_Q!$A$2:$A$1000,F$6,History_Q!$C$2:$C$1000,"operating_income"))-3),History_Q!$B$2:$B$1000,"<="&(SUMIFS(History_Q!$B$2:$B$1000,History_Q!$A$2:$A$1000,F$6,History_Q!$C$2:$C$1000,"operating_income")),History_Q!$E$2:$E$1000,"$m",History_Q!$G$2:$G$1000,"populated")-_xlfn.MINIFS(History_Q!$B$2:$B$1000,History_Q!$C$2:$C$1000,"operating_income",History_Q!$B$2:$B$1000,">="&((SUMIFS(History_Q!$B$2:$B$1000,History_Q!$A$2:$A$1000,F$6,History_Q!$C$2:$C$1000,"operating_income"))-3),History_Q!$B$2:$B$1000,"<="&(SUMIFS(History_Q!$B$2:$B$1000,History_Q!$A$2:$A$1000,F$6,History_Q!$C$2:$C$1000,"operating_income")),History_Q!$E$2:$E$1000,"$m",History_Q!$G$2:$G$1000,"populated")<>3,_xlfn.MAXIFS(History_Q!$B$2:$B$1000,History_Q!$C$2:$C$1000,"revenue",History_Q!$B$2:$B$1000,">="&((SUMIFS(History_Q!$B$2:$B$1000,History_Q!$A$2:$A$1000,F$6,History_Q!$C$2:$C$1000,"revenue"))-3),History_Q!$B$2:$B$1000,"<="&(SUMIFS(History_Q!$B$2:$B$1000,History_Q!$A$2:$A$1000,F$6,History_Q!$C$2:$C$1000,"revenue")),History_Q!$E$2:$E$1000,"$m",History_Q!$G$2:$G$1000,"populated")-_xlfn.MINIFS(History_Q!$B$2:$B$1000,History_Q!$C$2:$C$1000,"revenue",History_Q!$B$2:$B$1000,">="&((SUMIFS(History_Q!$B$2:$B$1000,History_Q!$A$2:$A$1000,F$6,History_Q!$C$2:$C$1000,"revenue"))-3),History_Q!$B$2:$B$1000,"<="&(SUMIFS(History_Q!$B$2:$B$1000,History_Q!$A$2:$A$1000,F$6,History_Q!$C$2:$C$1000,"revenue")),History_Q!$E$2:$E$1000,"$m",History_Q!$G$2:$G$1000,"populated")<>3,SUMIFS(History_Q!$D$2:$D$1000,History_Q!$C$2:$C$1000,"revenue",History_Q!$B$2:$B$1000,">="&((SUMIFS(History_Q!$B$2:$B$1000,History_Q!$A$2:$A$1000,F$6,History_Q!$C$2:$C$1000,"revenue"))-3),History_Q!$B$2:$B$1000,"<="&(SUMIFS(History_Q!$B$2:$B$1000,History_Q!$A$2:$A$1000,F$6,History_Q!$C$2:$C$1000,"revenue")),History_Q!$E$2:$E$1000,"$m",History_Q!$G$2:$G$1000,"populated")=0),"",SUMIFS(History_Q!$D$2:$D$1000,History_Q!$C$2:$C$1000,"operating_income",History_Q!$B$2:$B$1000,">="&((SUMIFS(History_Q!$B$2:$B$1000,History_Q!$A$2:$A$1000,F$6,History_Q!$C$2:$C$1000,"operating_income"))-3),History_Q!$B$2:$B$1000,"<="&(SUMIFS(History_Q!$B$2:$B$1000,History_Q!$A$2:$A$1000,F$6,History_Q!$C$2:$C$1000,"operating_income")),History_Q!$E$2:$E$1000,"$m",History_Q!$G$2:$G$1000,"populated")/SUMIFS(History_Q!$D$2:$D$1000,History_Q!$C$2:$C$1000,"revenue",History_Q!$B$2:$B$1000,">="&((SUMIFS(History_Q!$B$2:$B$1000,History_Q!$A$2:$A$1000,F$6,History_Q!$C$2:$C$1000,"revenue"))-3),History_Q!$B$2:$B$1000,"<="&(SUMIFS(History_Q!$B$2:$B$1000,History_Q!$A$2:$A$1000,F$6,History_Q!$C$2:$C$1000,"revenue")),History_Q!$E$2:$E$1000,"$m",History_Q!$G$2:$G$1000,"populated")) | G15: =IF(OR(G$6="",COUNTIFS(History_Q!$C$2:$C$1000,"operating_income",History_Q!$B$2:$B$1000,">="&((SUMIFS(History_Q!$B$2:$B$1000,History_Q!$A$2:$A$1000,G$6,History_Q!$C$2:$C$1000,"operating_income"))-3),History_Q!$B$2:$B$1000,"<="&(SUMIFS(History_Q!$B$2:$B$1000,History_Q!$A$2:$A$1000,G$6,History_Q!$C$2:$C$1000,"operating_income")),History_Q!$E$2:$E$1000,"$m",History_Q!$G$2:$G$1000,"populated")<>4,COUNTIFS(History_Q!$C$2:$C$1000,"revenue",History_Q!$B$2:$B$1000,">="&((SUMIFS(History_Q!$B$2:$B$1000,History_Q!$A$2:$A$1000,G$6,History_Q!$C$2:$C$1000,"revenue"))-3),History_Q!$B$2:$B$1000,"<="&(SUMIFS(History_Q!$B$2:$B$1000,History_Q!$A$2:$A$1000,G$6,History_Q!$C$2:$C$1000,"revenue")),History_Q!$E$2:$E$1000,"$m",History_Q!$G$2:$G$1000,"populated")<>4,_xlfn.MAXIFS(History_Q!$B$2:$B$1000,History_Q!$C$2:$C$1000,"operating_income",History_Q!$B$2:$B$1000,">="&((SUMIFS(History_Q!$B$2:$B$1000,History_Q!$A$2:$A$1000,G$6,History_Q!$C$2:$C$1000,"operating_income"))-3),History_Q!$B$2:$B$1000,"<="&(SUMIFS(History_Q!$B$2:$B$1000,History_Q!$A$2:$A$1000,G$6,History_Q!$C$2:$C$1000,"operating_income")),History_Q!$E$2:$E$1000,"$m",History_Q!$G$2:$G$1000,"populated")-_xlfn.MINIFS(History_Q!$B$2:$B$1000,History_Q!$C$2:$C$1000,"operating_income",History_Q!$B$2:$B$1000,">="&((SUMIFS(History_Q!$B$2:$B$1000,History_Q!$A$2:$A$1000,G$6,History_Q!$C$2:$C$1000,"operating_income"))-3),History_Q!$B$2:$B$1000,"<="&(SUMIFS(History_Q!$B$2:$B$1000,History_Q!$A$2:$A$1000,G$6,History_Q!$C$2:$C$1000,"operating_income")),History_Q!$E$2:$E$1000,"$m",History_Q!$G$2:$G$1000,"populated")<>3,_xlfn.MAXIFS(History_Q!$B$2:$B$1000,History_Q!$C$2:$C$1000,"revenue",History_Q!$B$2:$B$1000,">="&((SUMIFS(History_Q!$B$2:$B$1000,History_Q!$A$2:$A$1000,G$6,History_Q!$C$2:$C$1000,"revenue"))-3),History_Q!$B$2:$B$1000,"<="&(SUMIFS(History_Q!$B$2:$B$1000,History_Q!$A$2:$A$1000,G$6,History_Q!$C$2:$C$1000,"revenue")),History_Q!$E$2:$E$1000,"$m",History_Q!$G$2:$G$1000,"populated")-_xlfn.MINIFS(History_Q!$B$2:$B$1000,History_Q!$C$2:$C$1000,"revenue",History_Q!$B$2:$B$1000,">="&((SUMIFS(History_Q!$B$2:$B$1000,History_Q!$A$2:$A$1000,G$6,History_Q!$C$2:$C$1000,"revenue"))-3),History_Q!$B$2:$B$1000,"<="&(SUMIFS(History_Q!$B$2:$B$1000,History_Q!$A$2:$A$1000,G$6,History_Q!$C$2:$C$1000,"revenue")),History_Q!$E$2:$E$1000,"$m",History_Q!$G$2:$G$1000,"populated")<>3,SUMIFS(History_Q!$D$2:$D$1000,History_Q!$C$2:$C$1000,"revenue",History_Q!$B$2:$B$1000,">="&((SUMIFS(History_Q!$B$2:$B$1000,History_Q!$A$2:$A$1000,G$6,History_Q!$C$2:$C$1000,"revenue"))-3),History_Q!$B$2:$B$1000,"<="&(SUMIFS(History_Q!$B$2:$B$1000,History_Q!$A$2:$A$1000,G$6,History_Q!$C$2:$C$1000,"revenue")),History_Q!$E$2:$E$1000,"$m",History_Q!$G$2:$G$1000,"populated")=0),"",SUMIFS(History_Q!$D$2:$D$1000,History_Q!$C$2:$C$1000,"operating_income",History_Q!$B$2:$B$1000,">="&((SUMIFS(History_Q!$B$2:$B$1000,History_Q!$A$2:$A$1000,G$6,History_Q!$C$2:$C$1000,"operating_income"))-3),History_Q!$B$2:$B$1000,"<="&(SUMIFS(History_Q!$B$2:$B$1000,History_Q!$A$2:$A$1000,G$6,History_Q!$C$2:$C$1000,"operating_income")),History_Q!$E$2:$E$1000,"$m",History_Q!$G$2:$G$1000,"populated")/SUMIFS(History_Q!$D$2:$D$1000,History_Q!$C$2:$C$1000,"revenue",History_Q!$B$2:$B$1000,">="&((SUMIFS(History_Q!$B$2:$B$1000,History_Q!$A$2:$A$1000,G$6,History_Q!$C$2:$C$1000,"revenue"))-3),History_Q!$B$2:$B$1000,"<="&(SUMIFS(History_Q!$B$2:$B$1000,History_Q!$A$2:$A$1000,G$6,History_Q!$C$2:$C$1000,"revenue")),History_Q!$E$2:$E$1000,"$m",History_Q!$G$2:$G$1000,"populated")) | H15: =IF(OR(H$6="",COUNTIFS(History_Q!$C$2:$C$1000,"operating_income",History_Q!$B$2:$B$1000,">="&((SUMIFS(History_Q!$B$2:$B$1000,History_Q!$A$2:$A$1000,H$6,History_Q!$C$2:$C$1000,"operating_income"))-3),History_Q!$B$2:$B$1000,"<="&(SUMIFS(History_Q!$B$2:$B$1000,History_Q!$A$2:$A$1000,H$6,History_Q!$C$2:$C$1000,"operating_income")),History_Q!$E$2:$E$1000,"$m",History_Q!$G$2:$G$1000,"populated")<>4,COUNTIFS(History_Q!$C$2:$C$1000,"revenue",History_Q!$B$2:$B$1000,">="&((SUMIFS(History_Q!$B$2:$B$1000,History_Q!$A$2:$A$1000,H$6,History_Q!$C$2:$C$1000,"revenue"))-3),History_Q!$B$2:$B$1000,"<="&(SUMIFS(History_Q!$B$2:$B$1000,History_Q!$A$2:$A$1000,H$6,History_Q!$C$2:$C$1000,"revenue")),History_Q!$E$2:$E$1000,"$m",History_Q!$G$2:$G$1000,"populated")<>4,_xlfn.MAXIFS(History_Q!$B$2:$B$1000,History_Q!$C$2:$C$1000,"operating_income",History_Q!$B$2:$B$1000,">="&((SUMIFS(History_Q!$B$2:$B$1000,History_Q!$A$2:$A$1000,H$6,History_Q!$C$2:$C$1000,"operating_income"))-3),History_Q!$B$2:$B$1000,"<="&(SUMIFS(History_Q!$B$2:$B$1000,History_Q!$A$2:$A$1000,H$6,History_Q!$C$2:$C$1000,"operating_income")),History_Q!$E$2:$E$1000,"$m",History_Q!$G$2:$G$1000,"populated")-_xlfn.MINIFS(History_Q!$B$2:$B$1000,History_Q!$C$2:$C$1000,"operating_income",History_Q!$B$2:$B$1000,">="&((SUMIFS(History_Q!$B$2:$B$1000,History_Q!$A$2:$A$1000,H$6,History_Q!$C$2:$C$1000,"operating_income"))-3),History_Q!$B$2:$B$1000,"<="&(SUMIFS(History_Q!$B$2:$B$1000,History_Q!$A$2:$A$1000,H$6,History_Q!$C$2:$C$1000,"operating_income")),History_Q!$E$2:$E$1000,"$m",History_Q!$G$2:$G$1000,"populated")<>3,_xlfn.MAXIFS(History_Q!$B$2:$B$1000,History_Q!$C$2:$C$1000,"revenue",History_Q!$B$2:$B$1000,">="&((SUMIFS(History_Q!$B$2:$B$1000,History_Q!$A$2:$A$1000,H$6,History_Q!$C$2:$C$1000,"revenue"))-3),History_Q!$B$2:$B$1000,"<="&(SUMIFS(History_Q!$B$2:$B$1000,History_Q!$A$2:$A$1000,H$6,History_Q!$C$2:$C$1000,"revenue")),History_Q!$E$2:$E$1000,"$m",History_Q!$G$2:$G$1000,"populated")-_xlfn.MINIFS(History_Q!$B$2:$B$1000,History_Q!$C$2:$C$1000,"revenue",History_Q!$B$2:$B$1000,">="&((SUMIFS(History_Q!$B$2:$B$1000,History_Q!$A$2:$A$1000,H$6,History_Q!$C$2:$C$1000,"revenue"))-3),History_Q!$B$2:$B$1000,"<="&(SUMIFS(History_Q!$B$2:$B$1000,History_Q!$A$2:$A$1000,H$6,History_Q!$C$2:$C$1000,"revenue")),History_Q!$E$2:$E$1000,"$m",History_Q!$G$2:$G$1000,"populated")<>3,SUMIFS(History_Q!$D$2:$D$1000,History_Q!$C$2:$C$1000,"revenue",History_Q!$B$2:$B$1000,">="&((SUMIFS(History_Q!$B$2:$B$1000,History_Q!$A$2:$A$1000,H$6,History_Q!$C$2:$C$1000,"revenue"))-3),History_Q!$B$2:$B$1000,"<="&(SUMIFS(History_Q!$B$2:$B$1000,History_Q!$A$2:$A$1000,H$6,History_Q!$C$2:$C$1000,"revenue")),History_Q!$E$2:$E$1000,"$m",History_Q!$G$2:$G$1000,"populated")=0),"",SUMIFS(History_Q!$D$2:$D$1000,History_Q!$C$2:$C$1000,"operating_income",History_Q!$B$2:$B$1000,">="&((SUMIFS(History_Q!$B$2:$B$1000,History_Q!$A$2:$A$1000,H$6,History_Q!$C$2:$C$1000,"operating_income"))-3),History_Q!$B$2:$B$1000,"<="&(SUMIFS(History_Q!$B$2:$B$1000,History_Q!$A$2:$A$1000,H$6,History_Q!$C$2:$C$1000,"operating_income")),History_Q!$E$2:$E$1000,"$m",History_Q!$G$2:$G$1000,"populated")/SUMIFS(History_Q!$D$2:$D$1000,History_Q!$C$2:$C$1000,"revenue",History_Q!$B$2:$B$1000,">="&((SUMIFS(History_Q!$B$2:$B$1000,History_Q!$A$2:$A$1000,H$6,History_Q!$C$2:$C$1000,"revenue"))-3),History_Q!$B$2:$B$1000,"<="&(SUMIFS(History_Q!$B$2:$B$1000,History_Q!$A$2:$A$1000,H$6,History_Q!$C$2:$C$1000,"revenue")),History_Q!$E$2:$E$1000,"$m",History_Q!$G$2:$G$1000,"populated")) | I15: =IF(OR(I$6="",COUNTIFS(History_Q!$C$2:$C$1000,"operating_income",History_Q!$B$2:$B$1000,">="&((SUMIFS(History_Q!$B$2:$B$1000,History_Q!$A$2:$A$1000,I$6,History_Q!$C$2:$C$1000,"operating_income"))-3),History_Q!$B$2:$B$1000,"<="&(SUMIFS(History_Q!$B$2:$B$1000,History_Q!$A$2:$A$1000,I$6,History_Q!$C$2:$C$1000,"operating_income")),History_Q!$E$2:$E$1000,"$m",History_Q!$G$2:$G$1000,"populated")<>4,COUNTIFS(History_Q!$C$2:$C$1000,"revenue",History_Q!$B$2:$B$1000,">="&((SUMIFS(History_Q!$B$2:$B$1000,History_Q!$A$2:$A$1000,I$6,History_Q!$C$2:$C$1000,"revenue"))-3),History_Q!$B$2:$B$1000,"<="&(SUMIFS(History_Q!$B$2:$B$1000,History_Q!$A$2:$A$1000,I$6,History_Q!$C$2:$C$1000,"revenue")),History_Q!$E$2:$E$1000,"$m",History_Q!$G$2:$G$1000,"populated")<>4,_xlfn.MAXIFS(History_Q!$B$2:$B$1000,History_Q!$C$2:$C$1000,"operating_income",History_Q!$B$2:$B$1000,">="&((SUMIFS(History_Q!$B$2:$B$1000,History_Q!$A$2:$A$1000,I$6,History_Q!$C$2:$C$1000,"operating_income"))-3),History_Q!$B$2:$B$1000,"<="&(SUMIFS(History_Q!$B$2:$B$1000,History_Q!$A$2:$A$1000,I$6,History_Q!$C$2:$C$1000,"operating_income")),History_Q!$E$2:$E$1000,"$m",History_Q!$G$2:$G$1000,"populated")-_xlfn.MINIFS(History_Q!$B$2:$B$1000,History_Q!$C$2:$C$1000,"operating_income",History_Q!$B$2:$B$1000,">="&((SUMIFS(History_Q!$B$2:$B$1000,History_Q!$A$2:$A$1000,I$6,History_Q!$C$2:$C$1000,"operating_income"))-3),History_Q!$B$2:$B$1000,"<="&(SUMIFS(History_Q!$B$2:$B$1000,History_Q!$A$2:$A$1000,I$6,History_Q!$C$2:$C$1000,"operating_income")),History_Q!$E$2:$E$1000,"$m",History_Q!$G$2:$G$1000,"populated")<>3,_xlfn.MAXIFS(History_Q!$B$2:$B$1000,History_Q!$C$2:$C$1000,"revenue",History_Q!$B$2:$B$1000,">="&((SUMIFS(History_Q!$B$2:$B$1000,History_Q!$A$2:$A$1000,I$6,History_Q!$C$2:$C$1000,"revenue"))-3),History_Q!$B$2:$B$1000,"<="&(SUMIFS(History_Q!$B$2:$B$1000,History_Q!$A$2:$A$1000,I$6,History_Q!$C$2:$C$1000,"revenue")),History_Q!$E$2:$E$1000,"$m",History_Q!$G$2:$G$1000,"populated")-_xlfn.MINIFS(History_Q!$B$2:$B$1000,History_Q!$C$2:$C$1000,"revenue",History_Q!$B$2:$B$1000,">="&((SUMIFS(History_Q!$B$2:$B$1000,History_Q!$A$2:$A$1000,I$6,History_Q!$C$2:$C$1000,"revenue"))-3),History_Q!$B$2:$B$1000,"<="&(SUMIFS(History_Q!$B$2:$B$1000,History_Q!$A$2:$A$1000,I$6,History_Q!$C$2:$C$1000,"revenue")),History_Q!$E$2:$E$1000,"$m",History_Q!$G$2:$G$1000,"populated")<>3,SUMIFS(History_Q!$D$2:$D$1000,History_Q!$C$2:$C$1000,"revenue",History_Q!$B$2:$B$1000,">="&((SUMIFS(History_Q!$B$2:$B$1000,History_Q!$A$2:$A$1000,I$6,History_Q!$C$2:$C$1000,"revenue"))-3),History_Q!$B$2:$B$1000,"<="&(SUMIFS(History_Q!$B$2:$B$1000,History_Q!$A$2:$A$1000,I$6,History_Q!$C$2:$C$1000,"revenue")),History_Q!$E$2:$E$1000,"$m",History_Q!$G$2:$G$1000,"populated")=0),"",SUMIFS(History_Q!$D$2:$D$1000,History_Q!$C$2:$C$1000,"operating_income",History_Q!$B$2:$B$1000,">="&((SUMIFS(History_Q!$B$2:$B$1000,History_Q!$A$2:$A$1000,I$6,History_Q!$C$2:$C$1000,"operating_income"))-3),History_Q!$B$2:$B$1000,"<="&(SUMIFS(History_Q!$B$2:$B$1000,History_Q!$A$2:$A$1000,I$6,History_Q!$C$2:$C$1000,"operating_income")),History_Q!$E$2:$E$1000,"$m",History_Q!$G$2:$G$1000,"populated")/SUMIFS(History_Q!$D$2:$D$1000,History_Q!$C$2:$C$1000,"revenue",History_Q!$B$2:$B$1000,">="&((SUMIFS(History_Q!$B$2:$B$1000,History_Q!$A$2:$A$1000,I$6,History_Q!$C$2:$C$1000,"revenue"))-3),History_Q!$B$2:$B$1000,"<="&(SUMIFS(History_Q!$B$2:$B$1000,History_Q!$A$2:$A$1000,I$6,History_Q!$C$2:$C$1000,"revenue")),History_Q!$E$2:$E$1000,"$m",History_Q!$G$2:$G$1000,"populated")) | ... M15: =IF(OR(M$6="",COUNTIFS(History_Q!$C$2:$C$1000,"operating_income",History_Q!$B$2:$B$1000,">="&((SUMIFS(History_Q!$B$2:$B$1000,History_Q!$A$2:$A$1000,M$6,History_Q!$C$2:$C$1000,"operating_income"))-3),History_Q!$B$2:$B$1000,"<="&(SUMIFS(History_Q!$B$2:$B$1000,History_Q!$A$2:$A$1000,M$6,History_Q!$C$2:$C$1000,"operating_income")),History_Q!$E$2:$E$1000,"$m",History_Q!$G$2:$G$1000,"populated")<>4,COUNTIFS(History_Q!$C$2:$C$1000,"revenue",History_Q!$B$2:$B$1000,">="&((SUMIFS(History_Q!$B$2:$B$1000,History_Q!$A$2:$A$1000,M$6,History_Q!$C$2:$C$1000,"revenue"))-3),History_Q!$B$2:$B$1000,"<="&(SUMIFS(History_Q!$B$2:$B$1000,History_Q!$A$2:$A$1000,M$6,History_Q!$C$2:$C$1000,"revenue")),History_Q!$E$2:$E$1000,"$m",History_Q!$G$2:$G$1000,"populated")<>4,_xlfn.MAXIFS(History_Q!$B$2:$B$1000,History_Q!$C$2:$C$1000,"operating_income",History_Q!$B$2:$B$1000,">="&((SUMIFS(History_Q!$B$2:$B$1000,History_Q!$A$2:$A$1000,M$6,History_Q!$C$2:$C$1000,"operating_income"))-3),History_Q!$B$2:$B$1000,"<="&(SUMIFS(History_Q!$B$2:$B$1000,History_Q!$A$2:$A$1000,M$6,History_Q!$C$2:$C$1000,"operating_income")),History_Q!$E$2:$E$1000,"$m",History_Q!$G$2:$G$1000,"populated")-_xlfn.MINIFS(History_Q!$B$2:$B$1000,History_Q!$C$2:$C$1000,"operating_income",History_Q!$B$2:$B$1000,">="&((SUMIFS(History_Q!$B$2:$B$1000,History_Q!$A$2:$A$1000,M$6,History_Q!$C$2:$C$1000,"operating_income"))-3),History_Q!$B$2:$B$1000,"<="&(SUMIFS(History_Q!$B$2:$B$1000,History_Q!$A$2:$A$1000,M$6,History_Q!$C$2:$C$1000,"operating_income")),History_Q!$E$2:$E$1000,"$m",History_Q!$G$2:$G$1000,"populated")<>3,_xlfn.MAXIFS(History_Q!$B$2:$B$1000,History_Q!$C$2:$C$1000,"revenue",History_Q!$B$2:$B$1000,">="&((SUMIFS(History_Q!$B$2:$B$1000,History_Q!$A$2:$A$1000,M$6,History_Q!$C$2:$C$1000,"revenue"))-3),History_Q!$B$2:$B$1000,"<="&(SUMIFS(History_Q!$B$2:$B$1000,History_Q!$A$2:$A$1000,M$6,History_Q!$C$2:$C$1000,"revenue")),History_Q!$E$2:$E$1000,"$m",History_Q!$G$2:$G$1000,"populated")-_xlfn.MINIFS(History_Q!$B$2:$B$1000,History_Q!$C$2:$C$1000,"revenue",History_Q!$B$2:$B$1000,">="&((SUMIFS(History_Q!$B$2:$B$1000,History_Q!$A$2:$A$1000,M$6,History_Q!$C$2:$C$1000,"revenue"))-3),History_Q!$B$2:$B$1000,"<="&(SUMIFS(History_Q!$B$2:$B$1000,History_Q!$A$2:$A$1000,M$6,History_Q!$C$2:$C$1000,"revenue")),History_Q!$E$2:$E$1000,"$m",History_Q!$G$2:$G$1000,"populated")<>3,SUMIFS(History_Q!$D$2:$D$1000,History_Q!$C$2:$C$1000,"revenue",History_Q!$B$2:$B$1000,">="&((SUMIFS(History_Q!$B$2:$B$1000,History_Q!$A$2:$A$1000,M$6,History_Q!$C$2:$C$1000,"revenue"))-3),History_Q!$B$2:$B$1000,"<="&(SUMIFS(History_Q!$B$2:$B$1000,History_Q!$A$2:$A$1000,M$6,History_Q!$C$2:$C$1000,"revenue")),History_Q!$E$2:$E$1000,"$m",History_Q!$G$2:$G$1000,"populated")=0),"",SUMIFS(History_Q!$D$2:$D$1000,History_Q!$C$2:$C$1000,"operating_income",History_Q!$B$2:$B$1000,">="&((SUMIFS(History_Q!$B$2:$B$1000,History_Q!$A$2:$A$1000,M$6,History_Q!$C$2:$C$1000,"operating_income"))-3),History_Q!$B$2:$B$1000,"<="&(SUMIFS(History_Q!$B$2:$B$1000,History_Q!$A$2:$A$1000,M$6,History_Q!$C$2:$C$1000,"operating_income")),History_Q!$E$2:$E$1000,"$m",History_Q!$G$2:$G$1000,"populated")/SUMIFS(History_Q!$D$2:$D$1000,History_Q!$C$2:$C$1000,"revenue",History_Q!$B$2:$B$1000,">="&((SUMIFS(History_Q!$B$2:$B$1000,History_Q!$A$2:$A$1000,M$6,History_Q!$C$2:$C$1000,"revenue"))-3),History_Q!$B$2:$B$1000,"<="&(SUMIFS(History_Q!$B$2:$B$1000,History_Q!$A$2:$A$1000,M$6,History_Q!$C$2:$C$1000,"revenue")),History_Q!$E$2:$E$1000,"$m",History_Q!$G$2:$G$1000,"populated"))
A16: R&D % of revenue
A17: Core operating
A18: EBITDA (base)
A19: EBITDA margin % | B19: =IF(OR(B18="",B9="",B9=0),"",B18/B9) | C19: =IF(OR(C18="",C9="",C9=0),"",C18/C9) | D19: =IF(OR(D18="",D9="",D9=0),"",D18/D9) | E19: =IF(OR(E18="",E9="",E9=0),"",E18/E9) | F19: =IF(OR(F18="",F9="",F9=0),"",F18/F9) | G19: =IF(OR(G18="",G9="",G9=0),"",G18/G9) | H19: =IF(OR(H18="",H9="",H9=0),"",H18/H9) | I19: =IF(OR(I18="",I9="",I9=0),"",I18/I9) | ... M19: =IF(OR(M18="",M9="",M9=0),"",M18/M9)
A20: EBITDA YoY % | B20: =IF(OR(B$6="",COUNTIFS(History_Q!$C$2:$C$1000,"base_ebitda",History_Q!$B$2:$B$1000,(SUMIFS(History_Q!$B$2:$B$1000,History_Q!$A$2:$A$1000,B$6,History_Q!$C$2:$C$1000,"base_ebitda")),History_Q!$E$2:$E$1000,"$m",History_Q!$G$2:$G$1000,"populated")<>1,COUNTIFS(History_Q!$C$2:$C$1000,"base_ebitda",History_Q!$B$2:$B$1000,(SUMIFS(History_Q!$B$2:$B$1000,History_Q!$A$2:$A$1000,B$6,History_Q!$C$2:$C$1000,"base_ebitda")-4),History_Q!$E$2:$E$1000,"$m",History_Q!$G$2:$G$1000,"populated")<>1,SUMIFS(History_Q!$D$2:$D$1000,History_Q!$C$2:$C$1000,"base_ebitda",History_Q!$B$2:$B$1000,(SUMIFS(History_Q!$B$2:$B$1000,History_Q!$A$2:$A$1000,B$6,History_Q!$C$2:$C$1000,"base_ebitda")-4),History_Q!$E$2:$E$1000,"$m",History_Q!$G$2:$G$1000,"populated")=0),"",SUMIFS(History_Q!$D$2:$D$1000,History_Q!$C$2:$C$1000,"base_ebitda",History_Q!$B$2:$B$1000,(SUMIFS(History_Q!$B$2:$B$1000,History_Q!$A$2:$A$1000,B$6,History_Q!$C$2:$C$1000,"base_ebitda")),History_Q!$E$2:$E$1000,"$m",History_Q!$G$2:$G$1000,"populated")/SUMIFS(History_Q!$D$2:$D$1000,History_Q!$C$2:$C$1000,"base_ebitda",History_Q!$B$2:$B$1000,(SUMIFS(History_Q!$B$2:$B$1000,History_Q!$A$2:$A$1000,B$6,History_Q!$C$2:$C$1000,"base_ebitda")-4),History_Q!$E$2:$E$1000,"$m",History_Q!$G$2:$G$1000,"populated")-1) | C20: =IF(OR(C$6="",COUNTIFS(History_Q!$C$2:$C$1000,"base_ebitda",History_Q!$B$2:$B$1000,(SUMIFS(History_Q!$B$2:$B$1000,History_Q!$A$2:$A$1000,C$6,History_Q!$C$2:$C$1000,"base_ebitda")),History_Q!$E$2:$E$1000,"$m",History_Q!$G$2:$G$1000,"populated")<>1,COUNTIFS(History_Q!$C$2:$C$1000,"base_ebitda",History_Q!$B$2:$B$1000,(SUMIFS(History_Q!$B$2:$B$1000,History_Q!$A$2:$A$1000,C$6,History_Q!$C$2:$C$1000,"base_ebitda")-4),History_Q!$E$2:$E$1000,"$m",History_Q!$G$2:$G$1000,"populated")<>1,SUMIFS(History_Q!$D$2:$D$1000,History_Q!$C$2:$C$1000,"base_ebitda",History_Q!$B$2:$B$1000,(SUMIFS(History_Q!$B$2:$B$1000,History_Q!$A$2:$A$1000,C$6,History_Q!$C$2:$C$1000,"base_ebitda")-4),History_Q!$E$2:$E$1000,"$m",History_Q!$G$2:$G$1000,"populated")=0),"",SUMIFS(History_Q!$D$2:$D$1000,History_Q!$C$2:$C$1000,"base_ebitda",History_Q!$B$2:$B$1000,(SUMIFS(History_Q!$B$2:$B$1000,History_Q!$A$2:$A$1000,C$6,History_Q!$C$2:$C$1000,"base_ebitda")),History_Q!$E$2:$E$1000,"$m",History_Q!$G$2:$G$1000,"populated")/SUMIFS(History_Q!$D$2:$D$1000,History_Q!$C$2:$C$1000,"base_ebitda",History_Q!$B$2:$B$1000,(SUMIFS(History_Q!$B$2:$B$1000,History_Q!$A$2:$A$1000,C$6,History_Q!$C$2:$C$1000,"base_ebitda")-4),History_Q!$E$2:$E$1000,"$m",History_Q!$G$2:$G$1000,"populated")-1) | D20: =IF(OR(D$6="",COUNTIFS(History_Q!$C$2:$C$1000,"base_ebitda",History_Q!$B$2:$B$1000,(SUMIFS(History_Q!$B$2:$B$1000,History_Q!$A$2:$A$1000,D$6,History_Q!$C$2:$C$1000,"base_ebitda")),History_Q!$E$2:$E$1000,"$m",History_Q!$G$2:$G$1000,"populated")<>1,COUNTIFS(History_Q!$C$2:$C$1000,"base_ebitda",History_Q!$B$2:$B$1000,(SUMIFS(History_Q!$B$2:$B$1000,History_Q!$A$2:$A$1000,D$6,History_Q!$C$2:$C$1000,"base_ebitda")-4),History_Q!$E$2:$E$1000,"$m",History_Q!$G$2:$G$1000,"populated")<>1,SUMIFS(History_Q!$D$2:$D$1000,History_Q!$C$2:$C$1000,"base_ebitda",History_Q!$B$2:$B$1000,(SUMIFS(History_Q!$B$2:$B$1000,History_Q!$A$2:$A$1000,D$6,History_Q!$C$2:$C$1000,"base_ebitda")-4),History_Q!$E$2:$E$1000,"$m",History_Q!$G$2:$G$1000,"populated")=0),"",SUMIFS(History_Q!$D$2:$D$1000,History_Q!$C$2:$C$1000,"base_ebitda",History_Q!$B$2:$B$1000,(SUMIFS(History_Q!$B$2:$B$1000,History_Q!$A$2:$A$1000,D$6,History_Q!$C$2:$C$1000,"base_ebitda")),History_Q!$E$2:$E$1000,"$m",History_Q!$G$2:$G$1000,"populated")/SUMIFS(History_Q!$D$2:$D$1000,History_Q!$C$2:$C$1000,"base_ebitda",History_Q!$B$2:$B$1000,(SUMIFS(History_Q!$B$2:$B$1000,History_Q!$A$2:$A$1000,D$6,History_Q!$C$2:$C$1000,"base_ebitda")-4),History_Q!$E$2:$E$1000,"$m",History_Q!$G$2:$G$1000,"populated")-1) | E20: =IF(OR(E$6="",COUNTIFS(History_Q!$C$2:$C$1000,"base_ebitda",History_Q!$B$2:$B$1000,(SUMIFS(History_Q!$B$2:$B$1000,History_Q!$A$2:$A$1000,E$6,History_Q!$C$2:$C$1000,"base_ebitda")),History_Q!$E$2:$E$1000,"$m",History_Q!$G$2:$G$1000,"populated")<>1,COUNTIFS(History_Q!$C$2:$C$1000,"base_ebitda",History_Q!$B$2:$B$1000,(SUMIFS(History_Q!$B$2:$B$1000,History_Q!$A$2:$A$1000,E$6,History_Q!$C$2:$C$1000,"base_ebitda")-4),History_Q!$E$2:$E$1000,"$m",History_Q!$G$2:$G$1000,"populated")<>1,SUMIFS(History_Q!$D$2:$D$1000,History_Q!$C$2:$C$1000,"base_ebitda",History_Q!$B$2:$B$1000,(SUMIFS(History_Q!$B$2:$B$1000,History_Q!$A$2:$A$1000,E$6,History_Q!$C$2:$C$1000,"base_ebitda")-4),History_Q!$E$2:$E$1000,"$m",History_Q!$G$2:$G$1000,"populated")=0),"",SUMIFS(History_Q!$D$2:$D$1000,History_Q!$C$2:$C$1000,"base_ebitda",History_Q!$B$2:$B$1000,(SUMIFS(History_Q!$B$2:$B$1000,History_Q!$A$2:$A$1000,E$6,History_Q!$C$2:$C$1000,"base_ebitda")),History_Q!$E$2:$E$1000,"$m",History_Q!$G$2:$G$1000,"populated")/SUMIFS(History_Q!$D$2:$D$1000,History_Q!$C$2:$C$1000,"base_ebitda",History_Q!$B$2:$B$1000,(SUMIFS(History_Q!$B$2:$B$1000,History_Q!$A$2:$A$1000,E$6,History_Q!$C$2:$C$1000,"base_ebitda")-4),History_Q!$E$2:$E$1000,"$m",History_Q!$G$2:$G$1000,"populated")-1) | F20: =IF(OR(F$6="",COUNTIFS(History_Q!$C$2:$C$1000,"base_ebitda",History_Q!$B$2:$B$1000,(SUMIFS(History_Q!$B$2:$B$1000,History_Q!$A$2:$A$1000,F$6,History_Q!$C$2:$C$1000,"base_ebitda")),History_Q!$E$2:$E$1000,"$m",History_Q!$G$2:$G$1000,"populated")<>1,COUNTIFS(History_Q!$C$2:$C$1000,"base_ebitda",History_Q!$B$2:$B$1000,(SUMIFS(History_Q!$B$2:$B$1000,History_Q!$A$2:$A$1000,F$6,History_Q!$C$2:$C$1000,"base_ebitda")-4),History_Q!$E$2:$E$1000,"$m",History_Q!$G$2:$G$1000,"populated")<>1,SUMIFS(History_Q!$D$2:$D$1000,History_Q!$C$2:$C$1000,"base_ebitda",History_Q!$B$2:$B$1000,(SUMIFS(History_Q!$B$2:$B$1000,History_Q!$A$2:$A$1000,F$6,History_Q!$C$2:$C$1000,"base_ebitda")-4),History_Q!$E$2:$E$1000,"$m",History_Q!$G$2:$G$1000,"populated")=0),"",SUMIFS(History_Q!$D$2:$D$1000,History_Q!$C$2:$C$1000,"base_ebitda",History_Q!$B$2:$B$1000,(SUMIFS(History_Q!$B$2:$B$1000,History_Q!$A$2:$A$1000,F$6,History_Q!$C$2:$C$1000,"base_ebitda")),History_Q!$E$2:$E$1000,"$m",History_Q!$G$2:$G$1000,"populated")/SUMIFS(History_Q!$D$2:$D$1000,History_Q!$C$2:$C$1000,"base_ebitda",History_Q!$B$2:$B$1000,(SUMIFS(History_Q!$B$2:$B$1000,History_Q!$A$2:$A$1000,F$6,History_Q!$C$2:$C$1000,"base_ebitda")-4),History_Q!$E$2:$E$1000,"$m",History_Q!$G$2:$G$1000,"populated")-1) | G20: =IF(OR(G$6="",COUNTIFS(History_Q!$C$2:$C$1000,"base_ebitda",History_Q!$B$2:$B$1000,(SUMIFS(History_Q!$B$2:$B$1000,History_Q!$A$2:$A$1000,G$6,History_Q!$C$2:$C$1000,"base_ebitda")),History_Q!$E$2:$E$1000,"$m",History_Q!$G$2:$G$1000,"populated")<>1,COUNTIFS(History_Q!$C$2:$C$1000,"base_ebitda",History_Q!$B$2:$B$1000,(SUMIFS(History_Q!$B$2:$B$1000,History_Q!$A$2:$A$1000,G$6,History_Q!$C$2:$C$1000,"base_ebitda")-4),History_Q!$E$2:$E$1000,"$m",History_Q!$G$2:$G$1000,"populated")<>1,SUMIFS(History_Q!$D$2:$D$1000,History_Q!$C$2:$C$1000,"base_ebitda",History_Q!$B$2:$B$1000,(SUMIFS(History_Q!$B$2:$B$1000,History_Q!$A$2:$A$1000,G$6,History_Q!$C$2:$C$1000,"base_ebitda")-4),History_Q!$E$2:$E$1000,"$m",History_Q!$G$2:$G$1000,"populated")=0),"",SUMIFS(History_Q!$D$2:$D$1000,History_Q!$C$2:$C$1000,"base_ebitda",History_Q!$B$2:$B$1000,(SUMIFS(History_Q!$B$2:$B$1000,History_Q!$A$2:$A$1000,G$6,History_Q!$C$2:$C$1000,"base_ebitda")),History_Q!$E$2:$E$1000,"$m",History_Q!$G$2:$G$1000,"populated")/SUMIFS(History_Q!$D$2:$D$1000,History_Q!$C$2:$C$1000,"base_ebitda",History_Q!$B$2:$B$1000,(SUMIFS(History_Q!$B$2:$B$1000,History_Q!$A$2:$A$1000,G$6,History_Q!$C$2:$C$1000,"base_ebitda")-4),History_Q!$E$2:$E$1000,"$m",History_Q!$G$2:$G$1000,"populated")-1) | H20: =IF(OR(H$6="",COUNTIFS(History_Q!$C$2:$C$1000,"base_ebitda",History_Q!$B$2:$B$1000,(SUMIFS(History_Q!$B$2:$B$1000,History_Q!$A$2:$A$1000,H$6,History_Q!$C$2:$C$1000,"base_ebitda")),History_Q!$E$2:$E$1000,"$m",History_Q!$G$2:$G$1000,"populated")<>1,COUNTIFS(History_Q!$C$2:$C$1000,"base_ebitda",History_Q!$B$2:$B$1000,(SUMIFS(History_Q!$B$2:$B$1000,History_Q!$A$2:$A$1000,H$6,History_Q!$C$2:$C$1000,"base_ebitda")-4),History_Q!$E$2:$E$1000,"$m",History_Q!$G$2:$G$1000,"populated")<>1,SUMIFS(History_Q!$D$2:$D$1000,History_Q!$C$2:$C$1000,"base_ebitda",History_Q!$B$2:$B$1000,(SUMIFS(History_Q!$B$2:$B$1000,History_Q!$A$2:$A$1000,H$6,History_Q!$C$2:$C$1000,"base_ebitda")-4),History_Q!$E$2:$E$1000,"$m",History_Q!$G$2:$G$1000,"populated")=0),"",SUMIFS(History_Q!$D$2:$D$1000,History_Q!$C$2:$C$1000,"base_ebitda",History_Q!$B$2:$B$1000,(SUMIFS(History_Q!$B$2:$B$1000,History_Q!$A$2:$A$1000,H$6,History_Q!$C$2:$C$1000,"base_ebitda")),History_Q!$E$2:$E$1000,"$m",History_Q!$G$2:$G$1000,"populated")/SUMIFS(History_Q!$D$2:$D$1000,History_Q!$C$2:$C$1000,"base_ebitda",History_Q!$B$2:$B$1000,(SUMIFS(History_Q!$B$2:$B$1000,History_Q!$A$2:$A$1000,H$6,History_Q!$C$2:$C$1000,"base_ebitda")-4),History_Q!$E$2:$E$1000,"$m",History_Q!$G$2:$G$1000,"populated")-1) | I20: =IF(OR(I$6="",COUNTIFS(History_Q!$C$2:$C$1000,"base_ebitda",History_Q!$B$2:$B$1000,(SUMIFS(History_Q!$B$2:$B$1000,History_Q!$A$2:$A$1000,I$6,History_Q!$C$2:$C$1000,"base_ebitda")),History_Q!$E$2:$E$1000,"$m",History_Q!$G$2:$G$1000,"populated")<>1,COUNTIFS(History_Q!$C$2:$C$1000,"base_ebitda",History_Q!$B$2:$B$1000,(SUMIFS(History_Q!$B$2:$B$1000,History_Q!$A$2:$A$1000,I$6,History_Q!$C$2:$C$1000,"base_ebitda")-4),History_Q!$E$2:$E$1000,"$m",History_Q!$G$2:$G$1000,"populated")<>1,SUMIFS(History_Q!$D$2:$D$1000,History_Q!$C$2:$C$1000,"base_ebitda",History_Q!$B$2:$B$1000,(SUMIFS(History_Q!$B$2:$B$1000,History_Q!$A$2:$A$1000,I$6,History_Q!$C$2:$C$1000,"base_ebitda")-4),History_Q!$E$2:$E$1000,"$m",History_Q!$G$2:$G$1000,"populated")=0),"",SUMIFS(History_Q!$D$2:$D$1000,History_Q!$C$2:$C$1000,"base_ebitda",History_Q!$B$2:$B$1000,(SUMIFS(History_Q!$B$2:$B$1000,History_Q!$A$2:$A$1000,I$6,History_Q!$C$2:$C$1000,"base_ebitda")),History_Q!$E$2:$E$1000,"$m",History_Q!$G$2:$G$1000,"populated")/SUMIFS(History_Q!$D$2:$D$1000,History_Q!$C$2:$C$1000,"base_ebitda",History_Q!$B$2:$B$1000,(SUMIFS(History_Q!$B$2:$B$1000,History_Q!$A$2:$A$1000,I$6,History_Q!$C$2:$C$1000,"base_ebitda")-4),History_Q!$E$2:$E$1000,"$m",History_Q!$G$2:$G$1000,"populated")-1) | ... M20: =IF(OR(M$6="",COUNTIFS(History_Q!$C$2:$C$1000,"base_ebitda",History_Q!$B$2:$B$1000,(SUMIFS(History_Q!$B$2:$B$1000,History_Q!$A$2:$A$1000,M$6,History_Q!$C$2:$C$1000,"base_ebitda")),History_Q!$E$2:$E$1000,"$m",History_Q!$G$2:$G$1000,"populated")<>1,COUNTIFS(History_Q!$C$2:$C$1000,"base_ebitda",History_Q!$B$2:$B$1000,(SUMIFS(History_Q!$B$2:$B$1000,History_Q!$A$2:$A$1000,M$6,History_Q!$C$2:$C$1000,"base_ebitda")-4),History_Q!$E$2:$E$1000,"$m",History_Q!$G$2:$G$1000,"populated")<>1,SUMIFS(History_Q!$D$2:$D$1000,History_Q!$C$2:$C$1000,"base_ebitda",History_Q!$B$2:$B$1000,(SUMIFS(History_Q!$B$2:$B$1000,History_Q!$A$2:$A$1000,M$6,History_Q!$C$2:$C$1000,"base_ebitda")-4),History_Q!$E$2:$E$1000,"$m",History_Q!$G$2:$G$1000,"populated")=0),"",SUMIFS(History_Q!$D$2:$D$1000,History_Q!$C$2:$C$1000,"base_ebitda",History_Q!$B$2:$B$1000,(SUMIFS(History_Q!$B$2:$B$1000,History_Q!$A$2:$A$1000,M$6,History_Q!$C$2:$C$1000,"base_ebitda")),History_Q!$E$2:$E$1000,"$m",History_Q!$G$2:$G$1000,"populated")/SUMIFS(History_Q!$D$2:$D$1000,History_Q!$C$2:$C$1000,"base_ebitda",History_Q!$B$2:$B$1000,(SUMIFS(History_Q!$B$2:$B$1000,History_Q!$A$2:$A$1000,M$6,History_Q!$C$2:$C$1000,"base_ebitda")-4),History_Q!$E$2:$E$1000,"$m",History_Q!$G$2:$G$1000,"populated")-1)
A21: EBITDA (base, TTM) | B21: =IF(OR(B$6="",COUNTIFS(History_Q!$C$2:$C$1000,"base_ebitda",History_Q!$B$2:$B$1000,">="&((SUMIFS(History_Q!$B$2:$B$1000,History_Q!$A$2:$A$1000,B$6,History_Q!$C$2:$C$1000,"base_ebitda"))-3),History_Q!$B$2:$B$1000,"<="&(SUMIFS(History_Q!$B$2:$B$1000,History_Q!$A$2:$A$1000,B$6,History_Q!$C$2:$C$1000,"base_ebitda")),History_Q!$E$2:$E$1000,"$m",History_Q!$G$2:$G$1000,"populated")<>4,_xlfn.MAXIFS(History_Q!$B$2:$B$1000,History_Q!$C$2:$C$1000,"base_ebitda",History_Q!$B$2:$B$1000,">="&((SUMIFS(History_Q!$B$2:$B$1000,History_Q!$A$2:$A$1000,B$6,History_Q!$C$2:$C$1000,"base_ebitda"))-3),History_Q!$B$2:$B$1000,"<="&(SUMIFS(History_Q!$B$2:$B$1000,History_Q!$A$2:$A$1000,B$6,History_Q!$C$2:$C$1000,"base_ebitda")),History_Q!$E$2:$E$1000,"$m",History_Q!$G$2:$G$1000,"populated")-_xlfn.MINIFS(History_Q!$B$2:$B$1000,History_Q!$C$2:$C$1000,"base_ebitda",History_Q!$B$2:$B$1000,">="&((SUMIFS(History_Q!$B$2:$B$1000,History_Q!$A$2:$A$1000,B$6,History_Q!$C$2:$C$1000,"base_ebitda"))-3),History_Q!$B$2:$B$1000,"<="&(SUMIFS(History_Q!$B$2:$B$1000,History_Q!$A$2:$A$1000,B$6,History_Q!$C$2:$C$1000,"base_ebitda")),History_Q!$E$2:$E$1000,"$m",History_Q!$G$2:$G$1000,"populated")<>3),"",SUMIFS(History_Q!$D$2:$D$1000,History_Q!$C$2:$C$1000,"base_ebitda",History_Q!$B$2:$B$1000,">="&((SUMIFS(History_Q!$B$2:$B$1000,History_Q!$A$2:$A$1000,B$6,History_Q!$C$2:$C$1000,"base_ebitda"))-3),History_Q!$B$2:$B$1000,"<="&(SUMIFS(History_Q!$B$2:$B$1000,History_Q!$A$2:$A$1000,B$6,History_Q!$C$2:$C$1000,"base_ebitda")),History_Q!$E$2:$E$1000,"$m",History_Q!$G$2:$G$1000,"populated")) | C21: =IF(OR(C$6="",COUNTIFS(History_Q!$C$2:$C$1000,"base_ebitda",History_Q!$B$2:$B$1000,">="&((SUMIFS(History_Q!$B$2:$B$1000,History_Q!$A$2:$A$1000,C$6,History_Q!$C$2:$C$1000,"base_ebitda"))-3),History_Q!$B$2:$B$1000,"<="&(SUMIFS(History_Q!$B$2:$B$1000,History_Q!$A$2:$A$1000,C$6,History_Q!$C$2:$C$1000,"base_ebitda")),History_Q!$E$2:$E$1000,"$m",History_Q!$G$2:$G$1000,"populated")<>4,_xlfn.MAXIFS(History_Q!$B$2:$B$1000,History_Q!$C$2:$C$1000,"base_ebitda",History_Q!$B$2:$B$1000,">="&((SUMIFS(History_Q!$B$2:$B$1000,History_Q!$A$2:$A$1000,C$6,History_Q!$C$2:$C$1000,"base_ebitda"))-3),History_Q!$B$2:$B$1000,"<="&(SUMIFS(History_Q!$B$2:$B$1000,History_Q!$A$2:$A$1000,C$6,History_Q!$C$2:$C$1000,"base_ebitda")),History_Q!$E$2:$E$1000,"$m",History_Q!$G$2:$G$1000,"populated")-_xlfn.MINIFS(History_Q!$B$2:$B$1000,History_Q!$C$2:$C$1000,"base_ebitda",History_Q!$B$2:$B$1000,">="&((SUMIFS(History_Q!$B$2:$B$1000,History_Q!$A$2:$A$1000,C$6,History_Q!$C$2:$C$1000,"base_ebitda"))-3),History_Q!$B$2:$B$1000,"<="&(SUMIFS(History_Q!$B$2:$B$1000,History_Q!$A$2:$A$1000,C$6,History_Q!$C$2:$C$1000,"base_ebitda")),History_Q!$E$2:$E$1000,"$m",History_Q!$G$2:$G$1000,"populated")<>3),"",SUMIFS(History_Q!$D$2:$D$1000,History_Q!$C$2:$C$1000,"base_ebitda",History_Q!$B$2:$B$1000,">="&((SUMIFS(History_Q!$B$2:$B$1000,History_Q!$A$2:$A$1000,C$6,History_Q!$C$2:$C$1000,"base_ebitda"))-3),History_Q!$B$2:$B$1000,"<="&(SUMIFS(History_Q!$B$2:$B$1000,History_Q!$A$2:$A$1000,C$6,History_Q!$C$2:$C$1000,"base_ebitda")),History_Q!$E$2:$E$1000,"$m",History_Q!$G$2:$G$1000,"populated")) | D21: =IF(OR(D$6="",COUNTIFS(History_Q!$C$2:$C$1000,"base_ebitda",History_Q!$B$2:$B$1000,">="&((SUMIFS(History_Q!$B$2:$B$1000,History_Q!$A$2:$A$1000,D$6,History_Q!$C$2:$C$1000,"base_ebitda"))-3),History_Q!$B$2:$B$1000,"<="&(SUMIFS(History_Q!$B$2:$B$1000,History_Q!$A$2:$A$1000,D$6,History_Q!$C$2:$C$1000,"base_ebitda")),History_Q!$E$2:$E$1000,"$m",History_Q!$G$2:$G$1000,"populated")<>4,_xlfn.MAXIFS(History_Q!$B$2:$B$1000,History_Q!$C$2:$C$1000,"base_ebitda",History_Q!$B$2:$B$1000,">="&((SUMIFS(History_Q!$B$2:$B$1000,History_Q!$A$2:$A$1000,D$6,History_Q!$C$2:$C$1000,"base_ebitda"))-3),History_Q!$B$2:$B$1000,"<="&(SUMIFS(History_Q!$B$2:$B$1000,History_Q!$A$2:$A$1000,D$6,History_Q!$C$2:$C$1000,"base_ebitda")),History_Q!$E$2:$E$1000,"$m",History_Q!$G$2:$G$1000,"populated")-_xlfn.MINIFS(History_Q!$B$2:$B$1000,History_Q!$C$2:$C$1000,"base_ebitda",History_Q!$B$2:$B$1000,">="&((SUMIFS(History_Q!$B$2:$B$1000,History_Q!$A$2:$A$1000,D$6,History_Q!$C$2:$C$1000,"base_ebitda"))-3),History_Q!$B$2:$B$1000,"<="&(SUMIFS(History_Q!$B$2:$B$1000,History_Q!$A$2:$A$1000,D$6,History_Q!$C$2:$C$1000,"base_ebitda")),History_Q!$E$2:$E$1000,"$m",History_Q!$G$2:$G$1000,"populated")<>3),"",SUMIFS(History_Q!$D$2:$D$1000,History_Q!$C$2:$C$1000,"base_ebitda",History_Q!$B$2:$B$1000,">="&((SUMIFS(History_Q!$B$2:$B$1000,History_Q!$A$2:$A$1000,D$6,History_Q!$C$2:$C$1000,"base_ebitda"))-3),History_Q!$B$2:$B$1000,"<="&(SUMIFS(History_Q!$B$2:$B$1000,History_Q!$A$2:$A$1000,D$6,History_Q!$C$2:$C$1000,"base_ebitda")),History_Q!$E$2:$E$1000,"$m",History_Q!$G$2:$G$1000,"populated")) | E21: =IF(OR(E$6="",COUNTIFS(History_Q!$C$2:$C$1000,"base_ebitda",History_Q!$B$2:$B$1000,">="&((SUMIFS(History_Q!$B$2:$B$1000,History_Q!$A$2:$A$1000,E$6,History_Q!$C$2:$C$1000,"base_ebitda"))-3),History_Q!$B$2:$B$1000,"<="&(SUMIFS(History_Q!$B$2:$B$1000,History_Q!$A$2:$A$1000,E$6,History_Q!$C$2:$C$1000,"base_ebitda")),History_Q!$E$2:$E$1000,"$m",History_Q!$G$2:$G$1000,"populated")<>4,_xlfn.MAXIFS(History_Q!$B$2:$B$1000,History_Q!$C$2:$C$1000,"base_ebitda",History_Q!$B$2:$B$1000,">="&((SUMIFS(History_Q!$B$2:$B$1000,History_Q!$A$2:$A$1000,E$6,History_Q!$C$2:$C$1000,"base_ebitda"))-3),History_Q!$B$2:$B$1000,"<="&(SUMIFS(History_Q!$B$2:$B$1000,History_Q!$A$2:$A$1000,E$6,History_Q!$C$2:$C$1000,"base_ebitda")),History_Q!$E$2:$E$1000,"$m",History_Q!$G$2:$G$1000,"populated")-_xlfn.MINIFS(History_Q!$B$2:$B$1000,History_Q!$C$2:$C$1000,"base_ebitda",History_Q!$B$2:$B$1000,">="&((SUMIFS(History_Q!$B$2:$B$1000,History_Q!$A$2:$A$1000,E$6,History_Q!$C$2:$C$1000,"base_ebitda"))-3),History_Q!$B$2:$B$1000,"<="&(SUMIFS(History_Q!$B$2:$B$1000,History_Q!$A$2:$A$1000,E$6,History_Q!$C$2:$C$1000,"base_ebitda")),History_Q!$E$2:$E$1000,"$m",History_Q!$G$2:$G$1000,"populated")<>3),"",SUMIFS(History_Q!$D$2:$D$1000,History_Q!$C$2:$C$1000,"base_ebitda",History_Q!$B$2:$B$1000,">="&((SUMIFS(History_Q!$B$2:$B$1000,History_Q!$A$2:$A$1000,E$6,History_Q!$C$2:$C$1000,"base_ebitda"))-3),History_Q!$B$2:$B$1000,"<="&(SUMIFS(History_Q!$B$2:$B$1000,History_Q!$A$2:$A$1000,E$6,History_Q!$C$2:$C$1000,"base_ebitda")),History_Q!$E$2:$E$1000,"$m",History_Q!$G$2:$G$1000,"populated")) | F21: =IF(OR(F$6="",COUNTIFS(History_Q!$C$2:$C$1000,"base_ebitda",History_Q!$B$2:$B$1000,">="&((SUMIFS(History_Q!$B$2:$B$1000,History_Q!$A$2:$A$1000,F$6,History_Q!$C$2:$C$1000,"base_ebitda"))-3),History_Q!$B$2:$B$1000,"<="&(SUMIFS(History_Q!$B$2:$B$1000,History_Q!$A$2:$A$1000,F$6,History_Q!$C$2:$C$1000,"base_ebitda")),History_Q!$E$2:$E$1000,"$m",History_Q!$G$2:$G$1000,"populated")<>4,_xlfn.MAXIFS(History_Q!$B$2:$B$1000,History_Q!$C$2:$C$1000,"base_ebitda",History_Q!$B$2:$B$1000,">="&((SUMIFS(History_Q!$B$2:$B$1000,History_Q!$A$2:$A$1000,F$6,History_Q!$C$2:$C$1000,"base_ebitda"))-3),History_Q!$B$2:$B$1000,"<="&(SUMIFS(History_Q!$B$2:$B$1000,History_Q!$A$2:$A$1000,F$6,History_Q!$C$2:$C$1000,"base_ebitda")),History_Q!$E$2:$E$1000,"$m",History_Q!$G$2:$G$1000,"populated")-_xlfn.MINIFS(History_Q!$B$2:$B$1000,History_Q!$C$2:$C$1000,"base_ebitda",History_Q!$B$2:$B$1000,">="&((SUMIFS(History_Q!$B$2:$B$1000,History_Q!$A$2:$A$1000,F$6,History_Q!$C$2:$C$1000,"base_ebitda"))-3),History_Q!$B$2:$B$1000,"<="&(SUMIFS(History_Q!$B$2:$B$1000,History_Q!$A$2:$A$1000,F$6,History_Q!$C$2:$C$1000,"base_ebitda")),History_Q!$E$2:$E$1000,"$m",History_Q!$G$2:$G$1000,"populated")<>3),"",SUMIFS(History_Q!$D$2:$D$1000,History_Q!$C$2:$C$1000,"base_ebitda",History_Q!$B$2:$B$1000,">="&((SUMIFS(History_Q!$B$2:$B$1000,History_Q!$A$2:$A$1000,F$6,History_Q!$C$2:$C$1000,"base_ebitda"))-3),History_Q!$B$2:$B$1000,"<="&(SUMIFS(History_Q!$B$2:$B$1000,History_Q!$A$2:$A$1000,F$6,History_Q!$C$2:$C$1000,"base_ebitda")),History_Q!$E$2:$E$1000,"$m",History_Q!$G$2:$G$1000,"populated")) | G21: =IF(OR(G$6="",COUNTIFS(History_Q!$C$2:$C$1000,"base_ebitda",History_Q!$B$2:$B$1000,">="&((SUMIFS(History_Q!$B$2:$B$1000,History_Q!$A$2:$A$1000,G$6,History_Q!$C$2:$C$1000,"base_ebitda"))-3),History_Q!$B$2:$B$1000,"<="&(SUMIFS(History_Q!$B$2:$B$1000,History_Q!$A$2:$A$1000,G$6,History_Q!$C$2:$C$1000,"base_ebitda")),History_Q!$E$2:$E$1000,"$m",History_Q!$G$2:$G$1000,"populated")<>4,_xlfn.MAXIFS(History_Q!$B$2:$B$1000,History_Q!$C$2:$C$1000,"base_ebitda",History_Q!$B$2:$B$1000,">="&((SUMIFS(History_Q!$B$2:$B$1000,History_Q!$A$2:$A$1000,G$6,History_Q!$C$2:$C$1000,"base_ebitda"))-3),History_Q!$B$2:$B$1000,"<="&(SUMIFS(History_Q!$B$2:$B$1000,History_Q!$A$2:$A$1000,G$6,History_Q!$C$2:$C$1000,"base_ebitda")),History_Q!$E$2:$E$1000,"$m",History_Q!$G$2:$G$1000,"populated")-_xlfn.MINIFS(History_Q!$B$2:$B$1000,History_Q!$C$2:$C$1000,"base_ebitda",History_Q!$B$2:$B$1000,">="&((SUMIFS(History_Q!$B$2:$B$1000,History_Q!$A$2:$A$1000,G$6,History_Q!$C$2:$C$1000,"base_ebitda"))-3),History_Q!$B$2:$B$1000,"<="&(SUMIFS(History_Q!$B$2:$B$1000,History_Q!$A$2:$A$1000,G$6,History_Q!$C$2:$C$1000,"base_ebitda")),History_Q!$E$2:$E$1000,"$m",History_Q!$G$2:$G$1000,"populated")<>3),"",SUMIFS(History_Q!$D$2:$D$1000,History_Q!$C$2:$C$1000,"base_ebitda",History_Q!$B$2:$B$1000,">="&((SUMIFS(History_Q!$B$2:$B$1000,History_Q!$A$2:$A$1000,G$6,History_Q!$C$2:$C$1000,"base_ebitda"))-3),History_Q!$B$2:$B$1000,"<="&(SUMIFS(History_Q!$B$2:$B$1000,History_Q!$A$2:$A$1000,G$6,History_Q!$C$2:$C$1000,"base_ebitda")),History_Q!$E$2:$E$1000,"$m",History_Q!$G$2:$G$1000,"populated")) | H21: =IF(OR(H$6="",COUNTIFS(History_Q!$C$2:$C$1000,"base_ebitda",History_Q!$B$2:$B$1000,">="&((SUMIFS(History_Q!$B$2:$B$1000,History_Q!$A$2:$A$1000,H$6,History_Q!$C$2:$C$1000,"base_ebitda"))-3),History_Q!$B$2:$B$1000,"<="&(SUMIFS(History_Q!$B$2:$B$1000,History_Q!$A$2:$A$1000,H$6,History_Q!$C$2:$C$1000,"base_ebitda")),History_Q!$E$2:$E$1000,"$m",History_Q!$G$2:$G$1000,"populated")<>4,_xlfn.MAXIFS(History_Q!$B$2:$B$1000,History_Q!$C$2:$C$1000,"base_ebitda",History_Q!$B$2:$B$1000,">="&((SUMIFS(History_Q!$B$2:$B$1000,History_Q!$A$2:$A$1000,H$6,History_Q!$C$2:$C$1000,"base_ebitda"))-3),History_Q!$B$2:$B$1000,"<="&(SUMIFS(History_Q!$B$2:$B$1000,History_Q!$A$2:$A$1000,H$6,History_Q!$C$2:$C$1000,"base_ebitda")),History_Q!$E$2:$E$1000,"$m",History_Q!$G$2:$G$1000,"populated")-_xlfn.MINIFS(History_Q!$B$2:$B$1000,History_Q!$C$2:$C$1000,"base_ebitda",History_Q!$B$2:$B$1000,">="&((SUMIFS(History_Q!$B$2:$B$1000,History_Q!$A$2:$A$1000,H$6,History_Q!$C$2:$C$1000,"base_ebitda"))-3),History_Q!$B$2:$B$1000,"<="&(SUMIFS(History_Q!$B$2:$B$1000,History_Q!$A$2:$A$1000,H$6,History_Q!$C$2:$C$1000,"base_ebitda")),History_Q!$E$2:$E$1000,"$m",History_Q!$G$2:$G$1000,"populated")<>3),"",SUMIFS(History_Q!$D$2:$D$1000,History_Q!$C$2:$C$1000,"base_ebitda",History_Q!$B$2:$B$1000,">="&((SUMIFS(History_Q!$B$2:$B$1000,History_Q!$A$2:$A$1000,H$6,History_Q!$C$2:$C$1000,"base_ebitda"))-3),History_Q!$B$2:$B$1000,"<="&(SUMIFS(History_Q!$B$2:$B$1000,History_Q!$A$2:$A$1000,H$6,History_Q!$C$2:$C$1000,"base_ebitda")),History_Q!$E$2:$E$1000,"$m",History_Q!$G$2:$G$1000,"populated")) | I21: =IF(OR(I$6="",COUNTIFS(History_Q!$C$2:$C$1000,"base_ebitda",History_Q!$B$2:$B$1000,">="&((SUMIFS(History_Q!$B$2:$B$1000,History_Q!$A$2:$A$1000,I$6,History_Q!$C$2:$C$1000,"base_ebitda"))-3),History_Q!$B$2:$B$1000,"<="&(SUMIFS(History_Q!$B$2:$B$1000,History_Q!$A$2:$A$1000,I$6,History_Q!$C$2:$C$1000,"base_ebitda")),History_Q!$E$2:$E$1000,"$m",History_Q!$G$2:$G$1000,"populated")<>4,_xlfn.MAXIFS(History_Q!$B$2:$B$1000,History_Q!$C$2:$C$1000,"base_ebitda",History_Q!$B$2:$B$1000,">="&((SUMIFS(History_Q!$B$2:$B$1000,History_Q!$A$2:$A$1000,I$6,History_Q!$C$2:$C$1000,"base_ebitda"))-3),History_Q!$B$2:$B$1000,"<="&(SUMIFS(History_Q!$B$2:$B$1000,History_Q!$A$2:$A$1000,I$6,History_Q!$C$2:$C$1000,"base_ebitda")),History_Q!$E$2:$E$1000,"$m",History_Q!$G$2:$G$1000,"populated")-_xlfn.MINIFS(History_Q!$B$2:$B$1000,History_Q!$C$2:$C$1000,"base_ebitda",History_Q!$B$2:$B$1000,">="&((SUMIFS(History_Q!$B$2:$B$1000,History_Q!$A$2:$A$1000,I$6,History_Q!$C$2:$C$1000,"base_ebitda"))-3),History_Q!$B$2:$B$1000,"<="&(SUMIFS(History_Q!$B$2:$B$1000,History_Q!$A$2:$A$1000,I$6,History_Q!$C$2:$C$1000,"base_ebitda")),History_Q!$E$2:$E$1000,"$m",History_Q!$G$2:$G$1000,"populated")<>3),"",SUMIFS(History_Q!$D$2:$D$1000,History_Q!$C$2:$C$1000,"base_ebitda",History_Q!$B$2:$B$1000,">="&((SUMIFS(History_Q!$B$2:$B$1000,History_Q!$A$2:$A$1000,I$6,History_Q!$C$2:$C$1000,"base_ebitda"))-3),History_Q!$B$2:$B$1000,"<="&(SUMIFS(History_Q!$B$2:$B$1000,History_Q!$A$2:$A$1000,I$6,History_Q!$C$2:$C$1000,"base_ebitda")),History_Q!$E$2:$E$1000,"$m",History_Q!$G$2:$G$1000,"populated")) | ... M21: =IF(OR(M$6="",COUNTIFS(History_Q!$C$2:$C$1000,"base_ebitda",History_Q!$B$2:$B$1000,">="&((SUMIFS(History_Q!$B$2:$B$1000,History_Q!$A$2:$A$1000,M$6,History_Q!$C$2:$C$1000,"base_ebitda"))-3),History_Q!$B$2:$B$1000,"<="&(SUMIFS(History_Q!$B$2:$B$1000,History_Q!$A$2:$A$1000,M$6,History_Q!$C$2:$C$1000,"base_ebitda")),History_Q!$E$2:$E$1000,"$m",History_Q!$G$2:$G$1000,"populated")<>4,_xlfn.MAXIFS(History_Q!$B$2:$B$1000,History_Q!$C$2:$C$1000,"base_ebitda",History_Q!$B$2:$B$1000,">="&((SUMIFS(History_Q!$B$2:$B$1000,History_Q!$A$2:$A$1000,M$6,History_Q!$C$2:$C$1000,"base_ebitda"))-3),History_Q!$B$2:$B$1000,"<="&(SUMIFS(History_Q!$B$2:$B$1000,History_Q!$A$2:$A$1000,M$6,History_Q!$C$2:$C$1000,"base_ebitda")),History_Q!$E$2:$E$1000,"$m",History_Q!$G$2:$G$1000,"populated")-_xlfn.MINIFS(History_Q!$B$2:$B$1000,History_Q!$C$2:$C$1000,"base_ebitda",History_Q!$B$2:$B$1000,">="&((SUMIFS(History_Q!$B$2:$B$1000,History_Q!$A$2:$A$1000,M$6,History_Q!$C$2:$C$1000,"base_ebitda"))-3),History_Q!$B$2:$B$1000,"<="&(SUMIFS(History_Q!$B$2:$B$1000,History_Q!$A$2:$A$1000,M$6,History_Q!$C$2:$C$1000,"base_ebitda")),History_Q!$E$2:$E$1000,"$m",History_Q!$G$2:$G$1000,"populated")<>3),"",SUMIFS(History_Q!$D$2:$D$1000,History_Q!$C$2:$C$1000,"base_ebitda",History_Q!$B$2:$B$1000,">="&((SUMIFS(History_Q!$B$2:$B$1000,History_Q!$A$2:$A$1000,M$6,History_Q!$C$2:$C$1000,"base_ebitda"))-3),History_Q!$B$2:$B$1000,"<="&(SUMIFS(History_Q!$B$2:$B$1000,History_Q!$A$2:$A$1000,M$6,History_Q!$C$2:$C$1000,"base_ebitda")),History_Q!$E$2:$E$1000,"$m",History_Q!$G$2:$G$1000,"populated"))
A22: EBITDA margin (TTM) | B22: =IF(OR(B21="",B10="",B10=0),"",B21/B10) | C22: =IF(OR(C21="",C10="",C10=0),"",C21/C10) | D22: =IF(OR(D21="",D10="",D10=0),"",D21/D10) | E22: =IF(OR(E21="",E10="",E10=0),"",E21/E10) | F22: =IF(OR(F21="",F10="",F10=0),"",F21/F10) | G22: =IF(OR(G21="",G10="",G10=0),"",G21/G10) | H22: =IF(OR(H21="",H10="",H10=0),"",H21/H10) | I22: =IF(OR(I21="",I10="",I10=0),"",I21/I10) | ... M22: =IF(OR(M21="",M10="",M10=0),"",M21/M10)
A23: Adjusted operating
A24: Adjusted EBITDA
A25: Adjusted EBITDA (TTM) | B25: =IF(OR(B$6="",COUNTIFS(History_Q!$C$2:$C$1000,"adjusted_ebitda",History_Q!$B$2:$B$1000,">="&((SUMIFS(History_Q!$B$2:$B$1000,History_Q!$A$2:$A$1000,B$6,History_Q!$C$2:$C$1000,"adjusted_ebitda"))-3),History_Q!$B$2:$B$1000,"<="&(SUMIFS(History_Q!$B$2:$B$1000,History_Q!$A$2:$A$1000,B$6,History_Q!$C$2:$C$1000,"adjusted_ebitda")),History_Q!$E$2:$E$1000,"$m",History_Q!$G$2:$G$1000,"populated")<>4,_xlfn.MAXIFS(History_Q!$B$2:$B$1000,History_Q!$C$2:$C$1000,"adjusted_ebitda",History_Q!$B$2:$B$1000,">="&((SUMIFS(History_Q!$B$2:$B$1000,History_Q!$A$2:$A$1000,B$6,History_Q!$C$2:$C$1000,"adjusted_ebitda"))-3),History_Q!$B$2:$B$1000,"<="&(SUMIFS(History_Q!$B$2:$B$1000,History_Q!$A$2:$A$1000,B$6,History_Q!$C$2:$C$1000,"adjusted_ebitda")),History_Q!$E$2:$E$1000,"$m",History_Q!$G$2:$G$1000,"populated")-_xlfn.MINIFS(History_Q!$B$2:$B$1000,History_Q!$C$2:$C$1000,"adjusted_ebitda",History_Q!$B$2:$B$1000,">="&((SUMIFS(History_Q!$B$2:$B$1000,History_Q!$A$2:$A$1000,B$6,History_Q!$C$2:$C$1000,"adjusted_ebitda"))-3),History_Q!$B$2:$B$1000,"<="&(SUMIFS(History_Q!$B$2:$B$1000,History_Q!$A$2:$A$1000,B$6,History_Q!$C$2:$C$1000,"adjusted_ebitda")),History_Q!$E$2:$E$1000,"$m",History_Q!$G$2:$G$1000,"populated")<>3),"",SUMIFS(History_Q!$D$2:$D$1000,History_Q!$C$2:$C$1000,"adjusted_ebitda",History_Q!$B$2:$B$1000,">="&((SUMIFS(History_Q!$B$2:$B$1000,History_Q!$A$2:$A$1000,B$6,History_Q!$C$2:$C$1000,"adjusted_ebitda"))-3),History_Q!$B$2:$B$1000,"<="&(SUMIFS(History_Q!$B$2:$B$1000,History_Q!$A$2:$A$1000,B$6,History_Q!$C$2:$C$1000,"adjusted_ebitda")),History_Q!$E$2:$E$1000,"$m",History_Q!$G$2:$G$1000,"populated")) | C25: =IF(OR(C$6="",COUNTIFS(History_Q!$C$2:$C$1000,"adjusted_ebitda",History_Q!$B$2:$B$1000,">="&((SUMIFS(History_Q!$B$2:$B$1000,History_Q!$A$2:$A$1000,C$6,History_Q!$C$2:$C$1000,"adjusted_ebitda"))-3),History_Q!$B$2:$B$1000,"<="&(SUMIFS(History_Q!$B$2:$B$1000,History_Q!$A$2:$A$1000,C$6,History_Q!$C$2:$C$1000,"adjusted_ebitda")),History_Q!$E$2:$E$1000,"$m",History_Q!$G$2:$G$1000,"populated")<>4,_xlfn.MAXIFS(History_Q!$B$2:$B$1000,History_Q!$C$2:$C$1000,"adjusted_ebitda",History_Q!$B$2:$B$1000,">="&((SUMIFS(History_Q!$B$2:$B$1000,History_Q!$A$2:$A$1000,C$6,History_Q!$C$2:$C$1000,"adjusted_ebitda"))-3),History_Q!$B$2:$B$1000,"<="&(SUMIFS(History_Q!$B$2:$B$1000,History_Q!$A$2:$A$1000,C$6,History_Q!$C$2:$C$1000,"adjusted_ebitda")),History_Q!$E$2:$E$1000,"$m",History_Q!$G$2:$G$1000,"populated")-_xlfn.MINIFS(History_Q!$B$2:$B$1000,History_Q!$C$2:$C$1000,"adjusted_ebitda",History_Q!$B$2:$B$1000,">="&((SUMIFS(History_Q!$B$2:$B$1000,History_Q!$A$2:$A$1000,C$6,History_Q!$C$2:$C$1000,"adjusted_ebitda"))-3),History_Q!$B$2:$B$1000,"<="&(SUMIFS(History_Q!$B$2:$B$1000,History_Q!$A$2:$A$1000,C$6,History_Q!$C$2:$C$1000,"adjusted_ebitda")),History_Q!$E$2:$E$1000,"$m",History_Q!$G$2:$G$1000,"populated")<>3),"",SUMIFS(History_Q!$D$2:$D$1000,History_Q!$C$2:$C$1000,"adjusted_ebitda",History_Q!$B$2:$B$1000,">="&((SUMIFS(History_Q!$B$2:$B$1000,History_Q!$A$2:$A$1000,C$6,History_Q!$C$2:$C$1000,"adjusted_ebitda"))-3),History_Q!$B$2:$B$1000,"<="&(SUMIFS(History_Q!$B$2:$B$1000,History_Q!$A$2:$A$1000,C$6,History_Q!$C$2:$C$1000,"adjusted_ebitda")),History_Q!$E$2:$E$1000,"$m",History_Q!$G$2:$G$1000,"populated")) | D25: =IF(OR(D$6="",COUNTIFS(History_Q!$C$2:$C$1000,"adjusted_ebitda",History_Q!$B$2:$B$1000,">="&((SUMIFS(History_Q!$B$2:$B$1000,History_Q!$A$2:$A$1000,D$6,History_Q!$C$2:$C$1000,"adjusted_ebitda"))-3),History_Q!$B$2:$B$1000,"<="&(SUMIFS(History_Q!$B$2:$B$1000,History_Q!$A$2:$A$1000,D$6,History_Q!$C$2:$C$1000,"adjusted_ebitda")),History_Q!$E$2:$E$1000,"$m",History_Q!$G$2:$G$1000,"populated")<>4,_xlfn.MAXIFS(History_Q!$B$2:$B$1000,History_Q!$C$2:$C$1000,"adjusted_ebitda",History_Q!$B$2:$B$1000,">="&((SUMIFS(History_Q!$B$2:$B$1000,History_Q!$A$2:$A$1000,D$6,History_Q!$C$2:$C$1000,"adjusted_ebitda"))-3),History_Q!$B$2:$B$1000,"<="&(SUMIFS(History_Q!$B$2:$B$1000,History_Q!$A$2:$A$1000,D$6,History_Q!$C$2:$C$1000,"adjusted_ebitda")),History_Q!$E$2:$E$1000,"$m",History_Q!$G$2:$G$1000,"populated")-_xlfn.MINIFS(History_Q!$B$2:$B$1000,History_Q!$C$2:$C$1000,"adjusted_ebitda",History_Q!$B$2:$B$1000,">="&((SUMIFS(History_Q!$B$2:$B$1000,History_Q!$A$2:$A$1000,D$6,History_Q!$C$2:$C$1000,"adjusted_ebitda"))-3),History_Q!$B$2:$B$1000,"<="&(SUMIFS(History_Q!$B$2:$B$1000,History_Q!$A$2:$A$1000,D$6,History_Q!$C$2:$C$1000,"adjusted_ebitda")),History_Q!$E$2:$E$1000,"$m",History_Q!$G$2:$G$1000,"populated")<>3),"",SUMIFS(History_Q!$D$2:$D$1000,History_Q!$C$2:$C$1000,"adjusted_ebitda",History_Q!$B$2:$B$1000,">="&((SUMIFS(History_Q!$B$2:$B$1000,History_Q!$A$2:$A$1000,D$6,History_Q!$C$2:$C$1000,"adjusted_ebitda"))-3),History_Q!$B$2:$B$1000,"<="&(SUMIFS(History_Q!$B$2:$B$1000,History_Q!$A$2:$A$1000,D$6,History_Q!$C$2:$C$1000,"adjusted_ebitda")),History_Q!$E$2:$E$1000,"$m",History_Q!$G$2:$G$1000,"populated")) | E25: =IF(OR(E$6="",COUNTIFS(History_Q!$C$2:$C$1000,"adjusted_ebitda",History_Q!$B$2:$B$1000,">="&((SUMIFS(History_Q!$B$2:$B$1000,History_Q!$A$2:$A$1000,E$6,History_Q!$C$2:$C$1000,"adjusted_ebitda"))-3),History_Q!$B$2:$B$1000,"<="&(SUMIFS(History_Q!$B$2:$B$1000,History_Q!$A$2:$A$1000,E$6,History_Q!$C$2:$C$1000,"adjusted_ebitda")),History_Q!$E$2:$E$1000,"$m",History_Q!$G$2:$G$1000,"populated")<>4,_xlfn.MAXIFS(History_Q!$B$2:$B$1000,History_Q!$C$2:$C$1000,"adjusted_ebitda",History_Q!$B$2:$B$1000,">="&((SUMIFS(History_Q!$B$2:$B$1000,History_Q!$A$2:$A$1000,E$6,History_Q!$C$2:$C$1000,"adjusted_ebitda"))-3),History_Q!$B$2:$B$1000,"<="&(SUMIFS(History_Q!$B$2:$B$1000,History_Q!$A$2:$A$1000,E$6,History_Q!$C$2:$C$1000,"adjusted_ebitda")),History_Q!$E$2:$E$1000,"$m",History_Q!$G$2:$G$1000,"populated")-_xlfn.MINIFS(History_Q!$B$2:$B$1000,History_Q!$C$2:$C$1000,"adjusted_ebitda",History_Q!$B$2:$B$1000,">="&((SUMIFS(History_Q!$B$2:$B$1000,History_Q!$A$2:$A$1000,E$6,History_Q!$C$2:$C$1000,"adjusted_ebitda"))-3),History_Q!$B$2:$B$1000,"<="&(SUMIFS(History_Q!$B$2:$B$1000,History_Q!$A$2:$A$1000,E$6,History_Q!$C$2:$C$1000,"adjusted_ebitda")),History_Q!$E$2:$E$1000,"$m",History_Q!$G$2:$G$1000,"populated")<>3),"",SUMIFS(History_Q!$D$2:$D$1000,History_Q!$C$2:$C$1000,"adjusted_ebitda",History_Q!$B$2:$B$1000,">="&((SUMIFS(History_Q!$B$2:$B$1000,History_Q!$A$2:$A$1000,E$6,History_Q!$C$2:$C$1000,"adjusted_ebitda"))-3),History_Q!$B$2:$B$1000,"<="&(SUMIFS(History_Q!$B$2:$B$1000,History_Q!$A$2:$A$1000,E$6,History_Q!$C$2:$C$1000,"adjusted_ebitda")),History_Q!$E$2:$E$1000,"$m",History_Q!$G$2:$G$1000,"populated")) | F25: =IF(OR(F$6="",COUNTIFS(History_Q!$C$2:$C$1000,"adjusted_ebitda",History_Q!$B$2:$B$1000,">="&((SUMIFS(History_Q!$B$2:$B$1000,History_Q!$A$2:$A$1000,F$6,History_Q!$C$2:$C$1000,"adjusted_ebitda"))-3),History_Q!$B$2:$B$1000,"<="&(SUMIFS(History_Q!$B$2:$B$1000,History_Q!$A$2:$A$1000,F$6,History_Q!$C$2:$C$1000,"adjusted_ebitda")),History_Q!$E$2:$E$1000,"$m",History_Q!$G$2:$G$1000,"populated")<>4,_xlfn.MAXIFS(History_Q!$B$2:$B$1000,History_Q!$C$2:$C$1000,"adjusted_ebitda",History_Q!$B$2:$B$1000,">="&((SUMIFS(History_Q!$B$2:$B$1000,History_Q!$A$2:$A$1000,F$6,History_Q!$C$2:$C$1000,"adjusted_ebitda"))-3),History_Q!$B$2:$B$1000,"<="&(SUMIFS(History_Q!$B$2:$B$1000,History_Q!$A$2:$A$1000,F$6,History_Q!$C$2:$C$1000,"adjusted_ebitda")),History_Q!$E$2:$E$1000,"$m",History_Q!$G$2:$G$1000,"populated")-_xlfn.MINIFS(History_Q!$B$2:$B$1000,History_Q!$C$2:$C$1000,"adjusted_ebitda",History_Q!$B$2:$B$1000,">="&((SUMIFS(History_Q!$B$2:$B$1000,History_Q!$A$2:$A$1000,F$6,History_Q!$C$2:$C$1000,"adjusted_ebitda"))-3),History_Q!$B$2:$B$1000,"<="&(SUMIFS(History_Q!$B$2:$B$1000,History_Q!$A$2:$A$1000,F$6,History_Q!$C$2:$C$1000,"adjusted_ebitda")),History_Q!$E$2:$E$1000,"$m",History_Q!$G$2:$G$1000,"populated")<>3),"",SUMIFS(History_Q!$D$2:$D$1000,History_Q!$C$2:$C$1000,"adjusted_ebitda",History_Q!$B$2:$B$1000,">="&((SUMIFS(History_Q!$B$2:$B$1000,History_Q!$A$2:$A$1000,F$6,History_Q!$C$2:$C$1000,"adjusted_ebitda"))-3),History_Q!$B$2:$B$1000,"<="&(SUMIFS(History_Q!$B$2:$B$1000,History_Q!$A$2:$A$1000,F$6,History_Q!$C$2:$C$1000,"adjusted_ebitda")),History_Q!$E$2:$E$1000,"$m",History_Q!$G$2:$G$1000,"populated")) | G25: =IF(OR(G$6="",COUNTIFS(History_Q!$C$2:$C$1000,"adjusted_ebitda",History_Q!$B$2:$B$1000,">="&((SUMIFS(History_Q!$B$2:$B$1000,History_Q!$A$2:$A$1000,G$6,History_Q!$C$2:$C$1000,"adjusted_ebitda"))-3),History_Q!$B$2:$B$1000,"<="&(SUMIFS(History_Q!$B$2:$B$1000,History_Q!$A$2:$A$1000,G$6,History_Q!$C$2:$C$1000,"adjusted_ebitda")),History_Q!$E$2:$E$1000,"$m",History_Q!$G$2:$G$1000,"populated")<>4,_xlfn.MAXIFS(History_Q!$B$2:$B$1000,History_Q!$C$2:$C$1000,"adjusted_ebitda",History_Q!$B$2:$B$1000,">="&((SUMIFS(History_Q!$B$2:$B$1000,History_Q!$A$2:$A$1000,G$6,History_Q!$C$2:$C$1000,"adjusted_ebitda"))-3),History_Q!$B$2:$B$1000,"<="&(SUMIFS(History_Q!$B$2:$B$1000,History_Q!$A$2:$A$1000,G$6,History_Q!$C$2:$C$1000,"adjusted_ebitda")),History_Q!$E$2:$E$1000,"$m",History_Q!$G$2:$G$1000,"populated")-_xlfn.MINIFS(History_Q!$B$2:$B$1000,History_Q!$C$2:$C$1000,"adjusted_ebitda",History_Q!$B$2:$B$1000,">="&((SUMIFS(History_Q!$B$2:$B$1000,History_Q!$A$2:$A$1000,G$6,History_Q!$C$2:$C$1000,"adjusted_ebitda"))-3),History_Q!$B$2:$B$1000,"<="&(SUMIFS(History_Q!$B$2:$B$1000,History_Q!$A$2:$A$1000,G$6,History_Q!$C$2:$C$1000,"adjusted_ebitda")),History_Q!$E$2:$E$1000,"$m",History_Q!$G$2:$G$1000,"populated")<>3),"",SUMIFS(History_Q!$D$2:$D$1000,History_Q!$C$2:$C$1000,"adjusted_ebitda",History_Q!$B$2:$B$1000,">="&((SUMIFS(History_Q!$B$2:$B$1000,History_Q!$A$2:$A$1000,G$6,History_Q!$C$2:$C$1000,"adjusted_ebitda"))-3),History_Q!$B$2:$B$1000,"<="&(SUMIFS(History_Q!$B$2:$B$1000,History_Q!$A$2:$A$1000,G$6,History_Q!$C$2:$C$1000,"adjusted_ebitda")),History_Q!$E$2:$E$1000,"$m",History_Q!$G$2:$G$1000,"populated")) | H25: =IF(OR(H$6="",COUNTIFS(History_Q!$C$2:$C$1000,"adjusted_ebitda",History_Q!$B$2:$B$1000,">="&((SUMIFS(History_Q!$B$2:$B$1000,History_Q!$A$2:$A$1000,H$6,History_Q!$C$2:$C$1000,"adjusted_ebitda"))-3),History_Q!$B$2:$B$1000,"<="&(SUMIFS(History_Q!$B$2:$B$1000,History_Q!$A$2:$A$1000,H$6,History_Q!$C$2:$C$1000,"adjusted_ebitda")),History_Q!$E$2:$E$1000,"$m",History_Q!$G$2:$G$1000,"populated")<>4,_xlfn.MAXIFS(History_Q!$B$2:$B$1000,History_Q!$C$2:$C$1000,"adjusted_ebitda",History_Q!$B$2:$B$1000,">="&((SUMIFS(History_Q!$B$2:$B$1000,History_Q!$A$2:$A$1000,H$6,History_Q!$C$2:$C$1000,"adjusted_ebitda"))-3),History_Q!$B$2:$B$1000,"<="&(SUMIFS(History_Q!$B$2:$B$1000,History_Q!$A$2:$A$1000,H$6,History_Q!$C$2:$C$1000,"adjusted_ebitda")),History_Q!$E$2:$E$1000,"$m",History_Q!$G$2:$G$1000,"populated")-_xlfn.MINIFS(History_Q!$B$2:$B$1000,History_Q!$C$2:$C$1000,"adjusted_ebitda",History_Q!$B$2:$B$1000,">="&((SUMIFS(History_Q!$B$2:$B$1000,History_Q!$A$2:$A$1000,H$6,History_Q!$C$2:$C$1000,"adjusted_ebitda"))-3),History_Q!$B$2:$B$1000,"<="&(SUMIFS(History_Q!$B$2:$B$1000,History_Q!$A$2:$A$1000,H$6,History_Q!$C$2:$C$1000,"adjusted_ebitda")),History_Q!$E$2:$E$1000,"$m",History_Q!$G$2:$G$1000,"populated")<>3),"",SUMIFS(History_Q!$D$2:$D$1000,History_Q!$C$2:$C$1000,"adjusted_ebitda",History_Q!$B$2:$B$1000,">="&((SUMIFS(History_Q!$B$2:$B$1000,History_Q!$A$2:$A$1000,H$6,History_Q!$C$2:$C$1000,"adjusted_ebitda"))-3),History_Q!$B$2:$B$1000,"<="&(SUMIFS(History_Q!$B$2:$B$1000,History_Q!$A$2:$A$1000,H$6,History_Q!$C$2:$C$1000,"adjusted_ebitda")),History_Q!$E$2:$E$1000,"$m",History_Q!$G$2:$G$1000,"populated")) | I25: =IF(OR(I$6="",COUNTIFS(History_Q!$C$2:$C$1000,"adjusted_ebitda",History_Q!$B$2:$B$1000,">="&((SUMIFS(History_Q!$B$2:$B$1000,History_Q!$A$2:$A$1000,I$6,History_Q!$C$2:$C$1000,"adjusted_ebitda"))-3),History_Q!$B$2:$B$1000,"<="&(SUMIFS(History_Q!$B$2:$B$1000,History_Q!$A$2:$A$1000,I$6,History_Q!$C$2:$C$1000,"adjusted_ebitda")),History_Q!$E$2:$E$1000,"$m",History_Q!$G$2:$G$1000,"populated")<>4,_xlfn.MAXIFS(History_Q!$B$2:$B$1000,History_Q!$C$2:$C$1000,"adjusted_ebitda",History_Q!$B$2:$B$1000,">="&((SUMIFS(History_Q!$B$2:$B$1000,History_Q!$A$2:$A$1000,I$6,History_Q!$C$2:$C$1000,"adjusted_ebitda"))-3),History_Q!$B$2:$B$1000,"<="&(SUMIFS(History_Q!$B$2:$B$1000,History_Q!$A$2:$A$1000,I$6,History_Q!$C$2:$C$1000,"adjusted_ebitda")),History_Q!$E$2:$E$1000,"$m",History_Q!$G$2:$G$1000,"populated")-_xlfn.MINIFS(History_Q!$B$2:$B$1000,History_Q!$C$2:$C$1000,"adjusted_ebitda",History_Q!$B$2:$B$1000,">="&((SUMIFS(History_Q!$B$2:$B$1000,History_Q!$A$2:$A$1000,I$6,History_Q!$C$2:$C$1000,"adjusted_ebitda"))-3),History_Q!$B$2:$B$1000,"<="&(SUMIFS(History_Q!$B$2:$B$1000,History_Q!$A$2:$A$1000,I$6,History_Q!$C$2:$C$1000,"adjusted_ebitda")),History_Q!$E$2:$E$1000,"$m",History_Q!$G$2:$G$1000,"populated")<>3),"",SUMIFS(History_Q!$D$2:$D$1000,History_Q!$C$2:$C$1000,"adjusted_ebitda",History_Q!$B$2:$B$1000,">="&((SUMIFS(History_Q!$B$2:$B$1000,History_Q!$A$2:$A$1000,I$6,History_Q!$C$2:$C$1000,"adjusted_ebitda"))-3),History_Q!$B$2:$B$1000,"<="&(SUMIFS(History_Q!$B$2:$B$1000,History_Q!$A$2:$A$1000,I$6,History_Q!$C$2:$C$1000,"adjusted_ebitda")),History_Q!$E$2:$E$1000,"$m",History_Q!$G$2:$G$1000,"populated")) | ... M25: =IF(OR(M$6="",COUNTIFS(History_Q!$C$2:$C$1000,"adjusted_ebitda",History_Q!$B$2:$B$1000,">="&((SUMIFS(History_Q!$B$2:$B$1000,History_Q!$A$2:$A$1000,M$6,History_Q!$C$2:$C$1000,"adjusted_ebitda"))-3),History_Q!$B$2:$B$1000,"<="&(SUMIFS(History_Q!$B$2:$B$1000,History_Q!$A$2:$A$1000,M$6,History_Q!$C$2:$C$1000,"adjusted_ebitda")),History_Q!$E$2:$E$1000,"$m",History_Q!$G$2:$G$1000,"populated")<>4,_xlfn.MAXIFS(History_Q!$B$2:$B$1000,History_Q!$C$2:$C$1000,"adjusted_ebitda",History_Q!$B$2:$B$1000,">="&((SUMIFS(History_Q!$B$2:$B$1000,History_Q!$A$2:$A$1000,M$6,History_Q!$C$2:$C$1000,"adjusted_ebitda"))-3),History_Q!$B$2:$B$1000,"<="&(SUMIFS(History_Q!$B$2:$B$1000,History_Q!$A$2:$A$1000,M$6,History_Q!$C$2:$C$1000,"adjusted_ebitda")),History_Q!$E$2:$E$1000,"$m",History_Q!$G$2:$G$1000,"populated")-_xlfn.MINIFS(History_Q!$B$2:$B$1000,History_Q!$C$2:$C$1000,"adjusted_ebitda",History_Q!$B$2:$B$1000,">="&((SUMIFS(History_Q!$B$2:$B$1000,History_Q!$A$2:$A$1000,M$6,History_Q!$C$2:$C$1000,"adjusted_ebitda"))-3),History_Q!$B$2:$B$1000,"<="&(SUMIFS(History_Q!$B$2:$B$1000,History_Q!$A$2:$A$1000,M$6,History_Q!$C$2:$C$1000,"adjusted_ebitda")),History_Q!$E$2:$E$1000,"$m",History_Q!$G$2:$G$1000,"populated")<>3),"",SUMIFS(History_Q!$D$2:$D$1000,History_Q!$C$2:$C$1000,"adjusted_ebitda",History_Q!$B$2:$B$1000,">="&((SUMIFS(History_Q!$B$2:$B$1000,History_Q!$A$2:$A$1000,M$6,History_Q!$C$2:$C$1000,"adjusted_ebitda"))-3),History_Q!$B$2:$B$1000,"<="&(SUMIFS(History_Q!$B$2:$B$1000,History_Q!$A$2:$A$1000,M$6,History_Q!$C$2:$C$1000,"adjusted_ebitda")),History_Q!$E$2:$E$1000,"$m",History_Q!$G$2:$G$1000,"populated"))
A26: Adjusted EBITDA - EBITDA | B26: =IF(OR(B24="",B18=""),"",B24-B18) | C26: =IF(OR(C24="",C18=""),"",C24-C18) | D26: =IF(OR(D24="",D18=""),"",D24-D18) | E26: =IF(OR(E24="",E18=""),"",E24-E18) | F26: =IF(OR(F24="",F18=""),"",F24-F18) | G26: =IF(OR(G24="",G18=""),"",G24-G18) | H26: =IF(OR(H24="",H18=""),"",H24-H18) | I26: =IF(OR(I24="",I18=""),"",I24-I18) | ... M26: =IF(OR(M24="",M18=""),"",M24-M18)
A27: Adjusted EBITDA margin % | B27: =IF(OR(B24="",B9="",B9=0),"",B24/B9) | C27: =IF(OR(C24="",C9="",C9=0),"",C24/C9) | D27: =IF(OR(D24="",D9="",D9=0),"",D24/D9) | E27: =IF(OR(E24="",E9="",E9=0),"",E24/E9) | F27: =IF(OR(F24="",F9="",F9=0),"",F24/F9) | G27: =IF(OR(G24="",G9="",G9=0),"",G24/G9) | H27: =IF(OR(H24="",H9="",H9=0),"",H24/H9) | I27: =IF(OR(I24="",I9="",I9=0),"",I24/I9) | ... M27: =IF(OR(M24="",M9="",M9=0),"",M24/M9) | O27: Historical guidance
A28: Adjusted EBITDA YoY % | B28: =IF(OR(B$6="",COUNTIFS(History_Q!$C$2:$C$1000,"adjusted_ebitda",History_Q!$B$2:$B$1000,(SUMIFS(History_Q!$B$2:$B$1000,History_Q!$A$2:$A$1000,B$6,History_Q!$C$2:$C$1000,"adjusted_ebitda")),History_Q!$E$2:$E$1000,"$m",History_Q!$G$2:$G$1000,"populated")<>1,COUNTIFS(History_Q!$C$2:$C$1000,"adjusted_ebitda",History_Q!$B$2:$B$1000,(SUMIFS(History_Q!$B$2:$B$1000,History_Q!$A$2:$A$1000,B$6,History_Q!$C$2:$C$1000,"adjusted_ebitda")-4),History_Q!$E$2:$E$1000,"$m",History_Q!$G$2:$G$1000,"populated")<>1,SUMIFS(History_Q!$D$2:$D$1000,History_Q!$C$2:$C$1000,"adjusted_ebitda",History_Q!$B$2:$B$1000,(SUMIFS(History_Q!$B$2:$B$1000,History_Q!$A$2:$A$1000,B$6,History_Q!$C$2:$C$1000,"adjusted_ebitda")-4),History_Q!$E$2:$E$1000,"$m",History_Q!$G$2:$G$1000,"populated")=0),"",SUMIFS(History_Q!$D$2:$D$1000,History_Q!$C$2:$C$1000,"adjusted_ebitda",History_Q!$B$2:$B$1000,(SUMIFS(History_Q!$B$2:$B$1000,History_Q!$A$2:$A$1000,B$6,History_Q!$C$2:$C$1000,"adjusted_ebitda")),History_Q!$E$2:$E$1000,"$m",History_Q!$G$2:$G$1000,"populated")/SUMIFS(History_Q!$D$2:$D$1000,History_Q!$C$2:$C$1000,"adjusted_ebitda",History_Q!$B$2:$B$1000,(SUMIFS(History_Q!$B$2:$B$1000,History_Q!$A$2:$A$1000,B$6,History_Q!$C$2:$C$1000,"adjusted_ebitda")-4),History_Q!$E$2:$E$1000,"$m",History_Q!$G$2:$G$1000,"populated")-1) | C28: =IF(OR(C$6="",COUNTIFS(History_Q!$C$2:$C$1000,"adjusted_ebitda",History_Q!$B$2:$B$1000,(SUMIFS(History_Q!$B$2:$B$1000,History_Q!$A$2:$A$1000,C$6,History_Q!$C$2:$C$1000,"adjusted_ebitda")),History_Q!$E$2:$E$1000,"$m",History_Q!$G$2:$G$1000,"populated")<>1,COUNTIFS(History_Q!$C$2:$C$1000,"adjusted_ebitda",History_Q!$B$2:$B$1000,(SUMIFS(History_Q!$B$2:$B$1000,History_Q!$A$2:$A$1000,C$6,History_Q!$C$2:$C$1000,"adjusted_ebitda")-4),History_Q!$E$2:$E$1000,"$m",History_Q!$G$2:$G$1000,"populated")<>1,SUMIFS(History_Q!$D$2:$D$1000,History_Q!$C$2:$C$1000,"adjusted_ebitda",History_Q!$B$2:$B$1000,(SUMIFS(History_Q!$B$2:$B$1000,History_Q!$A$2:$A$1000,C$6,History_Q!$C$2:$C$1000,"adjusted_ebitda")-4),History_Q!$E$2:$E$1000,"$m",History_Q!$G$2:$G$1000,"populated")=0),"",SUMIFS(History_Q!$D$2:$D$1000,History_Q!$C$2:$C$1000,"adjusted_ebitda",History_Q!$B$2:$B$1000,(SUMIFS(History_Q!$B$2:$B$1000,History_Q!$A$2:$A$1000,C$6,History_Q!$C$2:$C$1000,"adjusted_ebitda")),History_Q!$E$2:$E$1000,"$m",History_Q!$G$2:$G$1000,"populated")/SUMIFS(History_Q!$D$2:$D$1000,History_Q!$C$2:$C$1000,"adjusted_ebitda",History_Q!$B$2:$B$1000,(SUMIFS(History_Q!$B$2:$B$1000,History_Q!$A$2:$A$1000,C$6,History_Q!$C$2:$C$1000,"adjusted_ebitda")-4),History_Q!$E$2:$E$1000,"$m",History_Q!$G$2:$G$1000,"populated")-1) | D28: =IF(OR(D$6="",COUNTIFS(History_Q!$C$2:$C$1000,"adjusted_ebitda",History_Q!$B$2:$B$1000,(SUMIFS(History_Q!$B$2:$B$1000,History_Q!$A$2:$A$1000,D$6,History_Q!$C$2:$C$1000,"adjusted_ebitda")),History_Q!$E$2:$E$1000,"$m",History_Q!$G$2:$G$1000,"populated")<>1,COUNTIFS(History_Q!$C$2:$C$1000,"adjusted_ebitda",History_Q!$B$2:$B$1000,(SUMIFS(History_Q!$B$2:$B$1000,History_Q!$A$2:$A$1000,D$6,History_Q!$C$2:$C$1000,"adjusted_ebitda")-4),History_Q!$E$2:$E$1000,"$m",History_Q!$G$2:$G$1000,"populated")<>1,SUMIFS(History_Q!$D$2:$D$1000,History_Q!$C$2:$C$1000,"adjusted_ebitda",History_Q!$B$2:$B$1000,(SUMIFS(History_Q!$B$2:$B$1000,History_Q!$A$2:$A$1000,D$6,History_Q!$C$2:$C$1000,"adjusted_ebitda")-4),History_Q!$E$2:$E$1000,"$m",History_Q!$G$2:$G$1000,"populated")=0),"",SUMIFS(History_Q!$D$2:$D$1000,History_Q!$C$2:$C$1000,"adjusted_ebitda",History_Q!$B$2:$B$1000,(SUMIFS(History_Q!$B$2:$B$1000,History_Q!$A$2:$A$1000,D$6,History_Q!$C$2:$C$1000,"adjusted_ebitda")),History_Q!$E$2:$E$1000,"$m",History_Q!$G$2:$G$1000,"populated")/SUMIFS(History_Q!$D$2:$D$1000,History_Q!$C$2:$C$1000,"adjusted_ebitda",History_Q!$B$2:$B$1000,(SUMIFS(History_Q!$B$2:$B$1000,History_Q!$A$2:$A$1000,D$6,History_Q!$C$2:$C$1000,"adjusted_ebitda")-4),History_Q!$E$2:$E$1000,"$m",History_Q!$G$2:$G$1000,"populated")-1) | E28: =IF(OR(E$6="",COUNTIFS(History_Q!$C$2:$C$1000,"adjusted_ebitda",History_Q!$B$2:$B$1000,(SUMIFS(History_Q!$B$2:$B$1000,History_Q!$A$2:$A$1000,E$6,History_Q!$C$2:$C$1000,"adjusted_ebitda")),History_Q!$E$2:$E$1000,"$m",History_Q!$G$2:$G$1000,"populated")<>1,COUNTIFS(History_Q!$C$2:$C$1000,"adjusted_ebitda",History_Q!$B$2:$B$1000,(SUMIFS(History_Q!$B$2:$B$1000,History_Q!$A$2:$A$1000,E$6,History_Q!$C$2:$C$1000,"adjusted_ebitda")-4),History_Q!$E$2:$E$1000,"$m",History_Q!$G$2:$G$1000,"populated")<>1,SUMIFS(History_Q!$D$2:$D$1000,History_Q!$C$2:$C$1000,"adjusted_ebitda",History_Q!$B$2:$B$1000,(SUMIFS(History_Q!$B$2:$B$1000,History_Q!$A$2:$A$1000,E$6,History_Q!$C$2:$C$1000,"adjusted_ebitda")-4),History_Q!$E$2:$E$1000,"$m",History_Q!$G$2:$G$1000,"populated")=0),"",SUMIFS(History_Q!$D$2:$D$1000,History_Q!$C$2:$C$1000,"adjusted_ebitda",History_Q!$B$2:$B$1000,(SUMIFS(History_Q!$B$2:$B$1000,History_Q!$A$2:$A$1000,E$6,History_Q!$C$2:$C$1000,"adjusted_ebitda")),History_Q!$E$2:$E$1000,"$m",History_Q!$G$2:$G$1000,"populated")/SUMIFS(History_Q!$D$2:$D$1000,History_Q!$C$2:$C$1000,"adjusted_ebitda",History_Q!$B$2:$B$1000,(SUMIFS(History_Q!$B$2:$B$1000,History_Q!$A$2:$A$1000,E$6,History_Q!$C$2:$C$1000,"adjusted_ebitda")-4),History_Q!$E$2:$E$1000,"$m",History_Q!$G$2:$G$1000,"populated")-1) | F28: =IF(OR(F$6="",COUNTIFS(History_Q!$C$2:$C$1000,"adjusted_ebitda",History_Q!$B$2:$B$1000,(SUMIFS(History_Q!$B$2:$B$1000,History_Q!$A$2:$A$1000,F$6,History_Q!$C$2:$C$1000,"adjusted_ebitda")),History_Q!$E$2:$E$1000,"$m",History_Q!$G$2:$G$1000,"populated")<>1,COUNTIFS(History_Q!$C$2:$C$1000,"adjusted_ebitda",History_Q!$B$2:$B$1000,(SUMIFS(History_Q!$B$2:$B$1000,History_Q!$A$2:$A$1000,F$6,History_Q!$C$2:$C$1000,"adjusted_ebitda")-4),History_Q!$E$2:$E$1000,"$m",History_Q!$G$2:$G$1000,"populated")<>1,SUMIFS(History_Q!$D$2:$D$1000,History_Q!$C$2:$C$1000,"adjusted_ebitda",History_Q!$B$2:$B$1000,(SUMIFS(History_Q!$B$2:$B$1000,History_Q!$A$2:$A$1000,F$6,History_Q!$C$2:$C$1000,"adjusted_ebitda")-4),History_Q!$E$2:$E$1000,"$m",History_Q!$G$2:$G$1000,"populated")=0),"",SUMIFS(History_Q!$D$2:$D$1000,History_Q!$C$2:$C$1000,"adjusted_ebitda",History_Q!$B$2:$B$1000,(SUMIFS(History_Q!$B$2:$B$1000,History_Q!$A$2:$A$1000,F$6,History_Q!$C$2:$C$1000,"adjusted_ebitda")),History_Q!$E$2:$E$1000,"$m",History_Q!$G$2:$G$1000,"populated")/SUMIFS(History_Q!$D$2:$D$1000,History_Q!$C$2:$C$1000,"adjusted_ebitda",History_Q!$B$2:$B$1000,(SUMIFS(History_Q!$B$2:$B$1000,History_Q!$A$2:$A$1000,F$6,History_Q!$C$2:$C$1000,"adjusted_ebitda")-4),History_Q!$E$2:$E$1000,"$m",History_Q!$G$2:$G$1000,"populated")-1) | G28: =IF(OR(G$6="",COUNTIFS(History_Q!$C$2:$C$1000,"adjusted_ebitda",History_Q!$B$2:$B$1000,(SUMIFS(History_Q!$B$2:$B$1000,History_Q!$A$2:$A$1000,G$6,History_Q!$C$2:$C$1000,"adjusted_ebitda")),History_Q!$E$2:$E$1000,"$m",History_Q!$G$2:$G$1000,"populated")<>1,COUNTIFS(History_Q!$C$2:$C$1000,"adjusted_ebitda",History_Q!$B$2:$B$1000,(SUMIFS(History_Q!$B$2:$B$1000,History_Q!$A$2:$A$1000,G$6,History_Q!$C$2:$C$1000,"adjusted_ebitda")-4),History_Q!$E$2:$E$1000,"$m",History_Q!$G$2:$G$1000,"populated")<>1,SUMIFS(History_Q!$D$2:$D$1000,History_Q!$C$2:$C$1000,"adjusted_ebitda",History_Q!$B$2:$B$1000,(SUMIFS(History_Q!$B$2:$B$1000,History_Q!$A$2:$A$1000,G$6,History_Q!$C$2:$C$1000,"adjusted_ebitda")-4),History_Q!$E$2:$E$1000,"$m",History_Q!$G$2:$G$1000,"populated")=0),"",SUMIFS(History_Q!$D$2:$D$1000,History_Q!$C$2:$C$1000,"adjusted_ebitda",History_Q!$B$2:$B$1000,(SUMIFS(History_Q!$B$2:$B$1000,History_Q!$A$2:$A$1000,G$6,History_Q!$C$2:$C$1000,"adjusted_ebitda")),History_Q!$E$2:$E$1000,"$m",History_Q!$G$2:$G$1000,"populated")/SUMIFS(History_Q!$D$2:$D$1000,History_Q!$C$2:$C$1000,"adjusted_ebitda",History_Q!$B$2:$B$1000,(SUMIFS(History_Q!$B$2:$B$1000,History_Q!$A$2:$A$1000,G$6,History_Q!$C$2:$C$1000,"adjusted_ebitda")-4),History_Q!$E$2:$E$1000,"$m",History_Q!$G$2:$G$1000,"populated")-1) | H28: =IF(OR(H$6="",COUNTIFS(History_Q!$C$2:$C$1000,"adjusted_ebitda",History_Q!$B$2:$B$1000,(SUMIFS(History_Q!$B$2:$B$1000,History_Q!$A$2:$A$1000,H$6,History_Q!$C$2:$C$1000,"adjusted_ebitda")),History_Q!$E$2:$E$1000,"$m",History_Q!$G$2:$G$1000,"populated")<>1,COUNTIFS(History_Q!$C$2:$C$1000,"adjusted_ebitda",History_Q!$B$2:$B$1000,(SUMIFS(History_Q!$B$2:$B$1000,History_Q!$A$2:$A$1000,H$6,History_Q!$C$2:$C$1000,"adjusted_ebitda")-4),History_Q!$E$2:$E$1000,"$m",History_Q!$G$2:$G$1000,"populated")<>1,SUMIFS(History_Q!$D$2:$D$1000,History_Q!$C$2:$C$1000,"adjusted_ebitda",History_Q!$B$2:$B$1000,(SUMIFS(History_Q!$B$2:$B$1000,History_Q!$A$2:$A$1000,H$6,History_Q!$C$2:$C$1000,"adjusted_ebitda")-4),History_Q!$E$2:$E$1000,"$m",History_Q!$G$2:$G$1000,"populated")=0),"",SUMIFS(History_Q!$D$2:$D$1000,History_Q!$C$2:$C$1000,"adjusted_ebitda",History_Q!$B$2:$B$1000,(SUMIFS(History_Q!$B$2:$B$1000,History_Q!$A$2:$A$1000,H$6,History_Q!$C$2:$C$1000,"adjusted_ebitda")),History_Q!$E$2:$E$1000,"$m",History_Q!$G$2:$G$1000,"populated")/SUMIFS(History_Q!$D$2:$D$1000,History_Q!$C$2:$C$1000,"adjusted_ebitda",History_Q!$B$2:$B$1000,(SUMIFS(History_Q!$B$2:$B$1000,History_Q!$A$2:$A$1000,H$6,History_Q!$C$2:$C$1000,"adjusted_ebitda")-4),History_Q!$E$2:$E$1000,"$m",History_Q!$G$2:$G$1000,"populated")-1) | I28: =IF(OR(I$6="",COUNTIFS(History_Q!$C$2:$C$1000,"adjusted_ebitda",History_Q!$B$2:$B$1000,(SUMIFS(History_Q!$B$2:$B$1000,History_Q!$A$2:$A$1000,I$6,History_Q!$C$2:$C$1000,"adjusted_ebitda")),History_Q!$E$2:$E$1000,"$m",History_Q!$G$2:$G$1000,"populated")<>1,COUNTIFS(History_Q!$C$2:$C$1000,"adjusted_ebitda",History_Q!$B$2:$B$1000,(SUMIFS(History_Q!$B$2:$B$1000,History_Q!$A$2:$A$1000,I$6,History_Q!$C$2:$C$1000,"adjusted_ebitda")-4),History_Q!$E$2:$E$1000,"$m",History_Q!$G$2:$G$1000,"populated")<>1,SUMIFS(History_Q!$D$2:$D$1000,History_Q!$C$2:$C$1000,"adjusted_ebitda",History_Q!$B$2:$B$1000,(SUMIFS(History_Q!$B$2:$B$1000,History_Q!$A$2:$A$1000,I$6,History_Q!$C$2:$C$1000,"adjusted_ebitda")-4),History_Q!$E$2:$E$1000,"$m",History_Q!$G$2:$G$1000,"populated")=0),"",SUMIFS(History_Q!$D$2:$D$1000,History_Q!$C$2:$C$1000,"adjusted_ebitda",History_Q!$B$2:$B$1000,(SUMIFS(History_Q!$B$2:$B$1000,History_Q!$A$2:$A$1000,I$6,History_Q!$C$2:$C$1000,"adjusted_ebitda")),History_Q!$E$2:$E$1000,"$m",History_Q!$G$2:$G$1000,"populated")/SUMIFS(History_Q!$D$2:$D$1000,History_Q!$C$2:$C$1000,"adjusted_ebitda",History_Q!$B$2:$B$1000,(SUMIFS(History_Q!$B$2:$B$1000,History_Q!$A$2:$A$1000,I$6,History_Q!$C$2:$C$1000,"adjusted_ebitda")-4),History_Q!$E$2:$E$1000,"$m",History_Q!$G$2:$G$1000,"populated")-1) | ... M28: =IF(OR(M$6="",COUNTIFS(History_Q!$C$2:$C$1000,"adjusted_ebitda",History_Q!$B$2:$B$1000,(SUMIFS(History_Q!$B$2:$B$1000,History_Q!$A$2:$A$1000,M$6,History_Q!$C$2:$C$1000,"adjusted_ebitda")),History_Q!$E$2:$E$1000,"$m",History_Q!$G$2:$G$1000,"populated")<>1,COUNTIFS(History_Q!$C$2:$C$1000,"adjusted_ebitda",History_Q!$B$2:$B$1000,(SUMIFS(History_Q!$B$2:$B$1000,History_Q!$A$2:$A$1000,M$6,History_Q!$C$2:$C$1000,"adjusted_ebitda")-4),History_Q!$E$2:$E$1000,"$m",History_Q!$G$2:$G$1000,"populated")<>1,SUMIFS(History_Q!$D$2:$D$1000,History_Q!$C$2:$C$1000,"adjusted_ebitda",History_Q!$B$2:$B$1000,(SUMIFS(History_Q!$B$2:$B$1000,History_Q!$A$2:$A$1000,M$6,History_Q!$C$2:$C$1000,"adjusted_ebitda")-4),History_Q!$E$2:$E$1000,"$m",History_Q!$G$2:$G$1000,"populated")=0),"",SUMIFS(History_Q!$D$2:$D$1000,History_Q!$C$2:$C$1000,"adjusted_ebitda",History_Q!$B$2:$B$1000,(SUMIFS(History_Q!$B$2:$B$1000,History_Q!$A$2:$A$1000,M$6,History_Q!$C$2:$C$1000,"adjusted_ebitda")),History_Q!$E$2:$E$1000,"$m",History_Q!$G$2:$G$1000,"populated")/SUMIFS(History_Q!$D$2:$D$1000,History_Q!$C$2:$C$1000,"adjusted_ebitda",History_Q!$B$2:$B$1000,(SUMIFS(History_Q!$B$2:$B$1000,History_Q!$A$2:$A$1000,M$6,History_Q!$C$2:$C$1000,"adjusted_ebitda")-4),History_Q!$E$2:$E$1000,"$m",History_Q!$G$2:$G$1000,"populated")-1) | O28: Metric | Q28: Stated in | R28: Applies to | S28: Guidance | X28: Unit | Y28: Published | Z28: Evidence | AA28: Role / source status
A29: Adjusted EBITDA margin (TTM) | B29: =IF(OR(B25="",B10="",B10=0),"",B25/B10) | C29: =IF(OR(C25="",C10="",C10=0),"",C25/C10) | D29: =IF(OR(D25="",D10="",D10=0),"",D25/D10) | E29: =IF(OR(E25="",E10="",E10=0),"",E25/E10) | F29: =IF(OR(F25="",F10="",F10=0),"",F25/F10) | G29: =IF(OR(G25="",G10="",G10=0),"",G25/G10) | H29: =IF(OR(H25="",H10="",H10=0),"",H25/H10) | I29: =IF(OR(I25="",I10="",I10=0),"",I25/I10) | ... M29: =IF(OR(M25="",M10="",M10=0),"",M25/M10)
A30: Adj EBIT (TTM)
A31: GAAP earnings
A32: EBIT
A33: EBIT margin % | B33: =IF(OR(B32="",B9="",B9=0),"",B32/B9) | C33: =IF(OR(C32="",C9="",C9=0),"",C32/C9) | D33: =IF(OR(D32="",D9="",D9=0),"",D32/D9) | E33: =IF(OR(E32="",E9="",E9=0),"",E32/E9) | F33: =IF(OR(F32="",F9="",F9=0),"",F32/F9) | G33: =IF(OR(G32="",G9="",G9=0),"",G32/G9) | H33: =IF(OR(H32="",H9="",H9=0),"",H32/H9) | I33: =IF(OR(I32="",I9="",I9=0),"",I32/I9) | ... M33: =IF(OR(M32="",M9="",M9=0),"",M32/M9)
A34: EBIT (TTM) | B34: =IF(OR(B$6="",COUNTIFS(History_Q!$C$2:$C$1000,"operating_income",History_Q!$B$2:$B$1000,">="&((SUMIFS(History_Q!$B$2:$B$1000,History_Q!$A$2:$A$1000,B$6,History_Q!$C$2:$C$1000,"operating_income"))-3),History_Q!$B$2:$B$1000,"<="&(SUMIFS(History_Q!$B$2:$B$1000,History_Q!$A$2:$A$1000,B$6,History_Q!$C$2:$C$1000,"operating_income")),History_Q!$E$2:$E$1000,"$m",History_Q!$G$2:$G$1000,"populated")<>4,_xlfn.MAXIFS(History_Q!$B$2:$B$1000,History_Q!$C$2:$C$1000,"operating_income",History_Q!$B$2:$B$1000,">="&((SUMIFS(History_Q!$B$2:$B$1000,History_Q!$A$2:$A$1000,B$6,History_Q!$C$2:$C$1000,"operating_income"))-3),History_Q!$B$2:$B$1000,"<="&(SUMIFS(History_Q!$B$2:$B$1000,History_Q!$A$2:$A$1000,B$6,History_Q!$C$2:$C$1000,"operating_income")),History_Q!$E$2:$E$1000,"$m",History_Q!$G$2:$G$1000,"populated")-_xlfn.MINIFS(History_Q!$B$2:$B$1000,History_Q!$C$2:$C$1000,"operating_income",History_Q!$B$2:$B$1000,">="&((SUMIFS(History_Q!$B$2:$B$1000,History_Q!$A$2:$A$1000,B$6,History_Q!$C$2:$C$1000,"operating_income"))-3),History_Q!$B$2:$B$1000,"<="&(SUMIFS(History_Q!$B$2:$B$1000,History_Q!$A$2:$A$1000,B$6,History_Q!$C$2:$C$1000,"operating_income")),History_Q!$E$2:$E$1000,"$m",History_Q!$G$2:$G$1000,"populated")<>3),"",SUMIFS(History_Q!$D$2:$D$1000,History_Q!$C$2:$C$1000,"operating_income",History_Q!$B$2:$B$1000,">="&((SUMIFS(History_Q!$B$2:$B$1000,History_Q!$A$2:$A$1000,B$6,History_Q!$C$2:$C$1000,"operating_income"))-3),History_Q!$B$2:$B$1000,"<="&(SUMIFS(History_Q!$B$2:$B$1000,History_Q!$A$2:$A$1000,B$6,History_Q!$C$2:$C$1000,"operating_income")),History_Q!$E$2:$E$1000,"$m",History_Q!$G$2:$G$1000,"populated")) | C34: =IF(OR(C$6="",COUNTIFS(History_Q!$C$2:$C$1000,"operating_income",History_Q!$B$2:$B$1000,">="&((SUMIFS(History_Q!$B$2:$B$1000,History_Q!$A$2:$A$1000,C$6,History_Q!$C$2:$C$1000,"operating_income"))-3),History_Q!$B$2:$B$1000,"<="&(SUMIFS(History_Q!$B$2:$B$1000,History_Q!$A$2:$A$1000,C$6,History_Q!$C$2:$C$1000,"operating_income")),History_Q!$E$2:$E$1000,"$m",History_Q!$G$2:$G$1000,"populated")<>4,_xlfn.MAXIFS(History_Q!$B$2:$B$1000,History_Q!$C$2:$C$1000,"operating_income",History_Q!$B$2:$B$1000,">="&((SUMIFS(History_Q!$B$2:$B$1000,History_Q!$A$2:$A$1000,C$6,History_Q!$C$2:$C$1000,"operating_income"))-3),History_Q!$B$2:$B$1000,"<="&(SUMIFS(History_Q!$B$2:$B$1000,History_Q!$A$2:$A$1000,C$6,History_Q!$C$2:$C$1000,"operating_income")),History_Q!$E$2:$E$1000,"$m",History_Q!$G$2:$G$1000,"populated")-_xlfn.MINIFS(History_Q!$B$2:$B$1000,History_Q!$C$2:$C$1000,"operating_income",History_Q!$B$2:$B$1000,">="&((SUMIFS(History_Q!$B$2:$B$1000,History_Q!$A$2:$A$1000,C$6,History_Q!$C$2:$C$1000,"operating_income"))-3),History_Q!$B$2:$B$1000,"<="&(SUMIFS(History_Q!$B$2:$B$1000,History_Q!$A$2:$A$1000,C$6,History_Q!$C$2:$C$1000,"operating_income")),History_Q!$E$2:$E$1000,"$m",History_Q!$G$2:$G$1000,"populated")<>3),"",SUMIFS(History_Q!$D$2:$D$1000,History_Q!$C$2:$C$1000,"operating_income",History_Q!$B$2:$B$1000,">="&((SUMIFS(History_Q!$B$2:$B$1000,History_Q!$A$2:$A$1000,C$6,History_Q!$C$2:$C$1000,"operating_income"))-3),History_Q!$B$2:$B$1000,"<="&(SUMIFS(History_Q!$B$2:$B$1000,History_Q!$A$2:$A$1000,C$6,History_Q!$C$2:$C$1000,"operating_income")),History_Q!$E$2:$E$1000,"$m",History_Q!$G$2:$G$1000,"populated")) | D34: =IF(OR(D$6="",COUNTIFS(History_Q!$C$2:$C$1000,"operating_income",History_Q!$B$2:$B$1000,">="&((SUMIFS(History_Q!$B$2:$B$1000,History_Q!$A$2:$A$1000,D$6,History_Q!$C$2:$C$1000,"operating_income"))-3),History_Q!$B$2:$B$1000,"<="&(SUMIFS(History_Q!$B$2:$B$1000,History_Q!$A$2:$A$1000,D$6,History_Q!$C$2:$C$1000,"operating_income")),History_Q!$E$2:$E$1000,"$m",History_Q!$G$2:$G$1000,"populated")<>4,_xlfn.MAXIFS(History_Q!$B$2:$B$1000,History_Q!$C$2:$C$1000,"operating_income",History_Q!$B$2:$B$1000,">="&((SUMIFS(History_Q!$B$2:$B$1000,History_Q!$A$2:$A$1000,D$6,History_Q!$C$2:$C$1000,"operating_income"))-3),History_Q!$B$2:$B$1000,"<="&(SUMIFS(History_Q!$B$2:$B$1000,History_Q!$A$2:$A$1000,D$6,History_Q!$C$2:$C$1000,"operating_income")),History_Q!$E$2:$E$1000,"$m",History_Q!$G$2:$G$1000,"populated")-_xlfn.MINIFS(History_Q!$B$2:$B$1000,History_Q!$C$2:$C$1000,"operating_income",History_Q!$B$2:$B$1000,">="&((SUMIFS(History_Q!$B$2:$B$1000,History_Q!$A$2:$A$1000,D$6,History_Q!$C$2:$C$1000,"operating_income"))-3),History_Q!$B$2:$B$1000,"<="&(SUMIFS(History_Q!$B$2:$B$1000,History_Q!$A$2:$A$1000,D$6,History_Q!$C$2:$C$1000,"operating_income")),History_Q!$E$2:$E$1000,"$m",History_Q!$G$2:$G$1000,"populated")<>3),"",SUMIFS(History_Q!$D$2:$D$1000,History_Q!$C$2:$C$1000,"operating_income",History_Q!$B$2:$B$1000,">="&((SUMIFS(History_Q!$B$2:$B$1000,History_Q!$A$2:$A$1000,D$6,History_Q!$C$2:$C$1000,"operating_income"))-3),History_Q!$B$2:$B$1000,"<="&(SUMIFS(History_Q!$B$2:$B$1000,History_Q!$A$2:$A$1000,D$6,History_Q!$C$2:$C$1000,"operating_income")),History_Q!$E$2:$E$1000,"$m",History_Q!$G$2:$G$1000,"populated")) | E34: =IF(OR(E$6="",COUNTIFS(History_Q!$C$2:$C$1000,"operating_income",History_Q!$B$2:$B$1000,">="&((SUMIFS(History_Q!$B$2:$B$1000,History_Q!$A$2:$A$1000,E$6,History_Q!$C$2:$C$1000,"operating_income"))-3),History_Q!$B$2:$B$1000,"<="&(SUMIFS(History_Q!$B$2:$B$1000,History_Q!$A$2:$A$1000,E$6,History_Q!$C$2:$C$1000,"operating_income")),History_Q!$E$2:$E$1000,"$m",History_Q!$G$2:$G$1000,"populated")<>4,_xlfn.MAXIFS(History_Q!$B$2:$B$1000,History_Q!$C$2:$C$1000,"operating_income",History_Q!$B$2:$B$1000,">="&((SUMIFS(History_Q!$B$2:$B$1000,History_Q!$A$2:$A$1000,E$6,History_Q!$C$2:$C$1000,"operating_income"))-3),History_Q!$B$2:$B$1000,"<="&(SUMIFS(History_Q!$B$2:$B$1000,History_Q!$A$2:$A$1000,E$6,History_Q!$C$2:$C$1000,"operating_income")),History_Q!$E$2:$E$1000,"$m",History_Q!$G$2:$G$1000,"populated")-_xlfn.MINIFS(History_Q!$B$2:$B$1000,History_Q!$C$2:$C$1000,"operating_income",History_Q!$B$2:$B$1000,">="&((SUMIFS(History_Q!$B$2:$B$1000,History_Q!$A$2:$A$1000,E$6,History_Q!$C$2:$C$1000,"operating_income"))-3),History_Q!$B$2:$B$1000,"<="&(SUMIFS(History_Q!$B$2:$B$1000,History_Q!$A$2:$A$1000,E$6,History_Q!$C$2:$C$1000,"operating_income")),History_Q!$E$2:$E$1000,"$m",History_Q!$G$2:$G$1000,"populated")<>3),"",SUMIFS(History_Q!$D$2:$D$1000,History_Q!$C$2:$C$1000,"operating_income",History_Q!$B$2:$B$1000,">="&((SUMIFS(History_Q!$B$2:$B$1000,History_Q!$A$2:$A$1000,E$6,History_Q!$C$2:$C$1000,"operating_income"))-3),History_Q!$B$2:$B$1000,"<="&(SUMIFS(History_Q!$B$2:$B$1000,History_Q!$A$2:$A$1000,E$6,History_Q!$C$2:$C$1000,"operating_income")),History_Q!$E$2:$E$1000,"$m",History_Q!$G$2:$G$1000,"populated")) | F34: =IF(OR(F$6="",COUNTIFS(History_Q!$C$2:$C$1000,"operating_income",History_Q!$B$2:$B$1000,">="&((SUMIFS(History_Q!$B$2:$B$1000,History_Q!$A$2:$A$1000,F$6,History_Q!$C$2:$C$1000,"operating_income"))-3),History_Q!$B$2:$B$1000,"<="&(SUMIFS(History_Q!$B$2:$B$1000,History_Q!$A$2:$A$1000,F$6,History_Q!$C$2:$C$1000,"operating_income")),History_Q!$E$2:$E$1000,"$m",History_Q!$G$2:$G$1000,"populated")<>4,_xlfn.MAXIFS(History_Q!$B$2:$B$1000,History_Q!$C$2:$C$1000,"operating_income",History_Q!$B$2:$B$1000,">="&((SUMIFS(History_Q!$B$2:$B$1000,History_Q!$A$2:$A$1000,F$6,History_Q!$C$2:$C$1000,"operating_income"))-3),History_Q!$B$2:$B$1000,"<="&(SUMIFS(History_Q!$B$2:$B$1000,History_Q!$A$2:$A$1000,F$6,History_Q!$C$2:$C$1000,"operating_income")),History_Q!$E$2:$E$1000,"$m",History_Q!$G$2:$G$1000,"populated")-_xlfn.MINIFS(History_Q!$B$2:$B$1000,History_Q!$C$2:$C$1000,"operating_income",History_Q!$B$2:$B$1000,">="&((SUMIFS(History_Q!$B$2:$B$1000,History_Q!$A$2:$A$1000,F$6,History_Q!$C$2:$C$1000,"operating_income"))-3),History_Q!$B$2:$B$1000,"<="&(SUMIFS(History_Q!$B$2:$B$1000,History_Q!$A$2:$A$1000,F$6,History_Q!$C$2:$C$1000,"operating_income")),History_Q!$E$2:$E$1000,"$m",History_Q!$G$2:$G$1000,"populated")<>3),"",SUMIFS(History_Q!$D$2:$D$1000,History_Q!$C$2:$C$1000,"operating_income",History_Q!$B$2:$B$1000,">="&((SUMIFS(History_Q!$B$2:$B$1000,History_Q!$A$2:$A$1000,F$6,History_Q!$C$2:$C$1000,"operating_income"))-3),History_Q!$B$2:$B$1000,"<="&(SUMIFS(History_Q!$B$2:$B$1000,History_Q!$A$2:$A$1000,F$6,History_Q!$C$2:$C$1000,"operating_income")),History_Q!$E$2:$E$1000,"$m",History_Q!$G$2:$G$1000,"populated")) | G34: =IF(OR(G$6="",COUNTIFS(History_Q!$C$2:$C$1000,"operating_income",History_Q!$B$2:$B$1000,">="&((SUMIFS(History_Q!$B$2:$B$1000,History_Q!$A$2:$A$1000,G$6,History_Q!$C$2:$C$1000,"operating_income"))-3),History_Q!$B$2:$B$1000,"<="&(SUMIFS(History_Q!$B$2:$B$1000,History_Q!$A$2:$A$1000,G$6,History_Q!$C$2:$C$1000,"operating_income")),History_Q!$E$2:$E$1000,"$m",History_Q!$G$2:$G$1000,"populated")<>4,_xlfn.MAXIFS(History_Q!$B$2:$B$1000,History_Q!$C$2:$C$1000,"operating_income",History_Q!$B$2:$B$1000,">="&((SUMIFS(History_Q!$B$2:$B$1000,History_Q!$A$2:$A$1000,G$6,History_Q!$C$2:$C$1000,"operating_income"))-3),History_Q!$B$2:$B$1000,"<="&(SUMIFS(History_Q!$B$2:$B$1000,History_Q!$A$2:$A$1000,G$6,History_Q!$C$2:$C$1000,"operating_income")),History_Q!$E$2:$E$1000,"$m",History_Q!$G$2:$G$1000,"populated")-_xlfn.MINIFS(History_Q!$B$2:$B$1000,History_Q!$C$2:$C$1000,"operating_income",History_Q!$B$2:$B$1000,">="&((SUMIFS(History_Q!$B$2:$B$1000,History_Q!$A$2:$A$1000,G$6,History_Q!$C$2:$C$1000,"operating_income"))-3),History_Q!$B$2:$B$1000,"<="&(SUMIFS(History_Q!$B$2:$B$1000,History_Q!$A$2:$A$1000,G$6,History_Q!$C$2:$C$1000,"operating_income")),History_Q!$E$2:$E$1000,"$m",History_Q!$G$2:$G$1000,"populated")<>3),"",SUMIFS(History_Q!$D$2:$D$1000,History_Q!$C$2:$C$1000,"operating_income",History_Q!$B$2:$B$1000,">="&((SUMIFS(History_Q!$B$2:$B$1000,History_Q!$A$2:$A$1000,G$6,History_Q!$C$2:$C$1000,"operating_income"))-3),History_Q!$B$2:$B$1000,"<="&(SUMIFS(History_Q!$B$2:$B$1000,History_Q!$A$2:$A$1000,G$6,History_Q!$C$2:$C$1000,"operating_income")),History_Q!$E$2:$E$1000,"$m",History_Q!$G$2:$G$1000,"populated")) | H34: =IF(OR(H$6="",COUNTIFS(History_Q!$C$2:$C$1000,"operating_income",History_Q!$B$2:$B$1000,">="&((SUMIFS(History_Q!$B$2:$B$1000,History_Q!$A$2:$A$1000,H$6,History_Q!$C$2:$C$1000,"operating_income"))-3),History_Q!$B$2:$B$1000,"<="&(SUMIFS(History_Q!$B$2:$B$1000,History_Q!$A$2:$A$1000,H$6,History_Q!$C$2:$C$1000,"operating_income")),History_Q!$E$2:$E$1000,"$m",History_Q!$G$2:$G$1000,"populated")<>4,_xlfn.MAXIFS(History_Q!$B$2:$B$1000,History_Q!$C$2:$C$1000,"operating_income",History_Q!$B$2:$B$1000,">="&((SUMIFS(History_Q!$B$2:$B$1000,History_Q!$A$2:$A$1000,H$6,History_Q!$C$2:$C$1000,"operating_income"))-3),History_Q!$B$2:$B$1000,"<="&(SUMIFS(History_Q!$B$2:$B$1000,History_Q!$A$2:$A$1000,H$6,History_Q!$C$2:$C$1000,"operating_income")),History_Q!$E$2:$E$1000,"$m",History_Q!$G$2:$G$1000,"populated")-_xlfn.MINIFS(History_Q!$B$2:$B$1000,History_Q!$C$2:$C$1000,"operating_income",History_Q!$B$2:$B$1000,">="&((SUMIFS(History_Q!$B$2:$B$1000,History_Q!$A$2:$A$1000,H$6,History_Q!$C$2:$C$1000,"operating_income"))-3),History_Q!$B$2:$B$1000,"<="&(SUMIFS(History_Q!$B$2:$B$1000,History_Q!$A$2:$A$1000,H$6,History_Q!$C$2:$C$1000,"operating_income")),History_Q!$E$2:$E$1000,"$m",History_Q!$G$2:$G$1000,"populated")<>3),"",SUMIFS(History_Q!$D$2:$D$1000,History_Q!$C$2:$C$1000,"operating_income",History_Q!$B$2:$B$1000,">="&((SUMIFS(History_Q!$B$2:$B$1000,History_Q!$A$2:$A$1000,H$6,History_Q!$C$2:$C$1000,"operating_income"))-3),History_Q!$B$2:$B$1000,"<="&(SUMIFS(History_Q!$B$2:$B$1000,History_Q!$A$2:$A$1000,H$6,History_Q!$C$2:$C$1000,"operating_income")),History_Q!$E$2:$E$1000,"$m",History_Q!$G$2:$G$1000,"populated")) | I34: =IF(OR(I$6="",COUNTIFS(History_Q!$C$2:$C$1000,"operating_income",History_Q!$B$2:$B$1000,">="&((SUMIFS(History_Q!$B$2:$B$1000,History_Q!$A$2:$A$1000,I$6,History_Q!$C$2:$C$1000,"operating_income"))-3),History_Q!$B$2:$B$1000,"<="&(SUMIFS(History_Q!$B$2:$B$1000,History_Q!$A$2:$A$1000,I$6,History_Q!$C$2:$C$1000,"operating_income")),History_Q!$E$2:$E$1000,"$m",History_Q!$G$2:$G$1000,"populated")<>4,_xlfn.MAXIFS(History_Q!$B$2:$B$1000,History_Q!$C$2:$C$1000,"operating_income",History_Q!$B$2:$B$1000,">="&((SUMIFS(History_Q!$B$2:$B$1000,History_Q!$A$2:$A$1000,I$6,History_Q!$C$2:$C$1000,"operating_income"))-3),History_Q!$B$2:$B$1000,"<="&(SUMIFS(History_Q!$B$2:$B$1000,History_Q!$A$2:$A$1000,I$6,History_Q!$C$2:$C$1000,"operating_income")),History_Q!$E$2:$E$1000,"$m",History_Q!$G$2:$G$1000,"populated")-_xlfn.MINIFS(History_Q!$B$2:$B$1000,History_Q!$C$2:$C$1000,"operating_income",History_Q!$B$2:$B$1000,">="&((SUMIFS(History_Q!$B$2:$B$1000,History_Q!$A$2:$A$1000,I$6,History_Q!$C$2:$C$1000,"operating_income"))-3),History_Q!$B$2:$B$1000,"<="&(SUMIFS(History_Q!$B$2:$B$1000,History_Q!$A$2:$A$1000,I$6,History_Q!$C$2:$C$1000,"operating_income")),History_Q!$E$2:$E$1000,"$m",History_Q!$G$2:$G$1000,"populated")<>3),"",SUMIFS(History_Q!$D$2:$D$1000,History_Q!$C$2:$C$1000,"operating_income",History_Q!$B$2:$B$1000,">="&((SUMIFS(History_Q!$B$2:$B$1000,History_Q!$A$2:$A$1000,I$6,History_Q!$C$2:$C$1000,"operating_income"))-3),History_Q!$B$2:$B$1000,"<="&(SUMIFS(History_Q!$B$2:$B$1000,History_Q!$A$2:$A$1000,I$6,History_Q!$C$2:$C$1000,"operating_income")),History_Q!$E$2:$E$1000,"$m",History_Q!$G$2:$G$1000,"populated")) | ... M34: =IF(OR(M$6="",COUNTIFS(History_Q!$C$2:$C$1000,"operating_income",History_Q!$B$2:$B$1000,">="&((SUMIFS(History_Q!$B$2:$B$1000,History_Q!$A$2:$A$1000,M$6,History_Q!$C$2:$C$1000,"operating_income"))-3),History_Q!$B$2:$B$1000,"<="&(SUMIFS(History_Q!$B$2:$B$1000,History_Q!$A$2:$A$1000,M$6,History_Q!$C$2:$C$1000,"operating_income")),History_Q!$E$2:$E$1000,"$m",History_Q!$G$2:$G$1000,"populated")<>4,_xlfn.MAXIFS(History_Q!$B$2:$B$1000,History_Q!$C$2:$C$1000,"operating_income",History_Q!$B$2:$B$1000,">="&((SUMIFS(History_Q!$B$2:$B$1000,History_Q!$A$2:$A$1000,M$6,History_Q!$C$2:$C$1000,"operating_income"))-3),History_Q!$B$2:$B$1000,"<="&(SUMIFS(History_Q!$B$2:$B$1000,History_Q!$A$2:$A$1000,M$6,History_Q!$C$2:$C$1000,"operating_income")),History_Q!$E$2:$E$1000,"$m",History_Q!$G$2:$G$1000,"populated")-_xlfn.MINIFS(History_Q!$B$2:$B$1000,History_Q!$C$2:$C$1000,"operating_income",History_Q!$B$2:$B$1000,">="&((SUMIFS(History_Q!$B$2:$B$1000,History_Q!$A$2:$A$1000,M$6,History_Q!$C$2:$C$1000,"operating_income"))-3),History_Q!$B$2:$B$1000,"<="&(SUMIFS(History_Q!$B$2:$B$1000,History_Q!$A$2:$A$1000,M$6,History_Q!$C$2:$C$1000,"operating_income")),History_Q!$E$2:$E$1000,"$m",History_Q!$G$2:$G$1000,"populated")<>3),"",SUMIFS(History_Q!$D$2:$D$1000,History_Q!$C$2:$C$1000,"operating_income",History_Q!$B$2:$B$1000,">="&((SUMIFS(History_Q!$B$2:$B$1000,History_Q!$A$2:$A$1000,M$6,History_Q!$C$2:$C$1000,"operating_income"))-3),History_Q!$B$2:$B$1000,"<="&(SUMIFS(History_Q!$B$2:$B$1000,History_Q!$A$2:$A$1000,M$6,History_Q!$C$2:$C$1000,"operating_income")),History_Q!$E$2:$E$1000,"$m",History_Q!$G$2:$G$1000,"populated"))
A35: EBIT margin (TTM) | B35: =IF(OR(B34="",B10="",B10=0),"",B34/B10) | C35: =IF(OR(C34="",C10="",C10=0),"",C34/C10) | D35: =IF(OR(D34="",D10="",D10=0),"",D34/D10) | E35: =IF(OR(E34="",E10="",E10=0),"",E34/E10) | F35: =IF(OR(F34="",F10="",F10=0),"",F34/F10) | G35: =IF(OR(G34="",G10="",G10=0),"",G34/G10) | H35: =IF(OR(H34="",H10="",H10=0),"",H34/H10) | I35: =IF(OR(I34="",I10="",I10=0),"",I34/I10) | ... M35: =IF(OR(M34="",M10="",M10=0),"",M34/M10)
A36: Net income
A37: Net margin % | B37: =IF(OR(B36="",B9="",B9=0),"",B36/B9) | C37: =IF(OR(C36="",C9="",C9=0),"",C36/C9) | D37: =IF(OR(D36="",D9="",D9=0),"",D36/D9) | E37: =IF(OR(E36="",E9="",E9=0),"",E36/E9) | F37: =IF(OR(F36="",F9="",F9=0),"",F36/F9) | G37: =IF(OR(G36="",G9="",G9=0),"",G36/G9) | H37: =IF(OR(H36="",H9="",H9=0),"",H36/H9) | I37: =IF(OR(I36="",I9="",I9=0),"",I36/I9) | ... M37: =IF(OR(M36="",M9="",M9=0),"",M36/M9)
A38: Net income YoY % | B38: =IF(OR(B$6="",COUNTIFS(History_Q!$C$2:$C$1000,"net_income",History_Q!$B$2:$B$1000,(SUMIFS(History_Q!$B$2:$B$1000,History_Q!$A$2:$A$1000,B$6,History_Q!$C$2:$C$1000,"net_income")),History_Q!$E$2:$E$1000,"$m",History_Q!$G$2:$G$1000,"populated")<>1,COUNTIFS(History_Q!$C$2:$C$1000,"net_income",History_Q!$B$2:$B$1000,(SUMIFS(History_Q!$B$2:$B$1000,History_Q!$A$2:$A$1000,B$6,History_Q!$C$2:$C$1000,"net_income")-4),History_Q!$E$2:$E$1000,"$m",History_Q!$G$2:$G$1000,"populated")<>1,SUMIFS(History_Q!$D$2:$D$1000,History_Q!$C$2:$C$1000,"net_income",History_Q!$B$2:$B$1000,(SUMIFS(History_Q!$B$2:$B$1000,History_Q!$A$2:$A$1000,B$6,History_Q!$C$2:$C$1000,"net_income")-4),History_Q!$E$2:$E$1000,"$m",History_Q!$G$2:$G$1000,"populated")=0),"",SUMIFS(History_Q!$D$2:$D$1000,History_Q!$C$2:$C$1000,"net_income",History_Q!$B$2:$B$1000,(SUMIFS(History_Q!$B$2:$B$1000,History_Q!$A$2:$A$1000,B$6,History_Q!$C$2:$C$1000,"net_income")),History_Q!$E$2:$E$1000,"$m",History_Q!$G$2:$G$1000,"populated")/SUMIFS(History_Q!$D$2:$D$1000,History_Q!$C$2:$C$1000,"net_income",History_Q!$B$2:$B$1000,(SUMIFS(History_Q!$B$2:$B$1000,History_Q!$A$2:$A$1000,B$6,History_Q!$C$2:$C$1000,"net_income")-4),History_Q!$E$2:$E$1000,"$m",History_Q!$G$2:$G$1000,"populated")-1) | C38: =IF(OR(C$6="",COUNTIFS(History_Q!$C$2:$C$1000,"net_income",History_Q!$B$2:$B$1000,(SUMIFS(History_Q!$B$2:$B$1000,History_Q!$A$2:$A$1000,C$6,History_Q!$C$2:$C$1000,"net_income")),History_Q!$E$2:$E$1000,"$m",History_Q!$G$2:$G$1000,"populated")<>1,COUNTIFS(History_Q!$C$2:$C$1000,"net_income",History_Q!$B$2:$B$1000,(SUMIFS(History_Q!$B$2:$B$1000,History_Q!$A$2:$A$1000,C$6,History_Q!$C$2:$C$1000,"net_income")-4),History_Q!$E$2:$E$1000,"$m",History_Q!$G$2:$G$1000,"populated")<>1,SUMIFS(History_Q!$D$2:$D$1000,History_Q!$C$2:$C$1000,"net_income",History_Q!$B$2:$B$1000,(SUMIFS(History_Q!$B$2:$B$1000,History_Q!$A$2:$A$1000,C$6,History_Q!$C$2:$C$1000,"net_income")-4),History_Q!$E$2:$E$1000,"$m",History_Q!$G$2:$G$1000,"populated")=0),"",SUMIFS(History_Q!$D$2:$D$1000,History_Q!$C$2:$C$1000,"net_income",History_Q!$B$2:$B$1000,(SUMIFS(History_Q!$B$2:$B$1000,History_Q!$A$2:$A$1000,C$6,History_Q!$C$2:$C$1000,"net_income")),History_Q!$E$2:$E$1000,"$m",History_Q!$G$2:$G$1000,"populated")/SUMIFS(History_Q!$D$2:$D$1000,History_Q!$C$2:$C$1000,"net_income",History_Q!$B$2:$B$1000,(SUMIFS(History_Q!$B$2:$B$1000,History_Q!$A$2:$A$1000,C$6,History_Q!$C$2:$C$1000,"net_income")-4),History_Q!$E$2:$E$1000,"$m",History_Q!$G$2:$G$1000,"populated")-1) | D38: =IF(OR(D$6="",COUNTIFS(History_Q!$C$2:$C$1000,"net_income",History_Q!$B$2:$B$1000,(SUMIFS(History_Q!$B$2:$B$1000,History_Q!$A$2:$A$1000,D$6,History_Q!$C$2:$C$1000,"net_income")),History_Q!$E$2:$E$1000,"$m",History_Q!$G$2:$G$1000,"populated")<>1,COUNTIFS(History_Q!$C$2:$C$1000,"net_income",History_Q!$B$2:$B$1000,(SUMIFS(History_Q!$B$2:$B$1000,History_Q!$A$2:$A$1000,D$6,History_Q!$C$2:$C$1000,"net_income")-4),History_Q!$E$2:$E$1000,"$m",History_Q!$G$2:$G$1000,"populated")<>1,SUMIFS(History_Q!$D$2:$D$1000,History_Q!$C$2:$C$1000,"net_income",History_Q!$B$2:$B$1000,(SUMIFS(History_Q!$B$2:$B$1000,History_Q!$A$2:$A$1000,D$6,History_Q!$C$2:$C$1000,"net_income")-4),History_Q!$E$2:$E$1000,"$m",History_Q!$G$2:$G$1000,"populated")=0),"",SUMIFS(History_Q!$D$2:$D$1000,History_Q!$C$2:$C$1000,"net_income",History_Q!$B$2:$B$1000,(SUMIFS(History_Q!$B$2:$B$1000,History_Q!$A$2:$A$1000,D$6,History_Q!$C$2:$C$1000,"net_income")),History_Q!$E$2:$E$1000,"$m",History_Q!$G$2:$G$1000,"populated")/SUMIFS(History_Q!$D$2:$D$1000,History_Q!$C$2:$C$1000,"net_income",History_Q!$B$2:$B$1000,(SUMIFS(History_Q!$B$2:$B$1000,History_Q!$A$2:$A$1000,D$6,History_Q!$C$2:$C$1000,"net_income")-4),History_Q!$E$2:$E$1000,"$m",History_Q!$G$2:$G$1000,"populated")-1) | E38: =IF(OR(E$6="",COUNTIFS(History_Q!$C$2:$C$1000,"net_income",History_Q!$B$2:$B$1000,(SUMIFS(History_Q!$B$2:$B$1000,History_Q!$A$2:$A$1000,E$6,History_Q!$C$2:$C$1000,"net_income")),History_Q!$E$2:$E$1000,"$m",History_Q!$G$2:$G$1000,"populated")<>1,COUNTIFS(History_Q!$C$2:$C$1000,"net_income",History_Q!$B$2:$B$1000,(SUMIFS(History_Q!$B$2:$B$1000,History_Q!$A$2:$A$1000,E$6,History_Q!$C$2:$C$1000,"net_income")-4),History_Q!$E$2:$E$1000,"$m",History_Q!$G$2:$G$1000,"populated")<>1,SUMIFS(History_Q!$D$2:$D$1000,History_Q!$C$2:$C$1000,"net_income",History_Q!$B$2:$B$1000,(SUMIFS(History_Q!$B$2:$B$1000,History_Q!$A$2:$A$1000,E$6,History_Q!$C$2:$C$1000,"net_income")-4),History_Q!$E$2:$E$1000,"$m",History_Q!$G$2:$G$1000,"populated")=0),"",SUMIFS(History_Q!$D$2:$D$1000,History_Q!$C$2:$C$1000,"net_income",History_Q!$B$2:$B$1000,(SUMIFS(History_Q!$B$2:$B$1000,History_Q!$A$2:$A$1000,E$6,History_Q!$C$2:$C$1000,"net_income")),History_Q!$E$2:$E$1000,"$m",History_Q!$G$2:$G$1000,"populated")/SUMIFS(History_Q!$D$2:$D$1000,History_Q!$C$2:$C$1000,"net_income",History_Q!$B$2:$B$1000,(SUMIFS(History_Q!$B$2:$B$1000,History_Q!$A$2:$A$1000,E$6,History_Q!$C$2:$C$1000,"net_income")-4),History_Q!$E$2:$E$1000,"$m",History_Q!$G$2:$G$1000,"populated")-1) | F38: =IF(OR(F$6="",COUNTIFS(History_Q!$C$2:$C$1000,"net_income",History_Q!$B$2:$B$1000,(SUMIFS(History_Q!$B$2:$B$1000,History_Q!$A$2:$A$1000,F$6,History_Q!$C$2:$C$1000,"net_income")),History_Q!$E$2:$E$1000,"$m",History_Q!$G$2:$G$1000,"populated")<>1,COUNTIFS(History_Q!$C$2:$C$1000,"net_income",History_Q!$B$2:$B$1000,(SUMIFS(History_Q!$B$2:$B$1000,History_Q!$A$2:$A$1000,F$6,History_Q!$C$2:$C$1000,"net_income")-4),History_Q!$E$2:$E$1000,"$m",History_Q!$G$2:$G$1000,"populated")<>1,SUMIFS(History_Q!$D$2:$D$1000,History_Q!$C$2:$C$1000,"net_income",History_Q!$B$2:$B$1000,(SUMIFS(History_Q!$B$2:$B$1000,History_Q!$A$2:$A$1000,F$6,History_Q!$C$2:$C$1000,"net_income")-4),History_Q!$E$2:$E$1000,"$m",History_Q!$G$2:$G$1000,"populated")=0),"",SUMIFS(History_Q!$D$2:$D$1000,History_Q!$C$2:$C$1000,"net_income",History_Q!$B$2:$B$1000,(SUMIFS(History_Q!$B$2:$B$1000,History_Q!$A$2:$A$1000,F$6,History_Q!$C$2:$C$1000,"net_income")),History_Q!$E$2:$E$1000,"$m",History_Q!$G$2:$G$1000,"populated")/SUMIFS(History_Q!$D$2:$D$1000,History_Q!$C$2:$C$1000,"net_income",History_Q!$B$2:$B$1000,(SUMIFS(History_Q!$B$2:$B$1000,History_Q!$A$2:$A$1000,F$6,History_Q!$C$2:$C$1000,"net_income")-4),History_Q!$E$2:$E$1000,"$m",History_Q!$G$2:$G$1000,"populated")-1) | G38: =IF(OR(G$6="",COUNTIFS(History_Q!$C$2:$C$1000,"net_income",History_Q!$B$2:$B$1000,(SUMIFS(History_Q!$B$2:$B$1000,History_Q!$A$2:$A$1000,G$6,History_Q!$C$2:$C$1000,"net_income")),History_Q!$E$2:$E$1000,"$m",History_Q!$G$2:$G$1000,"populated")<>1,COUNTIFS(History_Q!$C$2:$C$1000,"net_income",History_Q!$B$2:$B$1000,(SUMIFS(History_Q!$B$2:$B$1000,History_Q!$A$2:$A$1000,G$6,History_Q!$C$2:$C$1000,"net_income")-4),History_Q!$E$2:$E$1000,"$m",History_Q!$G$2:$G$1000,"populated")<>1,SUMIFS(History_Q!$D$2:$D$1000,History_Q!$C$2:$C$1000,"net_income",History_Q!$B$2:$B$1000,(SUMIFS(History_Q!$B$2:$B$1000,History_Q!$A$2:$A$1000,G$6,History_Q!$C$2:$C$1000,"net_income")-4),History_Q!$E$2:$E$1000,"$m",History_Q!$G$2:$G$1000,"populated")=0),"",SUMIFS(History_Q!$D$2:$D$1000,History_Q!$C$2:$C$1000,"net_income",History_Q!$B$2:$B$1000,(SUMIFS(History_Q!$B$2:$B$1000,History_Q!$A$2:$A$1000,G$6,History_Q!$C$2:$C$1000,"net_income")),History_Q!$E$2:$E$1000,"$m",History_Q!$G$2:$G$1000,"populated")/SUMIFS(History_Q!$D$2:$D$1000,History_Q!$C$2:$C$1000,"net_income",History_Q!$B$2:$B$1000,(SUMIFS(History_Q!$B$2:$B$1000,History_Q!$A$2:$A$1000,G$6,History_Q!$C$2:$C$1000,"net_income")-4),History_Q!$E$2:$E$1000,"$m",History_Q!$G$2:$G$1000,"populated")-1) | H38: =IF(OR(H$6="",COUNTIFS(History_Q!$C$2:$C$1000,"net_income",History_Q!$B$2:$B$1000,(SUMIFS(History_Q!$B$2:$B$1000,History_Q!$A$2:$A$1000,H$6,History_Q!$C$2:$C$1000,"net_income")),History_Q!$E$2:$E$1000,"$m",History_Q!$G$2:$G$1000,"populated")<>1,COUNTIFS(History_Q!$C$2:$C$1000,"net_income",History_Q!$B$2:$B$1000,(SUMIFS(History_Q!$B$2:$B$1000,History_Q!$A$2:$A$1000,H$6,History_Q!$C$2:$C$1000,"net_income")-4),History_Q!$E$2:$E$1000,"$m",History_Q!$G$2:$G$1000,"populated")<>1,SUMIFS(History_Q!$D$2:$D$1000,History_Q!$C$2:$C$1000,"net_income",History_Q!$B$2:$B$1000,(SUMIFS(History_Q!$B$2:$B$1000,History_Q!$A$2:$A$1000,H$6,History_Q!$C$2:$C$1000,"net_income")-4),History_Q!$E$2:$E$1000,"$m",History_Q!$G$2:$G$1000,"populated")=0),"",SUMIFS(History_Q!$D$2:$D$1000,History_Q!$C$2:$C$1000,"net_income",History_Q!$B$2:$B$1000,(SUMIFS(History_Q!$B$2:$B$1000,History_Q!$A$2:$A$1000,H$6,History_Q!$C$2:$C$1000,"net_income")),History_Q!$E$2:$E$1000,"$m",History_Q!$G$2:$G$1000,"populated")/SUMIFS(History_Q!$D$2:$D$1000,History_Q!$C$2:$C$1000,"net_income",History_Q!$B$2:$B$1000,(SUMIFS(History_Q!$B$2:$B$1000,History_Q!$A$2:$A$1000,H$6,History_Q!$C$2:$C$1000,"net_income")-4),History_Q!$E$2:$E$1000,"$m",History_Q!$G$2:$G$1000,"populated")-1) | I38: =IF(OR(I$6="",COUNTIFS(History_Q!$C$2:$C$1000,"net_income",History_Q!$B$2:$B$1000,(SUMIFS(History_Q!$B$2:$B$1000,History_Q!$A$2:$A$1000,I$6,History_Q!$C$2:$C$1000,"net_income")),History_Q!$E$2:$E$1000,"$m",History_Q!$G$2:$G$1000,"populated")<>1,COUNTIFS(History_Q!$C$2:$C$1000,"net_income",History_Q!$B$2:$B$1000,(SUMIFS(History_Q!$B$2:$B$1000,History_Q!$A$2:$A$1000,I$6,History_Q!$C$2:$C$1000,"net_income")-4),History_Q!$E$2:$E$1000,"$m",History_Q!$G$2:$G$1000,"populated")<>1,SUMIFS(History_Q!$D$2:$D$1000,History_Q!$C$2:$C$1000,"net_income",History_Q!$B$2:$B$1000,(SUMIFS(History_Q!$B$2:$B$1000,History_Q!$A$2:$A$1000,I$6,History_Q!$C$2:$C$1000,"net_income")-4),History_Q!$E$2:$E$1000,"$m",History_Q!$G$2:$G$1000,"populated")=0),"",SUMIFS(History_Q!$D$2:$D$1000,History_Q!$C$2:$C$1000,"net_income",History_Q!$B$2:$B$1000,(SUMIFS(History_Q!$B$2:$B$1000,History_Q!$A$2:$A$1000,I$6,History_Q!$C$2:$C$1000,"net_income")),History_Q!$E$2:$E$1000,"$m",History_Q!$G$2:$G$1000,"populated")/SUMIFS(History_Q!$D$2:$D$1000,History_Q!$C$2:$C$1000,"net_income",History_Q!$B$2:$B$1000,(SUMIFS(History_Q!$B$2:$B$1000,History_Q!$A$2:$A$1000,I$6,History_Q!$C$2:$C$1000,"net_income")-4),History_Q!$E$2:$E$1000,"$m",History_Q!$G$2:$G$1000,"populated")-1) | ... M38: =IF(OR(M$6="",COUNTIFS(History_Q!$C$2:$C$1000,"net_income",History_Q!$B$2:$B$1000,(SUMIFS(History_Q!$B$2:$B$1000,History_Q!$A$2:$A$1000,M$6,History_Q!$C$2:$C$1000,"net_income")),History_Q!$E$2:$E$1000,"$m",History_Q!$G$2:$G$1000,"populated")<>1,COUNTIFS(History_Q!$C$2:$C$1000,"net_income",History_Q!$B$2:$B$1000,(SUMIFS(History_Q!$B$2:$B$1000,History_Q!$A$2:$A$1000,M$6,History_Q!$C$2:$C$1000,"net_income")-4),History_Q!$E$2:$E$1000,"$m",History_Q!$G$2:$G$1000,"populated")<>1,SUMIFS(History_Q!$D$2:$D$1000,History_Q!$C$2:$C$1000,"net_income",History_Q!$B$2:$B$1000,(SUMIFS(History_Q!$B$2:$B$1000,History_Q!$A$2:$A$1000,M$6,History_Q!$C$2:$C$1000,"net_income")-4),History_Q!$E$2:$E$1000,"$m",History_Q!$G$2:$G$1000,"populated")=0),"",SUMIFS(History_Q!$D$2:$D$1000,History_Q!$C$2:$C$1000,"net_income",History_Q!$B$2:$B$1000,(SUMIFS(History_Q!$B$2:$B$1000,History_Q!$A$2:$A$1000,M$6,History_Q!$C$2:$C$1000,"net_income")),History_Q!$E$2:$E$1000,"$m",History_Q!$G$2:$G$1000,"populated")/SUMIFS(History_Q!$D$2:$D$1000,History_Q!$C$2:$C$1000,"net_income",History_Q!$B$2:$B$1000,(SUMIFS(History_Q!$B$2:$B$1000,History_Q!$A$2:$A$1000,M$6,History_Q!$C$2:$C$1000,"net_income")-4),History_Q!$E$2:$E$1000,"$m",History_Q!$G$2:$G$1000,"populated")-1)
A39: Net income (TTM) | B39: =IF(OR(B$6="",COUNTIFS(History_Q!$C$2:$C$1000,"net_income",History_Q!$B$2:$B$1000,">="&((SUMIFS(History_Q!$B$2:$B$1000,History_Q!$A$2:$A$1000,B$6,History_Q!$C$2:$C$1000,"net_income"))-3),History_Q!$B$2:$B$1000,"<="&(SUMIFS(History_Q!$B$2:$B$1000,History_Q!$A$2:$A$1000,B$6,History_Q!$C$2:$C$1000,"net_income")),History_Q!$E$2:$E$1000,"$m",History_Q!$G$2:$G$1000,"populated")<>4,_xlfn.MAXIFS(History_Q!$B$2:$B$1000,History_Q!$C$2:$C$1000,"net_income",History_Q!$B$2:$B$1000,">="&((SUMIFS(History_Q!$B$2:$B$1000,History_Q!$A$2:$A$1000,B$6,History_Q!$C$2:$C$1000,"net_income"))-3),History_Q!$B$2:$B$1000,"<="&(SUMIFS(History_Q!$B$2:$B$1000,History_Q!$A$2:$A$1000,B$6,History_Q!$C$2:$C$1000,"net_income")),History_Q!$E$2:$E$1000,"$m",History_Q!$G$2:$G$1000,"populated")-_xlfn.MINIFS(History_Q!$B$2:$B$1000,History_Q!$C$2:$C$1000,"net_income",History_Q!$B$2:$B$1000,">="&((SUMIFS(History_Q!$B$2:$B$1000,History_Q!$A$2:$A$1000,B$6,History_Q!$C$2:$C$1000,"net_income"))-3),History_Q!$B$2:$B$1000,"<="&(SUMIFS(History_Q!$B$2:$B$1000,History_Q!$A$2:$A$1000,B$6,History_Q!$C$2:$C$1000,"net_income")),History_Q!$E$2:$E$1000,"$m",History_Q!$G$2:$G$1000,"populated")<>3),"",SUMIFS(History_Q!$D$2:$D$1000,History_Q!$C$2:$C$1000,"net_income",History_Q!$B$2:$B$1000,">="&((SUMIFS(History_Q!$B$2:$B$1000,History_Q!$A$2:$A$1000,B$6,History_Q!$C$2:$C$1000,"net_income"))-3),History_Q!$B$2:$B$1000,"<="&(SUMIFS(History_Q!$B$2:$B$1000,History_Q!$A$2:$A$1000,B$6,History_Q!$C$2:$C$1000,"net_income")),History_Q!$E$2:$E$1000,"$m",History_Q!$G$2:$G$1000,"populated")) | C39: =IF(OR(C$6="",COUNTIFS(History_Q!$C$2:$C$1000,"net_income",History_Q!$B$2:$B$1000,">="&((SUMIFS(History_Q!$B$2:$B$1000,History_Q!$A$2:$A$1000,C$6,History_Q!$C$2:$C$1000,"net_income"))-3),History_Q!$B$2:$B$1000,"<="&(SUMIFS(History_Q!$B$2:$B$1000,History_Q!$A$2:$A$1000,C$6,History_Q!$C$2:$C$1000,"net_income")),History_Q!$E$2:$E$1000,"$m",History_Q!$G$2:$G$1000,"populated")<>4,_xlfn.MAXIFS(History_Q!$B$2:$B$1000,History_Q!$C$2:$C$1000,"net_income",History_Q!$B$2:$B$1000,">="&((SUMIFS(History_Q!$B$2:$B$1000,History_Q!$A$2:$A$1000,C$6,History_Q!$C$2:$C$1000,"net_income"))-3),History_Q!$B$2:$B$1000,"<="&(SUMIFS(History_Q!$B$2:$B$1000,History_Q!$A$2:$A$1000,C$6,History_Q!$C$2:$C$1000,"net_income")),History_Q!$E$2:$E$1000,"$m",History_Q!$G$2:$G$1000,"populated")-_xlfn.MINIFS(History_Q!$B$2:$B$1000,History_Q!$C$2:$C$1000,"net_income",History_Q!$B$2:$B$1000,">="&((SUMIFS(History_Q!$B$2:$B$1000,History_Q!$A$2:$A$1000,C$6,History_Q!$C$2:$C$1000,"net_income"))-3),History_Q!$B$2:$B$1000,"<="&(SUMIFS(History_Q!$B$2:$B$1000,History_Q!$A$2:$A$1000,C$6,History_Q!$C$2:$C$1000,"net_income")),History_Q!$E$2:$E$1000,"$m",History_Q!$G$2:$G$1000,"populated")<>3),"",SUMIFS(History_Q!$D$2:$D$1000,History_Q!$C$2:$C$1000,"net_income",History_Q!$B$2:$B$1000,">="&((SUMIFS(History_Q!$B$2:$B$1000,History_Q!$A$2:$A$1000,C$6,History_Q!$C$2:$C$1000,"net_income"))-3),History_Q!$B$2:$B$1000,"<="&(SUMIFS(History_Q!$B$2:$B$1000,History_Q!$A$2:$A$1000,C$6,History_Q!$C$2:$C$1000,"net_income")),History_Q!$E$2:$E$1000,"$m",History_Q!$G$2:$G$1000,"populated")) | D39: =IF(OR(D$6="",COUNTIFS(History_Q!$C$2:$C$1000,"net_income",History_Q!$B$2:$B$1000,">="&((SUMIFS(History_Q!$B$2:$B$1000,History_Q!$A$2:$A$1000,D$6,History_Q!$C$2:$C$1000,"net_income"))-3),History_Q!$B$2:$B$1000,"<="&(SUMIFS(History_Q!$B$2:$B$1000,History_Q!$A$2:$A$1000,D$6,History_Q!$C$2:$C$1000,"net_income")),History_Q!$E$2:$E$1000,"$m",History_Q!$G$2:$G$1000,"populated")<>4,_xlfn.MAXIFS(History_Q!$B$2:$B$1000,History_Q!$C$2:$C$1000,"net_income",History_Q!$B$2:$B$1000,">="&((SUMIFS(History_Q!$B$2:$B$1000,History_Q!$A$2:$A$1000,D$6,History_Q!$C$2:$C$1000,"net_income"))-3),History_Q!$B$2:$B$1000,"<="&(SUMIFS(History_Q!$B$2:$B$1000,History_Q!$A$2:$A$1000,D$6,History_Q!$C$2:$C$1000,"net_income")),History_Q!$E$2:$E$1000,"$m",History_Q!$G$2:$G$1000,"populated")-_xlfn.MINIFS(History_Q!$B$2:$B$1000,History_Q!$C$2:$C$1000,"net_income",History_Q!$B$2:$B$1000,">="&((SUMIFS(History_Q!$B$2:$B$1000,History_Q!$A$2:$A$1000,D$6,History_Q!$C$2:$C$1000,"net_income"))-3),History_Q!$B$2:$B$1000,"<="&(SUMIFS(History_Q!$B$2:$B$1000,History_Q!$A$2:$A$1000,D$6,History_Q!$C$2:$C$1000,"net_income")),History_Q!$E$2:$E$1000,"$m",History_Q!$G$2:$G$1000,"populated")<>3),"",SUMIFS(History_Q!$D$2:$D$1000,History_Q!$C$2:$C$1000,"net_income",History_Q!$B$2:$B$1000,">="&((SUMIFS(History_Q!$B$2:$B$1000,History_Q!$A$2:$A$1000,D$6,History_Q!$C$2:$C$1000,"net_income"))-3),History_Q!$B$2:$B$1000,"<="&(SUMIFS(History_Q!$B$2:$B$1000,History_Q!$A$2:$A$1000,D$6,History_Q!$C$2:$C$1000,"net_income")),History_Q!$E$2:$E$1000,"$m",History_Q!$G$2:$G$1000,"populated")) | E39: =IF(OR(E$6="",COUNTIFS(History_Q!$C$2:$C$1000,"net_income",History_Q!$B$2:$B$1000,">="&((SUMIFS(History_Q!$B$2:$B$1000,History_Q!$A$2:$A$1000,E$6,History_Q!$C$2:$C$1000,"net_income"))-3),History_Q!$B$2:$B$1000,"<="&(SUMIFS(History_Q!$B$2:$B$1000,History_Q!$A$2:$A$1000,E$6,History_Q!$C$2:$C$1000,"net_income")),History_Q!$E$2:$E$1000,"$m",History_Q!$G$2:$G$1000,"populated")<>4,_xlfn.MAXIFS(History_Q!$B$2:$B$1000,History_Q!$C$2:$C$1000,"net_income",History_Q!$B$2:$B$1000,">="&((SUMIFS(History_Q!$B$2:$B$1000,History_Q!$A$2:$A$1000,E$6,History_Q!$C$2:$C$1000,"net_income"))-3),History_Q!$B$2:$B$1000,"<="&(SUMIFS(History_Q!$B$2:$B$1000,History_Q!$A$2:$A$1000,E$6,History_Q!$C$2:$C$1000,"net_income")),History_Q!$E$2:$E$1000,"$m",History_Q!$G$2:$G$1000,"populated")-_xlfn.MINIFS(History_Q!$B$2:$B$1000,History_Q!$C$2:$C$1000,"net_income",History_Q!$B$2:$B$1000,">="&((SUMIFS(History_Q!$B$2:$B$1000,History_Q!$A$2:$A$1000,E$6,History_Q!$C$2:$C$1000,"net_income"))-3),History_Q!$B$2:$B$1000,"<="&(SUMIFS(History_Q!$B$2:$B$1000,History_Q!$A$2:$A$1000,E$6,History_Q!$C$2:$C$1000,"net_income")),History_Q!$E$2:$E$1000,"$m",History_Q!$G$2:$G$1000,"populated")<>3),"",SUMIFS(History_Q!$D$2:$D$1000,History_Q!$C$2:$C$1000,"net_income",History_Q!$B$2:$B$1000,">="&((SUMIFS(History_Q!$B$2:$B$1000,History_Q!$A$2:$A$1000,E$6,History_Q!$C$2:$C$1000,"net_income"))-3),History_Q!$B$2:$B$1000,"<="&(SUMIFS(History_Q!$B$2:$B$1000,History_Q!$A$2:$A$1000,E$6,History_Q!$C$2:$C$1000,"net_income")),History_Q!$E$2:$E$1000,"$m",History_Q!$G$2:$G$1000,"populated")) | F39: =IF(OR(F$6="",COUNTIFS(History_Q!$C$2:$C$1000,"net_income",History_Q!$B$2:$B$1000,">="&((SUMIFS(History_Q!$B$2:$B$1000,History_Q!$A$2:$A$1000,F$6,History_Q!$C$2:$C$1000,"net_income"))-3),History_Q!$B$2:$B$1000,"<="&(SUMIFS(History_Q!$B$2:$B$1000,History_Q!$A$2:$A$1000,F$6,History_Q!$C$2:$C$1000,"net_income")),History_Q!$E$2:$E$1000,"$m",History_Q!$G$2:$G$1000,"populated")<>4,_xlfn.MAXIFS(History_Q!$B$2:$B$1000,History_Q!$C$2:$C$1000,"net_income",History_Q!$B$2:$B$1000,">="&((SUMIFS(History_Q!$B$2:$B$1000,History_Q!$A$2:$A$1000,F$6,History_Q!$C$2:$C$1000,"net_income"))-3),History_Q!$B$2:$B$1000,"<="&(SUMIFS(History_Q!$B$2:$B$1000,History_Q!$A$2:$A$1000,F$6,History_Q!$C$2:$C$1000,"net_income")),History_Q!$E$2:$E$1000,"$m",History_Q!$G$2:$G$1000,"populated")-_xlfn.MINIFS(History_Q!$B$2:$B$1000,History_Q!$C$2:$C$1000,"net_income",History_Q!$B$2:$B$1000,">="&((SUMIFS(History_Q!$B$2:$B$1000,History_Q!$A$2:$A$1000,F$6,History_Q!$C$2:$C$1000,"net_income"))-3),History_Q!$B$2:$B$1000,"<="&(SUMIFS(History_Q!$B$2:$B$1000,History_Q!$A$2:$A$1000,F$6,History_Q!$C$2:$C$1000,"net_income")),History_Q!$E$2:$E$1000,"$m",History_Q!$G$2:$G$1000,"populated")<>3),"",SUMIFS(History_Q!$D$2:$D$1000,History_Q!$C$2:$C$1000,"net_income",History_Q!$B$2:$B$1000,">="&((SUMIFS(History_Q!$B$2:$B$1000,History_Q!$A$2:$A$1000,F$6,History_Q!$C$2:$C$1000,"net_income"))-3),History_Q!$B$2:$B$1000,"<="&(SUMIFS(History_Q!$B$2:$B$1000,History_Q!$A$2:$A$1000,F$6,History_Q!$C$2:$C$1000,"net_income")),History_Q!$E$2:$E$1000,"$m",History_Q!$G$2:$G$1000,"populated")) | G39: =IF(OR(G$6="",COUNTIFS(History_Q!$C$2:$C$1000,"net_income",History_Q!$B$2:$B$1000,">="&((SUMIFS(History_Q!$B$2:$B$1000,History_Q!$A$2:$A$1000,G$6,History_Q!$C$2:$C$1000,"net_income"))-3),History_Q!$B$2:$B$1000,"<="&(SUMIFS(History_Q!$B$2:$B$1000,History_Q!$A$2:$A$1000,G$6,History_Q!$C$2:$C$1000,"net_income")),History_Q!$E$2:$E$1000,"$m",History_Q!$G$2:$G$1000,"populated")<>4,_xlfn.MAXIFS(History_Q!$B$2:$B$1000,History_Q!$C$2:$C$1000,"net_income",History_Q!$B$2:$B$1000,">="&((SUMIFS(History_Q!$B$2:$B$1000,History_Q!$A$2:$A$1000,G$6,History_Q!$C$2:$C$1000,"net_income"))-3),History_Q!$B$2:$B$1000,"<="&(SUMIFS(History_Q!$B$2:$B$1000,History_Q!$A$2:$A$1000,G$6,History_Q!$C$2:$C$1000,"net_income")),History_Q!$E$2:$E$1000,"$m",History_Q!$G$2:$G$1000,"populated")-_xlfn.MINIFS(History_Q!$B$2:$B$1000,History_Q!$C$2:$C$1000,"net_income",History_Q!$B$2:$B$1000,">="&((SUMIFS(History_Q!$B$2:$B$1000,History_Q!$A$2:$A$1000,G$6,History_Q!$C$2:$C$1000,"net_income"))-3),History_Q!$B$2:$B$1000,"<="&(SUMIFS(History_Q!$B$2:$B$1000,History_Q!$A$2:$A$1000,G$6,History_Q!$C$2:$C$1000,"net_income")),History_Q!$E$2:$E$1000,"$m",History_Q!$G$2:$G$1000,"populated")<>3),"",SUMIFS(History_Q!$D$2:$D$1000,History_Q!$C$2:$C$1000,"net_income",History_Q!$B$2:$B$1000,">="&((SUMIFS(History_Q!$B$2:$B$1000,History_Q!$A$2:$A$1000,G$6,History_Q!$C$2:$C$1000,"net_income"))-3),History_Q!$B$2:$B$1000,"<="&(SUMIFS(History_Q!$B$2:$B$1000,History_Q!$A$2:$A$1000,G$6,History_Q!$C$2:$C$1000,"net_income")),History_Q!$E$2:$E$1000,"$m",History_Q!$G$2:$G$1000,"populated")) | H39: =IF(OR(H$6="",COUNTIFS(History_Q!$C$2:$C$1000,"net_income",History_Q!$B$2:$B$1000,">="&((SUMIFS(History_Q!$B$2:$B$1000,History_Q!$A$2:$A$1000,H$6,History_Q!$C$2:$C$1000,"net_income"))-3),History_Q!$B$2:$B$1000,"<="&(SUMIFS(History_Q!$B$2:$B$1000,History_Q!$A$2:$A$1000,H$6,History_Q!$C$2:$C$1000,"net_income")),History_Q!$E$2:$E$1000,"$m",History_Q!$G$2:$G$1000,"populated")<>4,_xlfn.MAXIFS(History_Q!$B$2:$B$1000,History_Q!$C$2:$C$1000,"net_income",History_Q!$B$2:$B$1000,">="&((SUMIFS(History_Q!$B$2:$B$1000,History_Q!$A$2:$A$1000,H$6,History_Q!$C$2:$C$1000,"net_income"))-3),History_Q!$B$2:$B$1000,"<="&(SUMIFS(History_Q!$B$2:$B$1000,History_Q!$A$2:$A$1000,H$6,History_Q!$C$2:$C$1000,"net_income")),History_Q!$E$2:$E$1000,"$m",History_Q!$G$2:$G$1000,"populated")-_xlfn.MINIFS(History_Q!$B$2:$B$1000,History_Q!$C$2:$C$1000,"net_income",History_Q!$B$2:$B$1000,">="&((SUMIFS(History_Q!$B$2:$B$1000,History_Q!$A$2:$A$1000,H$6,History_Q!$C$2:$C$1000,"net_income"))-3),History_Q!$B$2:$B$1000,"<="&(SUMIFS(History_Q!$B$2:$B$1000,History_Q!$A$2:$A$1000,H$6,History_Q!$C$2:$C$1000,"net_income")),History_Q!$E$2:$E$1000,"$m",History_Q!$G$2:$G$1000,"populated")<>3),"",SUMIFS(History_Q!$D$2:$D$1000,History_Q!$C$2:$C$1000,"net_income",History_Q!$B$2:$B$1000,">="&((SUMIFS(History_Q!$B$2:$B$1000,History_Q!$A$2:$A$1000,H$6,History_Q!$C$2:$C$1000,"net_income"))-3),History_Q!$B$2:$B$1000,"<="&(SUMIFS(History_Q!$B$2:$B$1000,History_Q!$A$2:$A$1000,H$6,History_Q!$C$2:$C$1000,"net_income")),History_Q!$E$2:$E$1000,"$m",History_Q!$G$2:$G$1000,"populated")) | I39: =IF(OR(I$6="",COUNTIFS(History_Q!$C$2:$C$1000,"net_income",History_Q!$B$2:$B$1000,">="&((SUMIFS(History_Q!$B$2:$B$1000,History_Q!$A$2:$A$1000,I$6,History_Q!$C$2:$C$1000,"net_income"))-3),History_Q!$B$2:$B$1000,"<="&(SUMIFS(History_Q!$B$2:$B$1000,History_Q!$A$2:$A$1000,I$6,History_Q!$C$2:$C$1000,"net_income")),History_Q!$E$2:$E$1000,"$m",History_Q!$G$2:$G$1000,"populated")<>4,_xlfn.MAXIFS(History_Q!$B$2:$B$1000,History_Q!$C$2:$C$1000,"net_income",History_Q!$B$2:$B$1000,">="&((SUMIFS(History_Q!$B$2:$B$1000,History_Q!$A$2:$A$1000,I$6,History_Q!$C$2:$C$1000,"net_income"))-3),History_Q!$B$2:$B$1000,"<="&(SUMIFS(History_Q!$B$2:$B$1000,History_Q!$A$2:$A$1000,I$6,History_Q!$C$2:$C$1000,"net_income")),History_Q!$E$2:$E$1000,"$m",History_Q!$G$2:$G$1000,"populated")-_xlfn.MINIFS(History_Q!$B$2:$B$1000,History_Q!$C$2:$C$1000,"net_income",History_Q!$B$2:$B$1000,">="&((SUMIFS(History_Q!$B$2:$B$1000,History_Q!$A$2:$A$1000,I$6,History_Q!$C$2:$C$1000,"net_income"))-3),History_Q!$B$2:$B$1000,"<="&(SUMIFS(History_Q!$B$2:$B$1000,History_Q!$A$2:$A$1000,I$6,History_Q!$C$2:$C$1000,"net_income")),History_Q!$E$2:$E$1000,"$m",History_Q!$G$2:$G$1000,"populated")<>3),"",SUMIFS(History_Q!$D$2:$D$1000,History_Q!$C$2:$C$1000,"net_income",History_Q!$B$2:$B$1000,">="&((SUMIFS(History_Q!$B$2:$B$1000,History_Q!$A$2:$A$1000,I$6,History_Q!$C$2:$C$1000,"net_income"))-3),History_Q!$B$2:$B$1000,"<="&(SUMIFS(History_Q!$B$2:$B$1000,History_Q!$A$2:$A$1000,I$6,History_Q!$C$2:$C$1000,"net_income")),History_Q!$E$2:$E$1000,"$m",History_Q!$G$2:$G$1000,"populated")) | ... M39: =IF(OR(M$6="",COUNTIFS(History_Q!$C$2:$C$1000,"net_income",History_Q!$B$2:$B$1000,">="&((SUMIFS(History_Q!$B$2:$B$1000,History_Q!$A$2:$A$1000,M$6,History_Q!$C$2:$C$1000,"net_income"))-3),History_Q!$B$2:$B$1000,"<="&(SUMIFS(History_Q!$B$2:$B$1000,History_Q!$A$2:$A$1000,M$6,History_Q!$C$2:$C$1000,"net_income")),History_Q!$E$2:$E$1000,"$m",History_Q!$G$2:$G$1000,"populated")<>4,_xlfn.MAXIFS(History_Q!$B$2:$B$1000,History_Q!$C$2:$C$1000,"net_income",History_Q!$B$2:$B$1000,">="&((SUMIFS(History_Q!$B$2:$B$1000,History_Q!$A$2:$A$1000,M$6,History_Q!$C$2:$C$1000,"net_income"))-3),History_Q!$B$2:$B$1000,"<="&(SUMIFS(History_Q!$B$2:$B$1000,History_Q!$A$2:$A$1000,M$6,History_Q!$C$2:$C$1000,"net_income")),History_Q!$E$2:$E$1000,"$m",History_Q!$G$2:$G$1000,"populated")-_xlfn.MINIFS(History_Q!$B$2:$B$1000,History_Q!$C$2:$C$1000,"net_income",History_Q!$B$2:$B$1000,">="&((SUMIFS(History_Q!$B$2:$B$1000,History_Q!$A$2:$A$1000,M$6,History_Q!$C$2:$C$1000,"net_income"))-3),History_Q!$B$2:$B$1000,"<="&(SUMIFS(History_Q!$B$2:$B$1000,History_Q!$A$2:$A$1000,M$6,History_Q!$C$2:$C$1000,"net_income")),History_Q!$E$2:$E$1000,"$m",History_Q!$G$2:$G$1000,"populated")<>3),"",SUMIFS(History_Q!$D$2:$D$1000,History_Q!$C$2:$C$1000,"net_income",History_Q!$B$2:$B$1000,">="&((SUMIFS(History_Q!$B$2:$B$1000,History_Q!$A$2:$A$1000,M$6,History_Q!$C$2:$C$1000,"net_income"))-3),History_Q!$B$2:$B$1000,"<="&(SUMIFS(History_Q!$B$2:$B$1000,History_Q!$A$2:$A$1000,M$6,History_Q!$C$2:$C$1000,"net_income")),History_Q!$E$2:$E$1000,"$m",History_Q!$G$2:$G$1000,"populated"))
A40: Net margin (TTM) | B40: =IF(OR(B39="",B10="",B10=0),"",B39/B10) | C40: =IF(OR(C39="",C10="",C10=0),"",C39/C10) | D40: =IF(OR(D39="",D10="",D10=0),"",D39/D10) | E40: =IF(OR(E39="",E10="",E10=0),"",E39/E10) | F40: =IF(OR(F39="",F10="",F10=0),"",F39/F10) | G40: =IF(OR(G39="",G10="",G10=0),"",G39/G10) | H40: =IF(OR(H39="",H10="",H10=0),"",H39/H10) | I40: =IF(OR(I39="",I10="",I10=0),"",I39/I10) | ... M40: =IF(OR(M39="",M10="",M10=0),"",M39/M10)
A41: Cash Flow
A42: Core cash flow
A43: CFO
A44: Capex
A45: Capex % of revenue | B45: =IF(OR(B44="",B9="",B9=0),"",B44/B9) | C45: =IF(OR(C44="",C9="",C9=0),"",C44/C9) | D45: =IF(OR(D44="",D9="",D9=0),"",D44/D9) | E45: =IF(OR(E44="",E9="",E9=0),"",E44/E9) | F45: =IF(OR(F44="",F9="",F9=0),"",F44/F9) | G45: =IF(OR(G44="",G9="",G9=0),"",G44/G9) | H45: =IF(OR(H44="",H9="",H9=0),"",H44/H9) | I45: =IF(OR(I44="",I9="",I9=0),"",I44/I9) | ... M45: =IF(OR(M44="",M9="",M9=0),"",M44/M9)
A46: Capex % of revenue (TTM) | B46: =IF(OR(B$6="",COUNTIFS(History_Q!$C$2:$C$1000,"capital_expenditures",History_Q!$B$2:$B$1000,">="&((SUMIFS(History_Q!$B$2:$B$1000,History_Q!$A$2:$A$1000,B$6,History_Q!$C$2:$C$1000,"capital_expenditures"))-3),History_Q!$B$2:$B$1000,"<="&(SUMIFS(History_Q!$B$2:$B$1000,History_Q!$A$2:$A$1000,B$6,History_Q!$C$2:$C$1000,"capital_expenditures")),History_Q!$E$2:$E$1000,"$m",History_Q!$G$2:$G$1000,"populated")<>4,COUNTIFS(History_Q!$C$2:$C$1000,"revenue",History_Q!$B$2:$B$1000,">="&((SUMIFS(History_Q!$B$2:$B$1000,History_Q!$A$2:$A$1000,B$6,History_Q!$C$2:$C$1000,"revenue"))-3),History_Q!$B$2:$B$1000,"<="&(SUMIFS(History_Q!$B$2:$B$1000,History_Q!$A$2:$A$1000,B$6,History_Q!$C$2:$C$1000,"revenue")),History_Q!$E$2:$E$1000,"$m",History_Q!$G$2:$G$1000,"populated")<>4,_xlfn.MAXIFS(History_Q!$B$2:$B$1000,History_Q!$C$2:$C$1000,"capital_expenditures",History_Q!$B$2:$B$1000,">="&((SUMIFS(History_Q!$B$2:$B$1000,History_Q!$A$2:$A$1000,B$6,History_Q!$C$2:$C$1000,"capital_expenditures"))-3),History_Q!$B$2:$B$1000,"<="&(SUMIFS(History_Q!$B$2:$B$1000,History_Q!$A$2:$A$1000,B$6,History_Q!$C$2:$C$1000,"capital_expenditures")),History_Q!$E$2:$E$1000,"$m",History_Q!$G$2:$G$1000,"populated")-_xlfn.MINIFS(History_Q!$B$2:$B$1000,History_Q!$C$2:$C$1000,"capital_expenditures",History_Q!$B$2:$B$1000,">="&((SUMIFS(History_Q!$B$2:$B$1000,History_Q!$A$2:$A$1000,B$6,History_Q!$C$2:$C$1000,"capital_expenditures"))-3),History_Q!$B$2:$B$1000,"<="&(SUMIFS(History_Q!$B$2:$B$1000,History_Q!$A$2:$A$1000,B$6,History_Q!$C$2:$C$1000,"capital_expenditures")),History_Q!$E$2:$E$1000,"$m",History_Q!$G$2:$G$1000,"populated")<>3,_xlfn.MAXIFS(History_Q!$B$2:$B$1000,History_Q!$C$2:$C$1000,"revenue",History_Q!$B$2:$B$1000,">="&((SUMIFS(History_Q!$B$2:$B$1000,History_Q!$A$2:$A$1000,B$6,History_Q!$C$2:$C$1000,"revenue"))-3),History_Q!$B$2:$B$1000,"<="&(SUMIFS(History_Q!$B$2:$B$1000,History_Q!$A$2:$A$1000,B$6,History_Q!$C$2:$C$1000,"revenue")),History_Q!$E$2:$E$1000,"$m",History_Q!$G$2:$G$1000,"populated")-_xlfn.MINIFS(History_Q!$B$2:$B$1000,History_Q!$C$2:$C$1000,"revenue",History_Q!$B$2:$B$1000,">="&((SUMIFS(History_Q!$B$2:$B$1000,History_Q!$A$2:$A$1000,B$6,History_Q!$C$2:$C$1000,"revenue"))-3),History_Q!$B$2:$B$1000,"<="&(SUMIFS(History_Q!$B$2:$B$1000,History_Q!$A$2:$A$1000,B$6,History_Q!$C$2:$C$1000,"revenue")),History_Q!$E$2:$E$1000,"$m",History_Q!$G$2:$G$1000,"populated")<>3,SUMIFS(History_Q!$D$2:$D$1000,History_Q!$C$2:$C$1000,"revenue",History_Q!$B$2:$B$1000,">="&((SUMIFS(History_Q!$B$2:$B$1000,History_Q!$A$2:$A$1000,B$6,History_Q!$C$2:$C$1000,"revenue"))-3),History_Q!$B$2:$B$1000,"<="&(SUMIFS(History_Q!$B$2:$B$1000,History_Q!$A$2:$A$1000,B$6,History_Q!$C$2:$C$1000,"revenue")),History_Q!$E$2:$E$1000,"$m",History_Q!$G$2:$G$1000,"populated")=0),"",SUMIFS(History_Q!$D$2:$D$1000,History_Q!$C$2:$C$1000,"capital_expenditures",History_Q!$B$2:$B$1000,">="&((SUMIFS(History_Q!$B$2:$B$1000,History_Q!$A$2:$A$1000,B$6,History_Q!$C$2:$C$1000,"capital_expenditures"))-3),History_Q!$B$2:$B$1000,"<="&(SUMIFS(History_Q!$B$2:$B$1000,History_Q!$A$2:$A$1000,B$6,History_Q!$C$2:$C$1000,"capital_expenditures")),History_Q!$E$2:$E$1000,"$m",History_Q!$G$2:$G$1000,"populated")/SUMIFS(History_Q!$D$2:$D$1000,History_Q!$C$2:$C$1000,"revenue",History_Q!$B$2:$B$1000,">="&((SUMIFS(History_Q!$B$2:$B$1000,History_Q!$A$2:$A$1000,B$6,History_Q!$C$2:$C$1000,"revenue"))-3),History_Q!$B$2:$B$1000,"<="&(SUMIFS(History_Q!$B$2:$B$1000,History_Q!$A$2:$A$1000,B$6,History_Q!$C$2:$C$1000,"revenue")),History_Q!$E$2:$E$1000,"$m",History_Q!$G$2:$G$1000,"populated")) | C46: =IF(OR(C$6="",COUNTIFS(History_Q!$C$2:$C$1000,"capital_expenditures",History_Q!$B$2:$B$1000,">="&((SUMIFS(History_Q!$B$2:$B$1000,History_Q!$A$2:$A$1000,C$6,History_Q!$C$2:$C$1000,"capital_expenditures"))-3),History_Q!$B$2:$B$1000,"<="&(SUMIFS(History_Q!$B$2:$B$1000,History_Q!$A$2:$A$1000,C$6,History_Q!$C$2:$C$1000,"capital_expenditures")),History_Q!$E$2:$E$1000,"$m",History_Q!$G$2:$G$1000,"populated")<>4,COUNTIFS(History_Q!$C$2:$C$1000,"revenue",History_Q!$B$2:$B$1000,">="&((SUMIFS(History_Q!$B$2:$B$1000,History_Q!$A$2:$A$1000,C$6,History_Q!$C$2:$C$1000,"revenue"))-3),History_Q!$B$2:$B$1000,"<="&(SUMIFS(History_Q!$B$2:$B$1000,History_Q!$A$2:$A$1000,C$6,History_Q!$C$2:$C$1000,"revenue")),History_Q!$E$2:$E$1000,"$m",History_Q!$G$2:$G$1000,"populated")<>4,_xlfn.MAXIFS(History_Q!$B$2:$B$1000,History_Q!$C$2:$C$1000,"capital_expenditures",History_Q!$B$2:$B$1000,">="&((SUMIFS(History_Q!$B$2:$B$1000,History_Q!$A$2:$A$1000,C$6,History_Q!$C$2:$C$1000,"capital_expenditures"))-3),History_Q!$B$2:$B$1000,"<="&(SUMIFS(History_Q!$B$2:$B$1000,History_Q!$A$2:$A$1000,C$6,History_Q!$C$2:$C$1000,"capital_expenditures")),History_Q!$E$2:$E$1000,"$m",History_Q!$G$2:$G$1000,"populated")-_xlfn.MINIFS(History_Q!$B$2:$B$1000,History_Q!$C$2:$C$1000,"capital_expenditures",History_Q!$B$2:$B$1000,">="&((SUMIFS(History_Q!$B$2:$B$1000,History_Q!$A$2:$A$1000,C$6,History_Q!$C$2:$C$1000,"capital_expenditures"))-3),History_Q!$B$2:$B$1000,"<="&(SUMIFS(History_Q!$B$2:$B$1000,History_Q!$A$2:$A$1000,C$6,History_Q!$C$2:$C$1000,"capital_expenditures")),History_Q!$E$2:$E$1000,"$m",History_Q!$G$2:$G$1000,"populated")<>3,_xlfn.MAXIFS(History_Q!$B$2:$B$1000,History_Q!$C$2:$C$1000,"revenue",History_Q!$B$2:$B$1000,">="&((SUMIFS(History_Q!$B$2:$B$1000,History_Q!$A$2:$A$1000,C$6,History_Q!$C$2:$C$1000,"revenue"))-3),History_Q!$B$2:$B$1000,"<="&(SUMIFS(History_Q!$B$2:$B$1000,History_Q!$A$2:$A$1000,C$6,History_Q!$C$2:$C$1000,"revenue")),History_Q!$E$2:$E$1000,"$m",History_Q!$G$2:$G$1000,"populated")-_xlfn.MINIFS(History_Q!$B$2:$B$1000,History_Q!$C$2:$C$1000,"revenue",History_Q!$B$2:$B$1000,">="&((SUMIFS(History_Q!$B$2:$B$1000,History_Q!$A$2:$A$1000,C$6,History_Q!$C$2:$C$1000,"revenue"))-3),History_Q!$B$2:$B$1000,"<="&(SUMIFS(History_Q!$B$2:$B$1000,History_Q!$A$2:$A$1000,C$6,History_Q!$C$2:$C$1000,"revenue")),History_Q!$E$2:$E$1000,"$m",History_Q!$G$2:$G$1000,"populated")<>3,SUMIFS(History_Q!$D$2:$D$1000,History_Q!$C$2:$C$1000,"revenue",History_Q!$B$2:$B$1000,">="&((SUMIFS(History_Q!$B$2:$B$1000,History_Q!$A$2:$A$1000,C$6,History_Q!$C$2:$C$1000,"revenue"))-3),History_Q!$B$2:$B$1000,"<="&(SUMIFS(History_Q!$B$2:$B$1000,History_Q!$A$2:$A$1000,C$6,History_Q!$C$2:$C$1000,"revenue")),History_Q!$E$2:$E$1000,"$m",History_Q!$G$2:$G$1000,"populated")=0),"",SUMIFS(History_Q!$D$2:$D$1000,History_Q!$C$2:$C$1000,"capital_expenditures",History_Q!$B$2:$B$1000,">="&((SUMIFS(History_Q!$B$2:$B$1000,History_Q!$A$2:$A$1000,C$6,History_Q!$C$2:$C$1000,"capital_expenditures"))-3),History_Q!$B$2:$B$1000,"<="&(SUMIFS(History_Q!$B$2:$B$1000,History_Q!$A$2:$A$1000,C$6,History_Q!$C$2:$C$1000,"capital_expenditures")),History_Q!$E$2:$E$1000,"$m",History_Q!$G$2:$G$1000,"populated")/SUMIFS(History_Q!$D$2:$D$1000,History_Q!$C$2:$C$1000,"revenue",History_Q!$B$2:$B$1000,">="&((SUMIFS(History_Q!$B$2:$B$1000,History_Q!$A$2:$A$1000,C$6,History_Q!$C$2:$C$1000,"revenue"))-3),History_Q!$B$2:$B$1000,"<="&(SUMIFS(History_Q!$B$2:$B$1000,History_Q!$A$2:$A$1000,C$6,History_Q!$C$2:$C$1000,"revenue")),History_Q!$E$2:$E$1000,"$m",History_Q!$G$2:$G$1000,"populated")) | D46: =IF(OR(D$6="",COUNTIFS(History_Q!$C$2:$C$1000,"capital_expenditures",History_Q!$B$2:$B$1000,">="&((SUMIFS(History_Q!$B$2:$B$1000,History_Q!$A$2:$A$1000,D$6,History_Q!$C$2:$C$1000,"capital_expenditures"))-3),History_Q!$B$2:$B$1000,"<="&(SUMIFS(History_Q!$B$2:$B$1000,History_Q!$A$2:$A$1000,D$6,History_Q!$C$2:$C$1000,"capital_expenditures")),History_Q!$E$2:$E$1000,"$m",History_Q!$G$2:$G$1000,"populated")<>4,COUNTIFS(History_Q!$C$2:$C$1000,"revenue",History_Q!$B$2:$B$1000,">="&((SUMIFS(History_Q!$B$2:$B$1000,History_Q!$A$2:$A$1000,D$6,History_Q!$C$2:$C$1000,"revenue"))-3),History_Q!$B$2:$B$1000,"<="&(SUMIFS(History_Q!$B$2:$B$1000,History_Q!$A$2:$A$1000,D$6,History_Q!$C$2:$C$1000,"revenue")),History_Q!$E$2:$E$1000,"$m",History_Q!$G$2:$G$1000,"populated")<>4,_xlfn.MAXIFS(History_Q!$B$2:$B$1000,History_Q!$C$2:$C$1000,"capital_expenditures",History_Q!$B$2:$B$1000,">="&((SUMIFS(History_Q!$B$2:$B$1000,History_Q!$A$2:$A$1000,D$6,History_Q!$C$2:$C$1000,"capital_expenditures"))-3),History_Q!$B$2:$B$1000,"<="&(SUMIFS(History_Q!$B$2:$B$1000,History_Q!$A$2:$A$1000,D$6,History_Q!$C$2:$C$1000,"capital_expenditures")),History_Q!$E$2:$E$1000,"$m",History_Q!$G$2:$G$1000,"populated")-_xlfn.MINIFS(History_Q!$B$2:$B$1000,History_Q!$C$2:$C$1000,"capital_expenditures",History_Q!$B$2:$B$1000,">="&((SUMIFS(History_Q!$B$2:$B$1000,History_Q!$A$2:$A$1000,D$6,History_Q!$C$2:$C$1000,"capital_expenditures"))-3),History_Q!$B$2:$B$1000,"<="&(SUMIFS(History_Q!$B$2:$B$1000,History_Q!$A$2:$A$1000,D$6,History_Q!$C$2:$C$1000,"capital_expenditures")),History_Q!$E$2:$E$1000,"$m",History_Q!$G$2:$G$1000,"populated")<>3,_xlfn.MAXIFS(History_Q!$B$2:$B$1000,History_Q!$C$2:$C$1000,"revenue",History_Q!$B$2:$B$1000,">="&((SUMIFS(History_Q!$B$2:$B$1000,History_Q!$A$2:$A$1000,D$6,History_Q!$C$2:$C$1000,"revenue"))-3),History_Q!$B$2:$B$1000,"<="&(SUMIFS(History_Q!$B$2:$B$1000,History_Q!$A$2:$A$1000,D$6,History_Q!$C$2:$C$1000,"revenue")),History_Q!$E$2:$E$1000,"$m",History_Q!$G$2:$G$1000,"populated")-_xlfn.MINIFS(History_Q!$B$2:$B$1000,History_Q!$C$2:$C$1000,"revenue",History_Q!$B$2:$B$1000,">="&((SUMIFS(History_Q!$B$2:$B$1000,History_Q!$A$2:$A$1000,D$6,History_Q!$C$2:$C$1000,"revenue"))-3),History_Q!$B$2:$B$1000,"<="&(SUMIFS(History_Q!$B$2:$B$1000,History_Q!$A$2:$A$1000,D$6,History_Q!$C$2:$C$1000,"revenue")),History_Q!$E$2:$E$1000,"$m",History_Q!$G$2:$G$1000,"populated")<>3,SUMIFS(History_Q!$D$2:$D$1000,History_Q!$C$2:$C$1000,"revenue",History_Q!$B$2:$B$1000,">="&((SUMIFS(History_Q!$B$2:$B$1000,History_Q!$A$2:$A$1000,D$6,History_Q!$C$2:$C$1000,"revenue"))-3),History_Q!$B$2:$B$1000,"<="&(SUMIFS(History_Q!$B$2:$B$1000,History_Q!$A$2:$A$1000,D$6,History_Q!$C$2:$C$1000,"revenue")),History_Q!$E$2:$E$1000,"$m",History_Q!$G$2:$G$1000,"populated")=0),"",SUMIFS(History_Q!$D$2:$D$1000,History_Q!$C$2:$C$1000,"capital_expenditures",History_Q!$B$2:$B$1000,">="&((SUMIFS(History_Q!$B$2:$B$1000,History_Q!$A$2:$A$1000,D$6,History_Q!$C$2:$C$1000,"capital_expenditures"))-3),History_Q!$B$2:$B$1000,"<="&(SUMIFS(History_Q!$B$2:$B$1000,History_Q!$A$2:$A$1000,D$6,History_Q!$C$2:$C$1000,"capital_expenditures")),History_Q!$E$2:$E$1000,"$m",History_Q!$G$2:$G$1000,"populated")/SUMIFS(History_Q!$D$2:$D$1000,History_Q!$C$2:$C$1000,"revenue",History_Q!$B$2:$B$1000,">="&((SUMIFS(History_Q!$B$2:$B$1000,History_Q!$A$2:$A$1000,D$6,History_Q!$C$2:$C$1000,"revenue"))-3),History_Q!$B$2:$B$1000,"<="&(SUMIFS(History_Q!$B$2:$B$1000,History_Q!$A$2:$A$1000,D$6,History_Q!$C$2:$C$1000,"revenue")),History_Q!$E$2:$E$1000,"$m",History_Q!$G$2:$G$1000,"populated")) | E46: =IF(OR(E$6="",COUNTIFS(History_Q!$C$2:$C$1000,"capital_expenditures",History_Q!$B$2:$B$1000,">="&((SUMIFS(History_Q!$B$2:$B$1000,History_Q!$A$2:$A$1000,E$6,History_Q!$C$2:$C$1000,"capital_expenditures"))-3),History_Q!$B$2:$B$1000,"<="&(SUMIFS(History_Q!$B$2:$B$1000,History_Q!$A$2:$A$1000,E$6,History_Q!$C$2:$C$1000,"capital_expenditures")),History_Q!$E$2:$E$1000,"$m",History_Q!$G$2:$G$1000,"populated")<>4,COUNTIFS(History_Q!$C$2:$C$1000,"revenue",History_Q!$B$2:$B$1000,">="&((SUMIFS(History_Q!$B$2:$B$1000,History_Q!$A$2:$A$1000,E$6,History_Q!$C$2:$C$1000,"revenue"))-3),History_Q!$B$2:$B$1000,"<="&(SUMIFS(History_Q!$B$2:$B$1000,History_Q!$A$2:$A$1000,E$6,History_Q!$C$2:$C$1000,"revenue")),History_Q!$E$2:$E$1000,"$m",History_Q!$G$2:$G$1000,"populated")<>4,_xlfn.MAXIFS(History_Q!$B$2:$B$1000,History_Q!$C$2:$C$1000,"capital_expenditures",History_Q!$B$2:$B$1000,">="&((SUMIFS(History_Q!$B$2:$B$1000,History_Q!$A$2:$A$1000,E$6,History_Q!$C$2:$C$1000,"capital_expenditures"))-3),History_Q!$B$2:$B$1000,"<="&(SUMIFS(History_Q!$B$2:$B$1000,History_Q!$A$2:$A$1000,E$6,History_Q!$C$2:$C$1000,"capital_expenditures")),History_Q!$E$2:$E$1000,"$m",History_Q!$G$2:$G$1000,"populated")-_xlfn.MINIFS(History_Q!$B$2:$B$1000,History_Q!$C$2:$C$1000,"capital_expenditures",History_Q!$B$2:$B$1000,">="&((SUMIFS(History_Q!$B$2:$B$1000,History_Q!$A$2:$A$1000,E$6,History_Q!$C$2:$C$1000,"capital_expenditures"))-3),History_Q!$B$2:$B$1000,"<="&(SUMIFS(History_Q!$B$2:$B$1000,History_Q!$A$2:$A$1000,E$6,History_Q!$C$2:$C$1000,"capital_expenditures")),History_Q!$E$2:$E$1000,"$m",History_Q!$G$2:$G$1000,"populated")<>3,_xlfn.MAXIFS(History_Q!$B$2:$B$1000,History_Q!$C$2:$C$1000,"revenue",History_Q!$B$2:$B$1000,">="&((SUMIFS(History_Q!$B$2:$B$1000,History_Q!$A$2:$A$1000,E$6,History_Q!$C$2:$C$1000,"revenue"))-3),History_Q!$B$2:$B$1000,"<="&(SUMIFS(History_Q!$B$2:$B$1000,History_Q!$A$2:$A$1000,E$6,History_Q!$C$2:$C$1000,"revenue")),History_Q!$E$2:$E$1000,"$m",History_Q!$G$2:$G$1000,"populated")-_xlfn.MINIFS(History_Q!$B$2:$B$1000,History_Q!$C$2:$C$1000,"revenue",History_Q!$B$2:$B$1000,">="&((SUMIFS(History_Q!$B$2:$B$1000,History_Q!$A$2:$A$1000,E$6,History_Q!$C$2:$C$1000,"revenue"))-3),History_Q!$B$2:$B$1000,"<="&(SUMIFS(History_Q!$B$2:$B$1000,History_Q!$A$2:$A$1000,E$6,History_Q!$C$2:$C$1000,"revenue")),History_Q!$E$2:$E$1000,"$m",History_Q!$G$2:$G$1000,"populated")<>3,SUMIFS(History_Q!$D$2:$D$1000,History_Q!$C$2:$C$1000,"revenue",History_Q!$B$2:$B$1000,">="&((SUMIFS(History_Q!$B$2:$B$1000,History_Q!$A$2:$A$1000,E$6,History_Q!$C$2:$C$1000,"revenue"))-3),History_Q!$B$2:$B$1000,"<="&(SUMIFS(History_Q!$B$2:$B$1000,History_Q!$A$2:$A$1000,E$6,History_Q!$C$2:$C$1000,"revenue")),History_Q!$E$2:$E$1000,"$m",History_Q!$G$2:$G$1000,"populated")=0),"",SUMIFS(History_Q!$D$2:$D$1000,History_Q!$C$2:$C$1000,"capital_expenditures",History_Q!$B$2:$B$1000,">="&((SUMIFS(History_Q!$B$2:$B$1000,History_Q!$A$2:$A$1000,E$6,History_Q!$C$2:$C$1000,"capital_expenditures"))-3),History_Q!$B$2:$B$1000,"<="&(SUMIFS(History_Q!$B$2:$B$1000,History_Q!$A$2:$A$1000,E$6,History_Q!$C$2:$C$1000,"capital_expenditures")),History_Q!$E$2:$E$1000,"$m",History_Q!$G$2:$G$1000,"populated")/SUMIFS(History_Q!$D$2:$D$1000,History_Q!$C$2:$C$1000,"revenue",History_Q!$B$2:$B$1000,">="&((SUMIFS(History_Q!$B$2:$B$1000,History_Q!$A$2:$A$1000,E$6,History_Q!$C$2:$C$1000,"revenue"))-3),History_Q!$B$2:$B$1000,"<="&(SUMIFS(History_Q!$B$2:$B$1000,History_Q!$A$2:$A$1000,E$6,History_Q!$C$2:$C$1000,"revenue")),History_Q!$E$2:$E$1000,"$m",History_Q!$G$2:$G$1000,"populated")) | F46: =IF(OR(F$6="",COUNTIFS(History_Q!$C$2:$C$1000,"capital_expenditures",History_Q!$B$2:$B$1000,">="&((SUMIFS(History_Q!$B$2:$B$1000,History_Q!$A$2:$A$1000,F$6,History_Q!$C$2:$C$1000,"capital_expenditures"))-3),History_Q!$B$2:$B$1000,"<="&(SUMIFS(History_Q!$B$2:$B$1000,History_Q!$A$2:$A$1000,F$6,History_Q!$C$2:$C$1000,"capital_expenditures")),History_Q!$E$2:$E$1000,"$m",History_Q!$G$2:$G$1000,"populated")<>4,COUNTIFS(History_Q!$C$2:$C$1000,"revenue",History_Q!$B$2:$B$1000,">="&((SUMIFS(History_Q!$B$2:$B$1000,History_Q!$A$2:$A$1000,F$6,History_Q!$C$2:$C$1000,"revenue"))-3),History_Q!$B$2:$B$1000,"<="&(SUMIFS(History_Q!$B$2:$B$1000,History_Q!$A$2:$A$1000,F$6,History_Q!$C$2:$C$1000,"revenue")),History_Q!$E$2:$E$1000,"$m",History_Q!$G$2:$G$1000,"populated")<>4,_xlfn.MAXIFS(History_Q!$B$2:$B$1000,History_Q!$C$2:$C$1000,"capital_expenditures",History_Q!$B$2:$B$1000,">="&((SUMIFS(History_Q!$B$2:$B$1000,History_Q!$A$2:$A$1000,F$6,History_Q!$C$2:$C$1000,"capital_expenditures"))-3),History_Q!$B$2:$B$1000,"<="&(SUMIFS(History_Q!$B$2:$B$1000,History_Q!$A$2:$A$1000,F$6,History_Q!$C$2:$C$1000,"capital_expenditures")),History_Q!$E$2:$E$1000,"$m",History_Q!$G$2:$G$1000,"populated")-_xlfn.MINIFS(History_Q!$B$2:$B$1000,History_Q!$C$2:$C$1000,"capital_expenditures",History_Q!$B$2:$B$1000,">="&((SUMIFS(History_Q!$B$2:$B$1000,History_Q!$A$2:$A$1000,F$6,History_Q!$C$2:$C$1000,"capital_expenditures"))-3),History_Q!$B$2:$B$1000,"<="&(SUMIFS(History_Q!$B$2:$B$1000,History_Q!$A$2:$A$1000,F$6,History_Q!$C$2:$C$1000,"capital_expenditures")),History_Q!$E$2:$E$1000,"$m",History_Q!$G$2:$G$1000,"populated")<>3,_xlfn.MAXIFS(History_Q!$B$2:$B$1000,History_Q!$C$2:$C$1000,"revenue",History_Q!$B$2:$B$1000,">="&((SUMIFS(History_Q!$B$2:$B$1000,History_Q!$A$2:$A$1000,F$6,History_Q!$C$2:$C$1000,"revenue"))-3),History_Q!$B$2:$B$1000,"<="&(SUMIFS(History_Q!$B$2:$B$1000,History_Q!$A$2:$A$1000,F$6,History_Q!$C$2:$C$1000,"revenue")),History_Q!$E$2:$E$1000,"$m",History_Q!$G$2:$G$1000,"populated")-_xlfn.MINIFS(History_Q!$B$2:$B$1000,History_Q!$C$2:$C$1000,"revenue",History_Q!$B$2:$B$1000,">="&((SUMIFS(History_Q!$B$2:$B$1000,History_Q!$A$2:$A$1000,F$6,History_Q!$C$2:$C$1000,"revenue"))-3),History_Q!$B$2:$B$1000,"<="&(SUMIFS(History_Q!$B$2:$B$1000,History_Q!$A$2:$A$1000,F$6,History_Q!$C$2:$C$1000,"revenue")),History_Q!$E$2:$E$1000,"$m",History_Q!$G$2:$G$1000,"populated")<>3,SUMIFS(History_Q!$D$2:$D$1000,History_Q!$C$2:$C$1000,"revenue",History_Q!$B$2:$B$1000,">="&((SUMIFS(History_Q!$B$2:$B$1000,History_Q!$A$2:$A$1000,F$6,History_Q!$C$2:$C$1000,"revenue"))-3),History_Q!$B$2:$B$1000,"<="&(SUMIFS(History_Q!$B$2:$B$1000,History_Q!$A$2:$A$1000,F$6,History_Q!$C$2:$C$1000,"revenue")),History_Q!$E$2:$E$1000,"$m",History_Q!$G$2:$G$1000,"populated")=0),"",SUMIFS(History_Q!$D$2:$D$1000,History_Q!$C$2:$C$1000,"capital_expenditures",History_Q!$B$2:$B$1000,">="&((SUMIFS(History_Q!$B$2:$B$1000,History_Q!$A$2:$A$1000,F$6,History_Q!$C$2:$C$1000,"capital_expenditures"))-3),History_Q!$B$2:$B$1000,"<="&(SUMIFS(History_Q!$B$2:$B$1000,History_Q!$A$2:$A$1000,F$6,History_Q!$C$2:$C$1000,"capital_expenditures")),History_Q!$E$2:$E$1000,"$m",History_Q!$G$2:$G$1000,"populated")/SUMIFS(History_Q!$D$2:$D$1000,History_Q!$C$2:$C$1000,"revenue",History_Q!$B$2:$B$1000,">="&((SUMIFS(History_Q!$B$2:$B$1000,History_Q!$A$2:$A$1000,F$6,History_Q!$C$2:$C$1000,"revenue"))-3),History_Q!$B$2:$B$1000,"<="&(SUMIFS(History_Q!$B$2:$B$1000,History_Q!$A$2:$A$1000,F$6,History_Q!$C$2:$C$1000,"revenue")),History_Q!$E$2:$E$1000,"$m",History_Q!$G$2:$G$1000,"populated")) | G46: =IF(OR(G$6="",COUNTIFS(History_Q!$C$2:$C$1000,"capital_expenditures",History_Q!$B$2:$B$1000,">="&((SUMIFS(History_Q!$B$2:$B$1000,History_Q!$A$2:$A$1000,G$6,History_Q!$C$2:$C$1000,"capital_expenditures"))-3),History_Q!$B$2:$B$1000,"<="&(SUMIFS(History_Q!$B$2:$B$1000,History_Q!$A$2:$A$1000,G$6,History_Q!$C$2:$C$1000,"capital_expenditures")),History_Q!$E$2:$E$1000,"$m",History_Q!$G$2:$G$1000,"populated")<>4,COUNTIFS(History_Q!$C$2:$C$1000,"revenue",History_Q!$B$2:$B$1000,">="&((SUMIFS(History_Q!$B$2:$B$1000,History_Q!$A$2:$A$1000,G$6,History_Q!$C$2:$C$1000,"revenue"))-3),History_Q!$B$2:$B$1000,"<="&(SUMIFS(History_Q!$B$2:$B$1000,History_Q!$A$2:$A$1000,G$6,History_Q!$C$2:$C$1000,"revenue")),History_Q!$E$2:$E$1000,"$m",History_Q!$G$2:$G$1000,"populated")<>4,_xlfn.MAXIFS(History_Q!$B$2:$B$1000,History_Q!$C$2:$C$1000,"capital_expenditures",History_Q!$B$2:$B$1000,">="&((SUMIFS(History_Q!$B$2:$B$1000,History_Q!$A$2:$A$1000,G$6,History_Q!$C$2:$C$1000,"capital_expenditures"))-3),History_Q!$B$2:$B$1000,"<="&(SUMIFS(History_Q!$B$2:$B$1000,History_Q!$A$2:$A$1000,G$6,History_Q!$C$2:$C$1000,"capital_expenditures")),History_Q!$E$2:$E$1000,"$m",History_Q!$G$2:$G$1000,"populated")-_xlfn.MINIFS(History_Q!$B$2:$B$1000,History_Q!$C$2:$C$1000,"capital_expenditures",History_Q!$B$2:$B$1000,">="&((SUMIFS(History_Q!$B$2:$B$1000,History_Q!$A$2:$A$1000,G$6,History_Q!$C$2:$C$1000,"capital_expenditures"))-3),History_Q!$B$2:$B$1000,"<="&(SUMIFS(History_Q!$B$2:$B$1000,History_Q!$A$2:$A$1000,G$6,History_Q!$C$2:$C$1000,"capital_expenditures")),History_Q!$E$2:$E$1000,"$m",History_Q!$G$2:$G$1000,"populated")<>3,_xlfn.MAXIFS(History_Q!$B$2:$B$1000,History_Q!$C$2:$C$1000,"revenue",History_Q!$B$2:$B$1000,">="&((SUMIFS(History_Q!$B$2:$B$1000,History_Q!$A$2:$A$1000,G$6,History_Q!$C$2:$C$1000,"revenue"))-3),History_Q!$B$2:$B$1000,"<="&(SUMIFS(History_Q!$B$2:$B$1000,History_Q!$A$2:$A$1000,G$6,History_Q!$C$2:$C$1000,"revenue")),History_Q!$E$2:$E$1000,"$m",History_Q!$G$2:$G$1000,"populated")-_xlfn.MINIFS(History_Q!$B$2:$B$1000,History_Q!$C$2:$C$1000,"revenue",History_Q!$B$2:$B$1000,">="&((SUMIFS(History_Q!$B$2:$B$1000,History_Q!$A$2:$A$1000,G$6,History_Q!$C$2:$C$1000,"revenue"))-3),History_Q!$B$2:$B$1000,"<="&(SUMIFS(History_Q!$B$2:$B$1000,History_Q!$A$2:$A$1000,G$6,History_Q!$C$2:$C$1000,"revenue")),History_Q!$E$2:$E$1000,"$m",History_Q!$G$2:$G$1000,"populated")<>3,SUMIFS(History_Q!$D$2:$D$1000,History_Q!$C$2:$C$1000,"revenue",History_Q!$B$2:$B$1000,">="&((SUMIFS(History_Q!$B$2:$B$1000,History_Q!$A$2:$A$1000,G$6,History_Q!$C$2:$C$1000,"revenue"))-3),History_Q!$B$2:$B$1000,"<="&(SUMIFS(History_Q!$B$2:$B$1000,History_Q!$A$2:$A$1000,G$6,History_Q!$C$2:$C$1000,"revenue")),History_Q!$E$2:$E$1000,"$m",History_Q!$G$2:$G$1000,"populated")=0),"",SUMIFS(History_Q!$D$2:$D$1000,History_Q!$C$2:$C$1000,"capital_expenditures",History_Q!$B$2:$B$1000,">="&((SUMIFS(History_Q!$B$2:$B$1000,History_Q!$A$2:$A$1000,G$6,History_Q!$C$2:$C$1000,"capital_expenditures"))-3),History_Q!$B$2:$B$1000,"<="&(SUMIFS(History_Q!$B$2:$B$1000,History_Q!$A$2:$A$1000,G$6,History_Q!$C$2:$C$1000,"capital_expenditures")),History_Q!$E$2:$E$1000,"$m",History_Q!$G$2:$G$1000,"populated")/SUMIFS(History_Q!$D$2:$D$1000,History_Q!$C$2:$C$1000,"revenue",History_Q!$B$2:$B$1000,">="&((SUMIFS(History_Q!$B$2:$B$1000,History_Q!$A$2:$A$1000,G$6,History_Q!$C$2:$C$1000,"revenue"))-3),History_Q!$B$2:$B$1000,"<="&(SUMIFS(History_Q!$B$2:$B$1000,History_Q!$A$2:$A$1000,G$6,History_Q!$C$2:$C$1000,"revenue")),History_Q!$E$2:$E$1000,"$m",History_Q!$G$2:$G$1000,"populated")) | H46: =IF(OR(H$6="",COUNTIFS(History_Q!$C$2:$C$1000,"capital_expenditures",History_Q!$B$2:$B$1000,">="&((SUMIFS(History_Q!$B$2:$B$1000,History_Q!$A$2:$A$1000,H$6,History_Q!$C$2:$C$1000,"capital_expenditures"))-3),History_Q!$B$2:$B$1000,"<="&(SUMIFS(History_Q!$B$2:$B$1000,History_Q!$A$2:$A$1000,H$6,History_Q!$C$2:$C$1000,"capital_expenditures")),History_Q!$E$2:$E$1000,"$m",History_Q!$G$2:$G$1000,"populated")<>4,COUNTIFS(History_Q!$C$2:$C$1000,"revenue",History_Q!$B$2:$B$1000,">="&((SUMIFS(History_Q!$B$2:$B$1000,History_Q!$A$2:$A$1000,H$6,History_Q!$C$2:$C$1000,"revenue"))-3),History_Q!$B$2:$B$1000,"<="&(SUMIFS(History_Q!$B$2:$B$1000,History_Q!$A$2:$A$1000,H$6,History_Q!$C$2:$C$1000,"revenue")),History_Q!$E$2:$E$1000,"$m",History_Q!$G$2:$G$1000,"populated")<>4,_xlfn.MAXIFS(History_Q!$B$2:$B$1000,History_Q!$C$2:$C$1000,"capital_expenditures",History_Q!$B$2:$B$1000,">="&((SUMIFS(History_Q!$B$2:$B$1000,History_Q!$A$2:$A$1000,H$6,History_Q!$C$2:$C$1000,"capital_expenditures"))-3),History_Q!$B$2:$B$1000,"<="&(SUMIFS(History_Q!$B$2:$B$1000,History_Q!$A$2:$A$1000,H$6,History_Q!$C$2:$C$1000,"capital_expenditures")),History_Q!$E$2:$E$1000,"$m",History_Q!$G$2:$G$1000,"populated")-_xlfn.MINIFS(History_Q!$B$2:$B$1000,History_Q!$C$2:$C$1000,"capital_expenditures",History_Q!$B$2:$B$1000,">="&((SUMIFS(History_Q!$B$2:$B$1000,History_Q!$A$2:$A$1000,H$6,History_Q!$C$2:$C$1000,"capital_expenditures"))-3),History_Q!$B$2:$B$1000,"<="&(SUMIFS(History_Q!$B$2:$B$1000,History_Q!$A$2:$A$1000,H$6,History_Q!$C$2:$C$1000,"capital_expenditures")),History_Q!$E$2:$E$1000,"$m",History_Q!$G$2:$G$1000,"populated")<>3,_xlfn.MAXIFS(History_Q!$B$2:$B$1000,History_Q!$C$2:$C$1000,"revenue",History_Q!$B$2:$B$1000,">="&((SUMIFS(History_Q!$B$2:$B$1000,History_Q!$A$2:$A$1000,H$6,History_Q!$C$2:$C$1000,"revenue"))-3),History_Q!$B$2:$B$1000,"<="&(SUMIFS(History_Q!$B$2:$B$1000,History_Q!$A$2:$A$1000,H$6,History_Q!$C$2:$C$1000,"revenue")),History_Q!$E$2:$E$1000,"$m",History_Q!$G$2:$G$1000,"populated")-_xlfn.MINIFS(History_Q!$B$2:$B$1000,History_Q!$C$2:$C$1000,"revenue",History_Q!$B$2:$B$1000,">="&((SUMIFS(History_Q!$B$2:$B$1000,History_Q!$A$2:$A$1000,H$6,History_Q!$C$2:$C$1000,"revenue"))-3),History_Q!$B$2:$B$1000,"<="&(SUMIFS(History_Q!$B$2:$B$1000,History_Q!$A$2:$A$1000,H$6,History_Q!$C$2:$C$1000,"revenue")),History_Q!$E$2:$E$1000,"$m",History_Q!$G$2:$G$1000,"populated")<>3,SUMIFS(History_Q!$D$2:$D$1000,History_Q!$C$2:$C$1000,"revenue",History_Q!$B$2:$B$1000,">="&((SUMIFS(History_Q!$B$2:$B$1000,History_Q!$A$2:$A$1000,H$6,History_Q!$C$2:$C$1000,"revenue"))-3),History_Q!$B$2:$B$1000,"<="&(SUMIFS(History_Q!$B$2:$B$1000,History_Q!$A$2:$A$1000,H$6,History_Q!$C$2:$C$1000,"revenue")),History_Q!$E$2:$E$1000,"$m",History_Q!$G$2:$G$1000,"populated")=0),"",SUMIFS(History_Q!$D$2:$D$1000,History_Q!$C$2:$C$1000,"capital_expenditures",History_Q!$B$2:$B$1000,">="&((SUMIFS(History_Q!$B$2:$B$1000,History_Q!$A$2:$A$1000,H$6,History_Q!$C$2:$C$1000,"capital_expenditures"))-3),History_Q!$B$2:$B$1000,"<="&(SUMIFS(History_Q!$B$2:$B$1000,History_Q!$A$2:$A$1000,H$6,History_Q!$C$2:$C$1000,"capital_expenditures")),History_Q!$E$2:$E$1000,"$m",History_Q!$G$2:$G$1000,"populated")/SUMIFS(History_Q!$D$2:$D$1000,History_Q!$C$2:$C$1000,"revenue",History_Q!$B$2:$B$1000,">="&((SUMIFS(History_Q!$B$2:$B$1000,History_Q!$A$2:$A$1000,H$6,History_Q!$C$2:$C$1000,"revenue"))-3),History_Q!$B$2:$B$1000,"<="&(SUMIFS(History_Q!$B$2:$B$1000,History_Q!$A$2:$A$1000,H$6,History_Q!$C$2:$C$1000,"revenue")),History_Q!$E$2:$E$1000,"$m",History_Q!$G$2:$G$1000,"populated")) | I46: =IF(OR(I$6="",COUNTIFS(History_Q!$C$2:$C$1000,"capital_expenditures",History_Q!$B$2:$B$1000,">="&((SUMIFS(History_Q!$B$2:$B$1000,History_Q!$A$2:$A$1000,I$6,History_Q!$C$2:$C$1000,"capital_expenditures"))-3),History_Q!$B$2:$B$1000,"<="&(SUMIFS(History_Q!$B$2:$B$1000,History_Q!$A$2:$A$1000,I$6,History_Q!$C$2:$C$1000,"capital_expenditures")),History_Q!$E$2:$E$1000,"$m",History_Q!$G$2:$G$1000,"populated")<>4,COUNTIFS(History_Q!$C$2:$C$1000,"revenue",History_Q!$B$2:$B$1000,">="&((SUMIFS(History_Q!$B$2:$B$1000,History_Q!$A$2:$A$1000,I$6,History_Q!$C$2:$C$1000,"revenue"))-3),History_Q!$B$2:$B$1000,"<="&(SUMIFS(History_Q!$B$2:$B$1000,History_Q!$A$2:$A$1000,I$6,History_Q!$C$2:$C$1000,"revenue")),History_Q!$E$2:$E$1000,"$m",History_Q!$G$2:$G$1000,"populated")<>4,_xlfn.MAXIFS(History_Q!$B$2:$B$1000,History_Q!$C$2:$C$1000,"capital_expenditures",History_Q!$B$2:$B$1000,">="&((SUMIFS(History_Q!$B$2:$B$1000,History_Q!$A$2:$A$1000,I$6,History_Q!$C$2:$C$1000,"capital_expenditures"))-3),History_Q!$B$2:$B$1000,"<="&(SUMIFS(History_Q!$B$2:$B$1000,History_Q!$A$2:$A$1000,I$6,History_Q!$C$2:$C$1000,"capital_expenditures")),History_Q!$E$2:$E$1000,"$m",History_Q!$G$2:$G$1000,"populated")-_xlfn.MINIFS(History_Q!$B$2:$B$1000,History_Q!$C$2:$C$1000,"capital_expenditures",History_Q!$B$2:$B$1000,">="&((SUMIFS(History_Q!$B$2:$B$1000,History_Q!$A$2:$A$1000,I$6,History_Q!$C$2:$C$1000,"capital_expenditures"))-3),History_Q!$B$2:$B$1000,"<="&(SUMIFS(History_Q!$B$2:$B$1000,History_Q!$A$2:$A$1000,I$6,History_Q!$C$2:$C$1000,"capital_expenditures")),History_Q!$E$2:$E$1000,"$m",History_Q!$G$2:$G$1000,"populated")<>3,_xlfn.MAXIFS(History_Q!$B$2:$B$1000,History_Q!$C$2:$C$1000,"revenue",History_Q!$B$2:$B$1000,">="&((SUMIFS(History_Q!$B$2:$B$1000,History_Q!$A$2:$A$1000,I$6,History_Q!$C$2:$C$1000,"revenue"))-3),History_Q!$B$2:$B$1000,"<="&(SUMIFS(History_Q!$B$2:$B$1000,History_Q!$A$2:$A$1000,I$6,History_Q!$C$2:$C$1000,"revenue")),History_Q!$E$2:$E$1000,"$m",History_Q!$G$2:$G$1000,"populated")-_xlfn.MINIFS(History_Q!$B$2:$B$1000,History_Q!$C$2:$C$1000,"revenue",History_Q!$B$2:$B$1000,">="&((SUMIFS(History_Q!$B$2:$B$1000,History_Q!$A$2:$A$1000,I$6,History_Q!$C$2:$C$1000,"revenue"))-3),History_Q!$B$2:$B$1000,"<="&(SUMIFS(History_Q!$B$2:$B$1000,History_Q!$A$2:$A$1000,I$6,History_Q!$C$2:$C$1000,"revenue")),History_Q!$E$2:$E$1000,"$m",History_Q!$G$2:$G$1000,"populated")<>3,SUMIFS(History_Q!$D$2:$D$1000,History_Q!$C$2:$C$1000,"revenue",History_Q!$B$2:$B$1000,">="&((SUMIFS(History_Q!$B$2:$B$1000,History_Q!$A$2:$A$1000,I$6,History_Q!$C$2:$C$1000,"revenue"))-3),History_Q!$B$2:$B$1000,"<="&(SUMIFS(History_Q!$B$2:$B$1000,History_Q!$A$2:$A$1000,I$6,History_Q!$C$2:$C$1000,"revenue")),History_Q!$E$2:$E$1000,"$m",History_Q!$G$2:$G$1000,"populated")=0),"",SUMIFS(History_Q!$D$2:$D$1000,History_Q!$C$2:$C$1000,"capital_expenditures",History_Q!$B$2:$B$1000,">="&((SUMIFS(History_Q!$B$2:$B$1000,History_Q!$A$2:$A$1000,I$6,History_Q!$C$2:$C$1000,"capital_expenditures"))-3),History_Q!$B$2:$B$1000,"<="&(SUMIFS(History_Q!$B$2:$B$1000,History_Q!$A$2:$A$1000,I$6,History_Q!$C$2:$C$1000,"capital_expenditures")),History_Q!$E$2:$E$1000,"$m",History_Q!$G$2:$G$1000,"populated")/SUMIFS(History_Q!$D$2:$D$1000,History_Q!$C$2:$C$1000,"revenue",History_Q!$B$2:$B$1000,">="&((SUMIFS(History_Q!$B$2:$B$1000,History_Q!$A$2:$A$1000,I$6,History_Q!$C$2:$C$1000,"revenue"))-3),History_Q!$B$2:$B$1000,"<="&(SUMIFS(History_Q!$B$2:$B$1000,History_Q!$A$2:$A$1000,I$6,History_Q!$C$2:$C$1000,"revenue")),History_Q!$E$2:$E$1000,"$m",History_Q!$G$2:$G$1000,"populated")) | ... M46: =IF(OR(M$6="",COUNTIFS(History_Q!$C$2:$C$1000,"capital_expenditures",History_Q!$B$2:$B$1000,">="&((SUMIFS(History_Q!$B$2:$B$1000,History_Q!$A$2:$A$1000,M$6,History_Q!$C$2:$C$1000,"capital_expenditures"))-3),History_Q!$B$2:$B$1000,"<="&(SUMIFS(History_Q!$B$2:$B$1000,History_Q!$A$2:$A$1000,M$6,History_Q!$C$2:$C$1000,"capital_expenditures")),History_Q!$E$2:$E$1000,"$m",History_Q!$G$2:$G$1000,"populated")<>4,COUNTIFS(History_Q!$C$2:$C$1000,"revenue",History_Q!$B$2:$B$1000,">="&((SUMIFS(History_Q!$B$2:$B$1000,History_Q!$A$2:$A$1000,M$6,History_Q!$C$2:$C$1000,"revenue"))-3),History_Q!$B$2:$B$1000,"<="&(SUMIFS(History_Q!$B$2:$B$1000,History_Q!$A$2:$A$1000,M$6,History_Q!$C$2:$C$1000,"revenue")),History_Q!$E$2:$E$1000,"$m",History_Q!$G$2:$G$1000,"populated")<>4,_xlfn.MAXIFS(History_Q!$B$2:$B$1000,History_Q!$C$2:$C$1000,"capital_expenditures",History_Q!$B$2:$B$1000,">="&((SUMIFS(History_Q!$B$2:$B$1000,History_Q!$A$2:$A$1000,M$6,History_Q!$C$2:$C$1000,"capital_expenditures"))-3),History_Q!$B$2:$B$1000,"<="&(SUMIFS(History_Q!$B$2:$B$1000,History_Q!$A$2:$A$1000,M$6,History_Q!$C$2:$C$1000,"capital_expenditures")),History_Q!$E$2:$E$1000,"$m",History_Q!$G$2:$G$1000,"populated")-_xlfn.MINIFS(History_Q!$B$2:$B$1000,History_Q!$C$2:$C$1000,"capital_expenditures",History_Q!$B$2:$B$1000,">="&((SUMIFS(History_Q!$B$2:$B$1000,History_Q!$A$2:$A$1000,M$6,History_Q!$C$2:$C$1000,"capital_expenditures"))-3),History_Q!$B$2:$B$1000,"<="&(SUMIFS(History_Q!$B$2:$B$1000,History_Q!$A$2:$A$1000,M$6,History_Q!$C$2:$C$1000,"capital_expenditures")),History_Q!$E$2:$E$1000,"$m",History_Q!$G$2:$G$1000,"populated")<>3,_xlfn.MAXIFS(History_Q!$B$2:$B$1000,History_Q!$C$2:$C$1000,"revenue",History_Q!$B$2:$B$1000,">="&((SUMIFS(History_Q!$B$2:$B$1000,History_Q!$A$2:$A$1000,M$6,History_Q!$C$2:$C$1000,"revenue"))-3),History_Q!$B$2:$B$1000,"<="&(SUMIFS(History_Q!$B$2:$B$1000,History_Q!$A$2:$A$1000,M$6,History_Q!$C$2:$C$1000,"revenue")),History_Q!$E$2:$E$1000,"$m",History_Q!$G$2:$G$1000,"populated")-_xlfn.MINIFS(History_Q!$B$2:$B$1000,History_Q!$C$2:$C$1000,"revenue",History_Q!$B$2:$B$1000,">="&((SUMIFS(History_Q!$B$2:$B$1000,History_Q!$A$2:$A$1000,M$6,History_Q!$C$2:$C$1000,"revenue"))-3),History_Q!$B$2:$B$1000,"<="&(SUMIFS(History_Q!$B$2:$B$1000,History_Q!$A$2:$A$1000,M$6,History_Q!$C$2:$C$1000,"revenue")),History_Q!$E$2:$E$1000,"$m",History_Q!$G$2:$G$1000,"populated")<>3,SUMIFS(History_Q!$D$2:$D$1000,History_Q!$C$2:$C$1000,"revenue",History_Q!$B$2:$B$1000,">="&((SUMIFS(History_Q!$B$2:$B$1000,History_Q!$A$2:$A$1000,M$6,History_Q!$C$2:$C$1000,"revenue"))-3),History_Q!$B$2:$B$1000,"<="&(SUMIFS(History_Q!$B$2:$B$1000,History_Q!$A$2:$A$1000,M$6,History_Q!$C$2:$C$1000,"revenue")),History_Q!$E$2:$E$1000,"$m",History_Q!$G$2:$G$1000,"populated")=0),"",SUMIFS(History_Q!$D$2:$D$1000,History_Q!$C$2:$C$1000,"capital_expenditures",History_Q!$B$2:$B$1000,">="&((SUMIFS(History_Q!$B$2:$B$1000,History_Q!$A$2:$A$1000,M$6,History_Q!$C$2:$C$1000,"capital_expenditures"))-3),History_Q!$B$2:$B$1000,"<="&(SUMIFS(History_Q!$B$2:$B$1000,History_Q!$A$2:$A$1000,M$6,History_Q!$C$2:$C$1000,"capital_expenditures")),History_Q!$E$2:$E$1000,"$m",History_Q!$G$2:$G$1000,"populated")/SUMIFS(History_Q!$D$2:$D$1000,History_Q!$C$2:$C$1000,"revenue",History_Q!$B$2:$B$1000,">="&((SUMIFS(History_Q!$B$2:$B$1000,History_Q!$A$2:$A$1000,M$6,History_Q!$C$2:$C$1000,"revenue"))-3),History_Q!$B$2:$B$1000,"<="&(SUMIFS(History_Q!$B$2:$B$1000,History_Q!$A$2:$A$1000,M$6,History_Q!$C$2:$C$1000,"revenue")),History_Q!$E$2:$E$1000,"$m",History_Q!$G$2:$G$1000,"populated"))
A47: FCF (CFO - Capex) | B47: =IF(OR(B43="",B44=""),"",B43-B44) | C47: =IF(OR(C43="",C44=""),"",C43-C44) | D47: =IF(OR(D43="",D44=""),"",D43-D44) | E47: =IF(OR(E43="",E44=""),"",E43-E44) | F47: =IF(OR(F43="",F44=""),"",F43-F44) | G47: =IF(OR(G43="",G44=""),"",G43-G44) | H47: =IF(OR(H43="",H44=""),"",H43-H44) | I47: =IF(OR(I43="",I44=""),"",I43-I44) | ... M47: =IF(OR(M43="",M44=""),"",M43-M44)
